Workbook

Sheet Inicio
B2: 📊 MODELO DE SEGUIMIENTO · PLANEACIÓN ESTRATÉGICA 2026–2030
B3: Arquitectura: 1 hoja por indicador + Tablero Principal consolidado · Horizonte: enero 2026 – diciembre 2030
B5: 🗂️ ESTRUCTURA DEL ARCHIVO
B6: ● | C6: Inicio | D6: Esta hoja: portada e instrucciones.
B7: ● | C7: Parámetros | D7: Catálogo de responsables por indicador (editable) y referencias mensuales IPC/IBR.
B8: ● | C8: Tablero Principal | D8: Vista consolidada de los 25 indicadores. Recoge todos los meses y muestra metas + % cumplimiento por cada año.
B9: ● | C9: IND-01 ... IND-25 | D9: Una hoja por indicador con su captura mensual y cálculo específico.
B11: 🚀 FLUJO DE TRABAJO MENSUAL
B12: 1. Asigne responsables en la hoja Parámetros (catálogo editable).
B13: 2. Para cada indicador, abra su hoja (IND-XX) y registre las variables del mes en las celdas azules.
B14: 3. El resultado mensual, % de cumplimiento, semáforo y avance acumulado se calculan automáticamente.
B15: 4. El Tablero Principal consolida los 25 indicadores en una sola vista ejecutiva.
B16: 5. Las metas anuales son editables en cada hoja. Las marcadas como 'Por definir' deben completarse.
B17: 6. Los responsables se asignan en Parámetros y se propagan a todo el modelo.
B19: 🚦 SEMÁFORO DE CUMPLIMIENTO
B20: ● | C20: 🟢 En meta (Cumple) | D20: ≥ 95%
B21: ● | C21: 🟡 Atención (En riesgo) | D21: 80% – 94,9%
B22: ● | C22: 🔴 Crítico — revisar | D22: < 80%
B23: ● | C23: ⚪ Pendiente | D23: Sin dato / sin meta
B25: 📋 ÍNDICE DE INDICADORES
B26: Código | C26: Perspectiva | D26: Objetivo Específico | E26: Indicador | F26: Frecuencia
B27: IND-01 | C27: 💰 Financiera | D27: Aumento de ingresos | E27: Crecimiento de cartera en líneas de mayor rendimiento | F27: Mensual
B28: IND-02 | C28: 💰 Financiera | D28: Aumento de ingresos | E28: Crecimiento de ingresos operativos | F28: Mensual
B29: IND-03 | C29: 💰 Financiera | D29: Aumento de ingresos | E29: Crecimiento de ingresos por comisiones | F29: Mensual
B30: IND-04 | C30: 💰 Financiera | D30: Aumento de ingresos | E30: Rentabilidad Fondo de Liquidez | F30: Mensual
B31: IND-05 | C31: 💰 Financiera | D31: Reducción de mora | E31: Índice de mora | F31: Mensual
B32: IND-06 | C32: 💰 Financiera | D32: Reducción de mora | E32: Tasa de recuperación | F32: Mensual
B33: IND-07 | C33: 💰 Financiera | D33: Reducción de mora | E33: Tasa de normalización de cartera | F33: Mensual
B34: IND-08 | C34: 💰 Financiera | D34: Crecimiento y remuneración de depósitos | E34: Tasa de crecimiento de ahorros | F34: Mensual
B35: IND-09 | C35: 💰 Financiera | D35: Crecimiento y remuneración de depósitos | E35: Rentabilidad real de los depósitos | F35: Mensual
B36: IND-10 | C36: 💰 Financiera | D36: Rentabilidad y fortalecimiento patrimonial | E36: Suficiencia del Margen | F36: Mensual
B37: IND-11 | C37: 💰 Financiera | D37: Rentabilidad y fortalecimiento patrimonial | E37: Cumplimiento de pago de aportes sociales | F37: Mensual
... B51: IND-25 | C51: 🎓 Aprendizaje | D51: Formación y desarrollo del personal | E51: Clima organizacional y compromiso del personal | F51: Anual

Sheet Tablero Principal
B2: 📊 TABLERO PRINCIPAL DE INDICADORES · PLANEACIÓN ESTRATÉGICA 2026–2030
B3: Vista consolidada · Todos los indicadores · Todos los meses (Ene-2026 → Dic-2030) · Metas y % cumplimiento por año
B5: FICHA DEL INDICADOR | J5: 🎯 METAS ANUALES | O5: SÁBANA MENSUAL · 2026 | AA5: SÁBANA MENSUAL · 2027 | AM5: SÁBANA MENSUAL · 2028 | AY5: SÁBANA MENSUAL · 2029 | BK5: SÁBANA MENSUAL · 2030 | BW5: ✅ % CUMPLIMIENTO ANUAL | CB5: ESTADO
B6: Objetivo Específico | C6: Indicador | D6: Fórmula | E6: Descripción | F6: Unidad | G6: Tendencia | H6: Frecuencia | I6: Responsable | J6: 2026 | K6: 2027 | L6: 2028 | M6: 2029 | N6: 2030 | O6: Ene | P6: Feb | Q6: Mar | R6: Abr | S6: May | T6: Jun | U6: Jul | V6: Ago | W6: Sep | X6: Oct | Y6: Nov | Z6: Dic | AA6: Ene | AB6: Feb | AC6: Mar | AD6: Abr | AE6: May | AF6: Jun | AG6: Jul | AH6: Ago | AI6: Sep | AJ6: Oct | AK6: Nov | AL6: Dic | AM6: Ene | AN6: Feb | AO6: Mar | AP6: Abr | AQ6: May | AR6: Jun | AS6: Jul | AT6: Ago | AU6: Sep | AV6: Oct | AW6: Nov | AX6: Dic | AY6: Ene | AZ6: Feb | BA6: Mar | BB6: Abr | BC6: May | BD6: Jun | BE6: Jul | BF6: Ago | BG6: Sep | BH6: Oct | BI6: Nov | BJ6: Dic | BK6: Ene | BL6: Feb | BM6: Mar | BN6: Abr | BO6: May | BP6: Jun | BQ6: Jul | BR6: Ago | BS6: Sep | BT6: Oct | BU6: Nov | BV6: Dic | BW6: 2026 | BX6: 2027 | BY6: 2028 | BZ6: 2029 | CA6: 2030 | CB6: Semáforo
B7: 💰 PERSPECTIVA FINANCIERA
B8: Aumento de ingresos | C8: Crecimiento de cartera en líneas de mayor rendimiento | D8: Saldo de cartera de líneas de mayor rendimiento ÷ Saldo total de cartera | E8: Mide la participación de las líneas de crédito con mayor tasa efectiva y contribución al margen financiero. Por el momento, Rotativo y Tarjeta de Crédito. | F8: % | G8: Crecer | H8: Mensual | I8: =VLOOKUP("IND-01",Parámetros!$B$6:$F$30,5,FALSE()) -> Gerencia Financiera | J8: ='IND-01'!C14 -> 0.08 | K8: ='IND-01'!C15 -> 0.1 | L8: ='IND-01'!C16 -> 0.12 | M8: ='IND-01'!C17 -> 0.14 | N8: ='IND-01'!C18 -> 0.16 | O8: =IFERROR(IF('IND-01'!G23="","",'IND-01'!G23),"") -> 0.08 | P8: =IFERROR(IF('IND-01'!G24="","",'IND-01'!G24),"") -> 0.08 | Q8: =IFERROR(IF('IND-01'!G25="","",'IND-01'!G25),"") -> 0.08 | R8: =IFERROR(IF('IND-01'!G26="","",'IND-01'!G26),"") -> 0.08 | S8: =IFERROR(IF('IND-01'!G27="","",'IND-01'!G27),"") -> 0.08 | T8: =IFERROR(IF('IND-01'!G28="","",'IND-01'!G28),"") -> 0.08 | U8: =IFERROR(IF('IND-01'!G29="","",'IND-01'!G29),"") -> 0.08 | V8: =IFERROR(IF('IND-01'!G30="","",'IND-01'!G30),"") -> 0.08 | W8: =IFERROR(IF('IND-01'!G31="","",'IND-01'!G31),"") -> 0.08 | X8: =IFERROR(IF('IND-01'!G32="","",'IND-01'!G32),"") -> 0.08 | Y8: =IFERROR(IF('IND-01'!G33="","",'IND-01'!G33),"") -> 0.08 | Z8: =IFERROR(IF('IND-01'!G34="","",'IND-01'!G34),"") -> 0.08 | AA8: =IFERROR(IF('IND-01'!G35="","",'IND-01'!G35),"") -> 0.09 | AB8: =IFERROR(IF('IND-01'!G36="","",'IND-01'!G36),"") -> 0.091 | AC8: =IFERROR(IF('IND-01'!G37="","",'IND-01'!G37),"") -> 0.092 | AD8: =IFERROR(IF('IND-01'!G38="","",'IND-01'!G38),"") -> 0.093 | AE8: =IFERROR(IF('IND-01'!G39="","",'IND-01'!G39),"") -> 0.094 | AF8: =IFERROR(IF('IND-01'!G40="","",'IND-01'!G40),"") -> 0.095 | AG8: =IFERROR(IF('IND-01'!G41="","",'IND-01'!G41),"") | AH8: =IFERROR(IF('IND-01'!G42="","",'IND-01'!G42),"") | AI8: =IFERROR(IF('IND-01'!G43="","",'IND-01'!G43),"") | AJ8: =IFERROR(IF('IND-01'!G44="","",'IND-01'!G44),"") | AK8: =IFERROR(IF('IND-01'!G45="","",'IND-01'!G45),"") | AL8: =IFERROR(IF('IND-01'!G46="","",'IND-01'!G46),"") | AM8: =IFERROR(IF('IND-01'!G47="","",'IND-01'!G47),"") | AN8: =IFERROR(IF('IND-01'!G48="","",'IND-01'!G48),"") | AO8: =IFERROR(IF('IND-01'!G49="","",'IND-01'!G49),"") | AP8: =IFERROR(IF('IND-01'!G50="","",'IND-01'!G50),"") | AQ8: =IFERROR(IF('IND-01'!G51="","",'IND-01'!G51),"") | AR8: =IFERROR(IF('IND-01'!G52="","",'IND-01'!G52),"") | AS8: =IFERROR(IF('IND-01'!G53="","",'IND-01'!G53),"") | AT8: =IFERROR(IF('IND-01'!G54="","",'IND-01'!G54),"") | AU8: =IFERROR(IF('IND-01'!G55="","",'IND-01'!G55),"") | AV8: =IFERROR(IF('IND-01'!G56="","",'IND-01'!G56),"") | AW8: =IFERROR(IF('IND-01'!G57="","",'IND-01'!G57),"") | AX8: =IFERROR(IF('IND-01'!G58="","",'IND-01'!G58),"") | AY8: =IFERROR(IF('IND-01'!G59="","",'IND-01'!G59),"") | AZ8: =IFERROR(IF('IND-01'!G60="","",'IND-01'!G60),"") | BA8: =IFERROR(IF('IND-01'!G61="","",'IND-01'!G61),"") | BB8: =IFERROR(IF('IND-01'!G62="","",'IND-01'!G62),"") | BC8: =IFERROR(IF('IND-01'!G63="","",'IND-01'!G63),"") | BD8: =IFERROR(IF('IND-01'!G64="","",'IND-01'!G64),"") | BE8: =IFERROR(IF('IND-01'!G65="","",'IND-01'!G65),"") | BF8: =IFERROR(IF('IND-01'!G66="","",'IND-01'!G66),"") | BG8: =IFERROR(IF('IND-01'!G67="","",'IND-01'!G67),"") | BH8: =IFERROR(IF('IND-01'!G68="","",'IND-01'!G68),"") | BI8: =IFERROR(IF('IND-01'!G69="","",'IND-01'!G69),"") | BJ8: =IFERROR(IF('IND-01'!G70="","",'IND-01'!G70),"") | BK8: =IFERROR(IF('IND-01'!G71="","",'IND-01'!G71),"") | BL8: =IFERROR(IF('IND-01'!G72="","",'IND-01'!G72),"") | BM8: =IFERROR(IF('IND-01'!G73="","",'IND-01'!G73),"") | BN8: =IFERROR(IF('IND-01'!G74="","",'IND-01'!G74),"") | BO8: =IFERROR(IF('IND-01'!G75="","",'IND-01'!G75),"") | BP8: =IFERROR(IF('IND-01'!G76="","",'IND-01'!G76),"") | BQ8: =IFERROR(IF('IND-01'!G77="","",'IND-01'!G77),"") | BR8: =IFERROR(IF('IND-01'!G78="","",'IND-01'!G78),"") | BS8: =IFERROR(IF('IND-01'!G79="","",'IND-01'!G79),"") | BT8: =IFERROR(IF('IND-01'!G80="","",'IND-01'!G80),"") | BU8: =IFERROR(IF('IND-01'!G81="","",'IND-01'!G81),"") | BV8: =IFERROR(IF('IND-01'!G82="","",'IND-01'!G82),"") | BW8: =IFERROR(AVERAGE('IND-01'!I23:I34),"") -> 1 | BX8: =IFERROR(AVERAGE('IND-01'!I35:I46),"") -> 0.925 | BY8: =IFERROR(AVERAGE('IND-01'!I47:I58),"") | BZ8: =IFERROR(AVERAGE('IND-01'!I59:I70),"") | CA8: =IFERROR(AVERAGE('IND-01'!I71:I82),"") | CB8: =IFERROR(IF(LOOKUP(2,1/((BW8:CA8<>"")*(ISNUMBER(BW8:CA8))),BW8:CA8)>=0.95,"🟢 Cumple",IF(LOOKUP(2,1/((BW8:CA8<>"")*(ISNUMBER(BW8:CA8))),BW8:CA8)>=0.8,"🟡 En riesgo","🔴 Crítico")),"⚪ Pendiente") -> 🟡 En riesgo
B9: Aumento de ingresos | C9: Crecimiento de ingresos operativos | D9: (Ingresos de cartera final − Ingresos de cartera inicial) ÷ Ingresos de cartera inicial | E9: Refleja el impacto directo de la colocación sobre los ingresos financieros. | F9: % | G9: Crecer | H9: Mensual | I9: =VLOOKUP("IND-02",Parámetros!$B$6:$F$30,5,FALSE()) -> Gerencia Financiera | J9: ='IND-02'!C14 -> 0.1 | K9: ='IND-02'!C15 -> 0.1 | L9: ='IND-02'!C16 -> 0.1 | M9: ='IND-02'!C17 -> 0.1 | N9: ='IND-02'!C18 -> 0.1 | O9: =IFERROR(IF('IND-02'!F23="","",'IND-02'!F23),"") | P9: =IFERROR(IF('IND-02'!F24="","",'IND-02'!F24),"") -> 0.008 | Q9: =IFERROR(IF('IND-02'!F25="","",'IND-02'!F25),"") -> 0.008 | R9: =IFERROR(IF('IND-02'!F26="","",'IND-02'!F26),"") -> 0.008 | S9: =IFERROR(IF('IND-02'!F27="","",'IND-02'!F27),"") -> 0.008 | T9: =IFERROR(IF('IND-02'!F28="","",'IND-02'!F28),"") -> 0.008 | U9: =IFERROR(IF('IND-02'!F29="","",'IND-02'!F29),"") -> 0.008 | V9: =IFERROR(IF('IND-02'!F30="","",'IND-02'!F30),"") -> 0.008 | W9: =IFERROR(IF('IND-02'!F31="","",'IND-02'!F31),"") -> 0.008 | X9: =IFERROR(IF('IND-02'!F32="","",'IND-02'!F32),"") -> 0.008 | Y9: =IFERROR(IF('IND-02'!F33="","",'IND-02'!F33),"") -> 0.008 | Z9: =IFERROR(IF('IND-02'!F34="","",'IND-02'!F34),"") -> 0.008 | AA9: =IFERROR(IF('IND-02'!F35="","",'IND-02'!F35),"") -> 0.008 | AB9: =IFERROR(IF('IND-02'!F36="","",'IND-02'!F36),"") -> 0.008 | AC9: =IFERROR(IF('IND-02'!F37="","",'IND-02'!F37),"") -> 0.008 | AD9: =IFERROR(IF('IND-02'!F38="","",'IND-02'!F38),"") -> 0.008 | AE9: =IFERROR(IF('IND-02'!F39="","",'IND-02'!F39),"") -> 0.008 | AF9: =IFERROR(IF('IND-02'!F40="","",'IND-02'!F40),"") -> 0.008 | AG9: =IFERROR(IF('IND-02'!F41="","",'IND-02'!F41),"") | AH9: =IFERROR(IF('IND-02'!F42="","",'IND-02'!F42),"") | AI9: =IFERROR(IF('IND-02'!F43="","",'IND-02'!F43),"") | AJ9: =IFERROR(IF('IND-02'!F44="","",'IND-02'!F44),"") | AK9: =IFERROR(IF('IND-02'!F45="","",'IND-02'!F45),"") | AL9: =IFERROR(IF('IND-02'!F46="","",'IND-02'!F46),"") | AM9: =IFERROR(IF('IND-02'!F47="","",'IND-02'!F47),"") | AN9: =IFERROR(IF('IND-02'!F48="","",'IND-02'!F48),"") | AO9: =IFERROR(IF('IND-02'!F49="","",'IND-02'!F49),"") | AP9: =IFERROR(IF('IND-02'!F50="","",'IND-02'!F50),"") | AQ9: =IFERROR(IF('IND-02'!F51="","",'IND-02'!F51),"") | AR9: =IFERROR(IF('IND-02'!F52="","",'IND-02'!F52),"") | AS9: =IFERROR(IF('IND-02'!F53="","",'IND-02'!F53),"") | AT9: =IFERROR(IF('IND-02'!F54="","",'IND-02'!F54),"") | AU9: =IFERROR(IF('IND-02'!F55="","",'IND-02'!F55),"") | AV9: =IFERROR(IF('IND-02'!F56="","",'IND-02'!F56),"") | AW9: =IFERROR(IF('IND-02'!F57="","",'IND-02'!F57),"") | AX9: =IFERROR(IF('IND-02'!F58="","",'IND-02'!F58),"") | AY9: =IFERROR(IF('IND-02'!F59="","",'IND-02'!F59),"") | AZ9: =IFERROR(IF('IND-02'!F60="","",'IND-02'!F60),"") | BA9: =IFERROR(IF('IND-02'!F61="","",'IND-02'!F61),"") | BB9: =IFERROR(IF('IND-02'!F62="","",'IND-02'!F62),"") | BC9: =IFERROR(IF('IND-02'!F63="","",'IND-02'!F63),"") | BD9: =IFERROR(IF('IND-02'!F64="","",'IND-02'!F64),"") | BE9: =IFERROR(IF('IND-02'!F65="","",'IND-02'!F65),"") | BF9: =IFERROR(IF('IND-02'!F66="","",'IND-02'!F66),"") | BG9: =IFERROR(IF('IND-02'!F67="","",'IND-02'!F67),"") | BH9: =IFERROR(IF('IND-02'!F68="","",'IND-02'!F68),"") | BI9: =IFERROR(IF('IND-02'!F69="","",'IND-02'!F69),"") | BJ9: =IFERROR(IF('IND-02'!F70="","",'IND-02'!F70),"") | BK9: =IFERROR(IF('IND-02'!F71="","",'IND-02'!F71),"") | BL9: =IFERROR(IF('IND-02'!F72="","",'IND-02'!F72),"") | BM9: =IFERROR(IF('IND-02'!F73="","",'IND-02'!F73),"") | BN9: =IFERROR(IF('IND-02'!F74="","",'IND-02'!F74),"") | BO9: =IFERROR(IF('IND-02'!F75="","",'IND-02'!F75),"") | BP9: =IFERROR(IF('IND-02'!F76="","",'IND-02'!F76),"") | BQ9: =IFERROR(IF('IND-02'!F77="","",'IND-02'!F77),"") | BR9: =IFERROR(IF('IND-02'!F78="","",'IND-02'!F78),"") | BS9: =IFERROR(IF('IND-02'!F79="","",'IND-02'!F79),"") | BT9: =IFERROR(IF('IND-02'!F80="","",'IND-02'!F80),"") | BU9: =IFERROR(IF('IND-02'!F81="","",'IND-02'!F81),"") | BV9: =IFERROR(IF('IND-02'!F82="","",'IND-02'!F82),"") | BW9: =IFERROR(AVERAGE('IND-02'!H23:H34),"") -> 0.08 | BX9: =IFERROR(AVERAGE('IND-02'!H35:H46),"") -> 0.08 | BY9: =IFERROR(AVERAGE('IND-02'!H47:H58),"") | BZ9: =IFERROR(AVERAGE('IND-02'!H59:H70),"") | CA9: =IFERROR(AVERAGE('IND-02'!H71:H82),"") | CB9: =IFERROR(IF(LOOKUP(2,1/((BW9:CA9<>"")*(ISNUMBER(BW9:CA9))),BW9:CA9)>=0.95,"🟢 Cumple",IF(LOOKUP(2,1/((BW9:CA9<>"")*(ISNUMBER(BW9:CA9))),BW9:CA9)>=0.8,"🟡 En riesgo","🔴 Crítico")),"⚪ Pendiente") -> 🔴 Crítico
B10: Aumento de ingresos | C10: Crecimiento de ingresos por comisiones | D10: (Ingresos por comisiones final − Ingresos por comisiones inicial) ÷ Ingresos por comisiones inicial | E10: Mide el incremento de ingresos derivados del uso de servicios no financieros (convenios). | F10: % | G10: Crecer | H10: Mensual | I10: =VLOOKUP("IND-03",Parámetros!$B$6:$F$30,5,FALSE()) -> Cartera | J10: ='IND-03'!C14 -> 0.035 | K10: ='IND-03'!C15 -> 0.035 | L10: ='IND-03'!C16 -> 0.035 | M10: ='IND-03'!C17 -> 0.035 | N10: ='IND-03'!C18 -> 0.035 | O10: =IFERROR(IF('IND-03'!F23="","",'IND-03'!F23),"") | P10: =IFERROR(IF('IND-03'!F24="","",'IND-03'!F24),"") | Q10: =IFERROR(IF('IND-03'!F25="","",'IND-03'!F25),"") | R10: =IFERROR(IF('IND-03'!F26="","",'IND-03'!F26),"") | S10: =IFERROR(IF('IND-03'!F27="","",'IND-03'!F27),"") | T10: =IFERROR(IF('IND-03'!F28="","",'IND-03'!F28),"") | U10: =IFERROR(IF('IND-03'!F29="","",'IND-03'!F29),"") | V10: =IFERROR(IF('IND-03'!F30="","",'IND-03'!F30),"") | W10: =IFERROR(IF('IND-03'!F31="","",'IND-03'!F31),"") | X10: =IFERROR(IF('IND-03'!F32="","",'IND-03'!F32),"") | Y10: =IFERROR(IF('IND-03'!F33="","",'IND-03'!F33),"") | Z10: =IFERROR(IF('IND-03'!F34="","",'IND-03'!F34),"") | AA10: =IFERROR(IF('IND-03'!F35="","",'IND-03'!F35),"") | AB10: =IFERROR(IF('IND-03'!F36="","",'IND-03'!F36),"") | AC10: =IFERROR(IF('IND-03'!F37="","",'IND-03'!F37),"") | AD10: =IFERROR(IF('IND-03'!F38="","",'IND-03'!F38),"") | AE10: =IFERROR(IF('IND-03'!F39="","",'IND-03'!F39),"") | AF10: =IFERROR(IF('IND-03'!F40="","",'IND-03'!F40),"") | AG10: =IFERROR(IF('IND-03'!F41="","",'IND-03'!F41),"") | AH10: =IFERROR(IF('IND-03'!F42="","",'IND-03'!F42),"") | AI10: =IFERROR(IF('IND-03'!F43="","",'IND-03'!F43),"") | AJ10: =IFERROR(IF('IND-03'!F44="","",'IND-03'!F44),"") | AK10: =IFERROR(IF('IND-03'!F45="","",'IND-03'!F45),"") | AL10: =IFERROR(IF('IND-03'!F46="","",'IND-03'!F46),"") | AM10: =IFERROR(IF('IND-03'!F47="","",'IND-03'!F47),"") | AN10: =IFERROR(IF('IND-03'!F48="","",'IND-03'!F48),"") | AO10: =IFERROR(IF('IND-03'!F49="","",'IND-03'!F49),"") | AP10: =IFERROR(IF('IND-03'!F50="","",'IND-03'!F50),"") | AQ10: =IFERROR(IF('IND-03'!F51="","",'IND-03'!F51),"") | AR10: =IFERROR(IF('IND-03'!F52="","",'IND-03'!F52),"") | AS10: =IFERROR(IF('IND-03'!F53="","",'IND-03'!F53),"") | AT10: =IFERROR(IF('IND-03'!F54="","",'IND-03'!F54),"") | AU10: =IFERROR(IF('IND-03'!F55="","",'IND-03'!F55),"") | AV10: =IFERROR(IF('IND-03'!F56="","",'IND-03'!F56),"") | AW10: =IFERROR(IF('IND-03'!F57="","",'IND-03'!F57),"") | AX10: =IFERROR(IF('IND-03'!F58="","",'IND-03'!F58),"") | AY10: =IFERROR(IF('IND-03'!F59="","",'IND-03'!F59),"") | AZ10: =IFERROR(IF('IND-03'!F60="","",'IND-03'!F60),"") | BA10: =IFERROR(IF('IND-03'!F61="","",'IND-03'!F61),"") | BB10: =IFERROR(IF('IND-03'!F62="","",'IND-03'!F62),"") | BC10: =IFERROR(IF('IND-03'!F63="","",'IND-03'!F63),"") | BD10: =IFERROR(IF('IND-03'!F64="","",'IND-03'!F64),"") | BE10: =IFERROR(IF('IND-03'!F65="","",'IND-03'!F65),"") | BF10: =IFERROR(IF('IND-03'!F66="","",'IND-03'!F66),"") | BG10: =IFERROR(IF('IND-03'!F67="","",'IND-03'!F67),"") | BH10: =IFERROR(IF('IND-03'!F68="","",'IND-03'!F68),"") | BI10: =IFERROR(IF('IND-03'!F69="","",'IND-03'!F69),"") | BJ10: =IFERROR(IF('IND-03'!F70="","",'IND-03'!F70),"") | BK10: =IFERROR(IF('IND-03'!F71="","",'IND-03'!F71),"") | BL10: =IFERROR(IF('IND-03'!F72="","",'IND-03'!F72),"") | BM10: =IFERROR(IF('IND-03'!F73="","",'IND-03'!F73),"") | BN10: =IFERROR(IF('IND-03'!F74="","",'IND-03'!F74),"") | BO10: =IFERROR(IF('IND-03'!F75="","",'IND-03'!F75),"") | BP10: =IFERROR(IF('IND-03'!F76="","",'IND-03'!F76),"") | BQ10: =IFERROR(IF('IND-03'!F77="","",'IND-03'!F77),"") | BR10: =IFERROR(IF('IND-03'!F78="","",'IND-03'!F78),"") | BS10: =IFERROR(IF('IND-03'!F79="","",'IND-03'!F79),"") | BT10: =IFERROR(IF('IND-03'!F80="","",'IND-03'!F80),"") | BU10: =IFERROR(IF('IND-03'!F81="","",'IND-03'!F81),"") | BV10: =IFERROR(IF('IND-03'!F82="","",'IND-03'!F82),"") | BW10: =IFERROR(AVERAGE('IND-03'!H23:H34),"") | BX10: =IFERROR(AVERAGE('IND-03'!H35:H46),"") | BY10: =IFERROR(AVERAGE('IND-03'!H47:H58),"") | BZ10: =IFERROR(AVERAGE('IND-03'!H59:H70),"") | CA10: =IFERROR(AVERAGE('IND-03'!H71:H82),"") | CB10: =IFERROR(IF(LOOKUP(2,1/((BW10:CA10<>"")*(ISNUMBER(BW10:CA10))),BW10:CA10)>=0.95,"🟢 Cumple",IF(LOOKUP(2,1/((BW10:CA10<>"")*(ISNUMBER(BW10:CA10))),BW10:CA10)>=0.8,"🟡 En riesgo","🔴 Crítico")),"⚪ Pendiente") -> ⚪ Pendiente
B11: Aumento de ingresos | C11: Rentabilidad Fondo de Liquidez | D11: Tasa promedio ponderada de rentabilidad del fondo de liquidez − IBR | E11: Mide la capacidad de generar rentabilidad por encima del mercado. | F11: Puntos básicos | G11: Crecer | H11: Mensual | I11: =VLOOKUP("IND-04",Parámetros!$B$6:$F$30,5,FALSE()) -> Tesorería | J11: ='IND-04'!C14 -> -200 | K11: ='IND-04'!C15 -> -200 | L11: ='IND-04'!C16 -> -200 | M11: ='IND-04'!C17 -> -200 | N11: ='IND-04'!C18 -> -200 | O11: =IFERROR(IF('IND-04'!G23="","",'IND-04'!G23),"") | P11: =IFERROR(IF('IND-04'!G24="","",'IND-04'!G24),"") | Q11: =IFERROR(IF('IND-04'!G25="","",'IND-04'!G25),"") | R11: =IFERROR(IF('IND-04'!G26="","",'IND-04'!G26),"") | S11: =IFERROR(IF('IND-04'!G27="","",'IND-04'!G27),"") | T11: =IFERROR(IF('IND-04'!G28="","",'IND-04'!G28),"") | U11: =IFERROR(IF('IND-04'!G29="","",'IND-04'!G29),"") | V11: =IFERROR(IF('IND-04'!G30="","",'IND-04'!G30),"") | W11: =IFERROR(IF('IND-04'!G31="","",'IND-04'!G31),"") | X11: =IFERROR(IF('IND-04'!G32="","",'IND-04'!G32),"") | Y11: =IFERROR(IF('IND-04'!G33="","",'IND-04'!G33),"") | Z11: =IFERROR(IF('IND-04'!G34="","",'IND-04'!G34),"") | AA11: =IFERROR(IF('IND-04'!G35="","",'IND-04'!G35),"") | AB11: =IFERROR(IF('IND-04'!G36="","",'IND-04'!G36),"") | AC11: =IFERROR(IF('IND-04'!G37="","",'IND-04'!G37),"") | AD11: =IFERROR(IF('IND-04'!G38="","",'IND-04'!G38),"") | AE11: =IFERROR(IF('IND-04'!G39="","",'IND-04'!G39),"") | AF11: =IFERROR(IF('IND-04'!G40="","",'IND-04'!G40),"") | AG11: =IFERROR(IF('IND-04'!G41="","",'IND-04'!G41),"") | AH11: =IFERROR(IF('IND-04'!G42="","",'IND-04'!G42),"") | AI11: =IFERROR(IF('IND-04'!G43="","",'IND-04'!G43),"") | AJ11: =IFERROR(IF('IND-04'!G44="","",'IND-04'!G44),"") | AK11: =IFERROR(IF('IND-04'!G45="","",'IND-04'!G45),"") | AL11: =IFERROR(IF('IND-04'!G46="","",'IND-04'!G46),"") | AM11: =IFERROR(IF('IND-04'!G47="","",'IND-04'!G47),"") | AN11: =IFERROR(IF('IND-04'!G48="","",'IND-04'!G48),"") | AO11: =IFERROR(IF('IND-04'!G49="","",'IND-04'!G49),"") | AP11: =IFERROR(IF('IND-04'!G50="","",'IND-04'!G50),"") | AQ11: =IFERROR(IF('IND-04'!G51="","",'IND-04'!G51),"") | AR11: =IFERROR(IF('IND-04'!G52="","",'IND-04'!G52),"") | AS11: =IFERROR(IF('IND-04'!G53="","",'IND-04'!G53),"") | AT11: =IFERROR(IF('IND-04'!G54="","",'IND-04'!G54),"") | AU11: =IFERROR(IF('IND-04'!G55="","",'IND-04'!G55),"") | AV11: =IFERROR(IF('IND-04'!G56="","",'IND-04'!G56),"") | AW11: =IFERROR(IF('IND-04'!G57="","",'IND-04'!G57),"") | AX11: =IFERROR(IF('IND-04'!G58="","",'IND-04'!G58),"") | AY11: =IFERROR(IF('IND-04'!G59="","",'IND-04'!G59),"") | AZ11: =IFERROR(IF('IND-04'!G60="","",'IND-04'!G60),"") | BA11: =IFERROR(IF('IND-04'!G61="","",'IND-04'!G61),"") | BB11: =IFERROR(IF('IND-04'!G62="","",'IND-04'!G62),"") | BC11: =IFERROR(IF('IND-04'!G63="","",'IND-04'!G63),"") | BD11: =IFERROR(IF('IND-04'!G64="","",'IND-04'!G64),"") | BE11: =IFERROR(IF('IND-04'!G65="","",'IND-04'!G65),"") | BF11: =IFERROR(IF('IND-04'!G66="","",'IND-04'!G66),"") | BG11: =IFERROR(IF('IND-04'!G67="","",'IND-04'!G67),"") | BH11: =IFERROR(IF('IND-04'!G68="","",'IND-04'!G68),"") | BI11: =IFERROR(IF('IND-04'!G69="","",'IND-04'!G69),"") | BJ11: =IFERROR(IF('IND-04'!G70="","",'IND-04'!G70),"") | BK11: =IFERROR(IF('IND-04'!G71="","",'IND-04'!G71),"") | BL11: =IFERROR(IF('IND-04'!G72="","",'IND-04'!G72),"") | BM11: =IFERROR(IF('IND-04'!G73="","",'IND-04'!G73),"") | BN11: =IFERROR(IF('IND-04'!G74="","",'IND-04'!G74),"") | BO11: =IFERROR(IF('IND-04'!G75="","",'IND-04'!G75),"") | BP11: =IFERROR(IF('IND-04'!G76="","",'IND-04'!G76),"") | BQ11: =IFERROR(IF('IND-04'!G77="","",'IND-04'!G77),"") | BR11: =IFERROR(IF('IND-04'!G78="","",'IND-04'!G78),"") | BS11: =IFERROR(IF('IND-04'!G79="","",'IND-04'!G79),"") | BT11: =IFERROR(IF('IND-04'!G80="","",'IND-04'!G80),"") | BU11: =IFERROR(IF('IND-04'!G81="","",'IND-04'!G81),"") | BV11: =IFERROR(IF('IND-04'!G82="","",'IND-04'!G82),"") | BW11: =IFERROR(AVERAGE('IND-04'!I23:I34),"") | BX11: =IFERROR(AVERAGE('IND-04'!I35:I46),"") | BY11: =IFERROR(AVERAGE('IND-04'!I47:I58),"") | BZ11: =IFERROR(AVERAGE('IND-04'!I59:I70),"") | CA11: =IFERROR(AVERAGE('IND-04'!I71:I82),"") | CB11: =IFERROR(IF(LOOKUP(2,1/((BW11:CA11<>"")*(ISNUMBER(BW11:CA11))),BW11:CA11)>=0.95,"🟢 Cumple",IF(LOOKUP(2,1/((BW11:CA11<>"")*(ISNUMBER(BW11:CA11))),BW11:CA11)>=0.8,"🟡 En riesgo","🔴 Crítico")),"⚪ Pendiente") -> ⚪ Pendiente
B12: Reducción de mora | C12: Índice de mora | D12: Saldo de cartera ≥ B ÷ Saldo total de cartera | E12: Mide el nivel de morosidad de la cartera por crédito, sin aplicación de arrastres o riesgo. | F12: % | G12: Reducir | H12: Mensual | I12: =VLOOKUP("IND-05",Parámetros!$B$6:$F$30,5,FALSE()) -> Cartera | J12: ='IND-05'!C14 -> 0.05 | K12: ='IND-05'!C15 -> 0.05 | L12: ='IND-05'!C16 -> 0.05 | M12: ='IND-05'!C17 -> 0.05 | N12: ='IND-05'!C18 -> 0.05 | O12: =IFERROR(IF('IND-05'!G23="","",'IND-05'!G23),"") -> 0.045 | P12: =IFERROR(IF('IND-05'!G24="","",'IND-05'!G24),"") -> 0.046 | Q12: =IFERROR(IF('IND-05'!G25="","",'IND-05'!G25),"") -> 0.047 | R12: =IFERROR(IF('IND-05'!G26="","",'IND-05'!G26),"") -> 0.048 | S12: =IFERROR(IF('IND-05'!G27="","",'IND-05'!G27),"") -> 0.049 | T12: =IFERROR(IF('IND-05'!G28="","",'IND-05'!G28),"") -> 0.05 | U12: =IFERROR(IF('IND-05'!G29="","",'IND-05'!G29),"") -> 0.051 | V12: =IFERROR(IF('IND-05'!G30="","",'IND-05'!G30),"") -> 0.052 | W12: =IFERROR(IF('IND-05'!G31="","",'IND-05'!G31),"") -> 0.053 | X12: =IFERROR(IF('IND-05'!G32="","",'IND-05'!G32),"") -> 0.054 | Y12: =IFERROR(IF('IND-05'!G33="","",'IND-05'!G33),"") -> 0.055 | Z12: =IFERROR(IF('IND-05'!G34="","",'IND-05'!G34),"") -> 0.056 | AA12: =IFERROR(IF('IND-05'!G35="","",'IND-05'!G35),"") -> 0.1 | AB12: =IFERROR(IF('IND-05'!G36="","",'IND-05'!G36),"") -> 0.1 | AC12: =IFERROR(IF('IND-05'!G37="","",'IND-05'!G37),"") -> 0.1 | AD12: =IFERROR(IF('IND-05'!G38="","",'IND-05'!G38),"") | AE12: =IFERROR(IF('IND-05'!G39="","",'IND-05'!G39),"") | AF12: =IFERROR(IF('IND-05'!G40="","",'IND-05'!G40),"") | AG12: =IFERROR(IF('IND-05'!G41="","",'IND-05'!G41),"") | AH12: =IFERROR(IF('IND-05'!G42="","",'IND-05'!G42),"") | AI12: =IFERROR(IF('IND-05'!G43="","",'IND-05'!G43),"") | AJ12: =IFERROR(IF('IND-05'!G44="","",'IND-05'!G44),"") | AK12: =IFERROR(IF('IND-05'!G45="","",'IND-05'!G45),"") | AL12: =IFERROR(IF('IND-05'!G46="","",'IND-05'!G46),"") | AM12: =IFERROR(IF('IND-05'!G47="","",'IND-05'!G47),"") | AN12: =IFERROR(IF('IND-05'!G48="","",'IND-05'!G48),"") | AO12: =IFERROR(IF('IND-05'!G49="","",'IND-05'!G49),"") | AP12: =IFERROR(IF('IND-05'!G50="","",'IND-05'!G50),"") | AQ12: =IFERROR(IF('IND-05'!G51="","",'IND-05'!G51),"") | AR12: =IFERROR(IF('IND-05'!G52="","",'IND-05'!G52),"") | AS12: =IFERROR(IF('IND-05'!G53="","",'IND-05'!G53),"") | AT12: =IFERROR(IF('IND-05'!G54="","",'IND-05'!G54),"") | AU12: =IFERROR(IF('IND-05'!G55="","",'IND-05'!G55),"") | AV12: =IFERROR(IF('IND-05'!G56="","",'IND-05'!G56),"") | AW12: =IFERROR(IF('IND-05'!G57="","",'IND-05'!G57),"") | AX12: =IFERROR(IF('IND-05'!G58="","",'IND-05'!G58),"") | AY12: =IFERROR(IF('IND-05'!G59="","",'IND-05'!G59),"") | AZ12: =IFERROR(IF('IND-05'!G60="","",'IND-05'!G60),"") | BA12: =IFERROR(IF('IND-05'!G61="","",'IND-05'!G61),"") | BB12: =IFERROR(IF('IND-05'!G62="","",'IND-05'!G62),"") | BC12: =IFERROR(IF('IND-05'!G63="","",'IND-05'!G63),"") | BD12: =IFERROR(IF('IND-05'!G64="","",'IND-05'!G64),"") | BE12: =IFERROR(IF('IND-05'!G65="","",'IND-05'!G65),"") | BF12: =IFERROR(IF('IND-05'!G66="","",'IND-05'!G66),"") | BG12: =IFERROR(IF('IND-05'!G67="","",'IND-05'!G67),"") | BH12: =IFERROR(IF('IND-05'!G68="","",'IND-05'!G68),"") | BI12: =IFERROR(IF('IND-05'!G69="","",'IND-05'!G69),"") | BJ12: =IFERROR(IF('IND-05'!G70="","",'IND-05'!G70),"") | BK12: =IFERROR(IF('IND-05'!G71="","",'IND-05'!G71),"") | BL12: =IFERROR(IF('IND-05'!G72="","",'IND-05'!G72),"") | BM12: =IFERROR(IF('IND-05'!G73="","",'IND-05'!G73),"") | BN12: =IFERROR(IF('IND-05'!G74="","",'IND-05'!G74),"") | BO12: =IFERROR(IF('IND-05'!G75="","",'IND-05'!G75),"") | BP12: =IFERROR(IF('IND-05'!G76="","",'IND-05'!G76),"") | BQ12: =IFERROR(IF('IND-05'!G77="","",'IND-05'!G77),"") | BR12: =IFERROR(IF('IND-05'!G78="","",'IND-05'!G78),"") | BS12: =IFERROR(IF('IND-05'!G79="","",'IND-05'!G79),"") | BT12: =IFERROR(IF('IND-05'!G80="","",'IND-05'!G80),"") | BU12: =IFERROR(IF('IND-05'!G81="","",'IND-05'!G81),"") | BV12: =IFERROR(IF('IND-05'!G82="","",'IND-05'!G82),"") | BW12: =IFERROR(AVERAGE('IND-05'!I23:I34),"") -> 0.99476442 | BX12: =IFERROR(AVERAGE('IND-05'!I35:I46),"") -> 0.5 | BY12: =IFERROR(AVERAGE('IND-05'!I47:I58),"") | BZ12: =IFERROR(AVERAGE('IND-05'!I59:I70),"") | CA12: =IFERROR(AVERAGE('IND-05'!I71:I82),"") | CB12: =IFERROR(IF(LOOKUP(2,1/((BW12:CA12<>"")*(ISNUMBER(BW12:CA12))),BW12:CA12)>=0.95,"🟢 Cumple",IF(LOOKUP(2,1/((BW12:CA12<>"")*(ISNUMBER(BW12:CA12))),BW12:CA12)>=0.8,"🟡 En riesgo","🔴 Crítico")),"⚪ Pendiente") -> 🔴 Crítico
B13: Reducción de mora | C13: Tasa de recuperación | D13: Saldo de cartera recuperada ÷ Saldo de cartera deteriorada | E13: Mide la proporción de cartera recuperada frente a la deteriorada por rodamiento (matriz de transición). | F13: % | G13: Crecer | H13: Mensual | I13: =VLOOKUP("IND-06",Parámetros!$B$6:$F$30,5,FALSE()) -> Por definir | J13: ='IND-06'!C14 -> 0.3 | K13: ='IND-06'!C15 -> 0.3 | L13: ='IND-06'!C16 -> 0.3 | M13: ='IND-06'!C17 -> 0.3 | N13: ='IND-06'!C18 -> 0.3 | O13: =IFERROR(IF('IND-06'!G23="","",'IND-06'!G23),"") | P13: =IFERROR(IF('IND-06'!G24="","",'IND-06'!G24),"") | Q13: =IFERROR(IF('IND-06'!G25="","",'IND-06'!G25),"") | R13: =IFERROR(IF('IND-06'!G26="","",'IND-06'!G26),"") | S13: =IFERROR(IF('IND-06'!G27="","",'IND-06'!G27),"") | T13: =IFERROR(IF('IND-06'!G28="","",'IND-06'!G28),"") | U13: =IFERROR(IF('IND-06'!G29="","",'IND-06'!G29),"") | V13: =IFERROR(IF('IND-06'!G30="","",'IND-06'!G30),"") | W13: =IFERROR(IF('IND-06'!G31="","",'IND-06'!G31),"") | X13: =IFERROR(IF('IND-06'!G32="","",'IND-06'!G32),"") | Y13: =IFERROR(IF('IND-06'!G33="","",'IND-06'!G33),"") | Z13: =IFERROR(IF('IND-06'!G34="","",'IND-06'!G34),"") | AA13: =IFERROR(IF('IND-06'!G35="","",'IND-06'!G35),"") | AB13: =IFERROR(IF('IND-06'!G36="","",'IND-06'!G36),"") | AC13: =IFERROR(IF('IND-06'!G37="","",'IND-06'!G37),"") | AD13: =IFERROR(IF('IND-06'!G38="","",'IND-06'!G38),"") | AE13: =IFERROR(IF('IND-06'!G39="","",'IND-06'!G39),"") | AF13: =IFERROR(IF('IND-06'!G40="","",'IND-06'!G40),"") | AG13: =IFERROR(IF('IND-06'!G41="","",'IND-06'!G41),"") | AH13: =IFERROR(IF('IND-06'!G42="","",'IND-06'!G42),"") | AI13: =IFERROR(IF('IND-06'!G43="","",'IND-06'!G43),"") | AJ13: =IFERROR(IF('IND-06'!G44="","",'IND-06'!G44),"") | AK13: =IFERROR(IF('IND-06'!G45="","",'IND-06'!G45),"") | AL13: =IFERROR(IF('IND-06'!G46="","",'IND-06'!G46),"") | AM13: =IFERROR(IF('IND-06'!G47="","",'IND-06'!G47),"") | AN13: =IFERROR(IF('IND-06'!G48="","",'IND-06'!G48),"") | AO13: =IFERROR(IF('IND-06'!G49="","",'IND-06'!G49),"") | AP13: =IFERROR(IF('IND-06'!G50="","",'IND-06'!G50),"") | AQ13: =IFERROR(IF('IND-06'!G51="","",'IND-06'!G51),"") | AR13: =IFERROR(IF('IND-06'!G52="","",'IND-06'!G52),"") | AS13: =IFERROR(IF('IND-06'!G53="","",'IND-06'!G53),"") | AT13: =IFERROR(IF('IND-06'!G54="","",'IND-06'!G54),"") | AU13: =IFERROR(IF('IND-06'!G55="","",'IND-06'!G55),"") | AV13: =IFERROR(IF('IND-06'!G56="","",'IND-06'!G56),"") | AW13: =IFERROR(IF('IND-06'!G57="","",'IND-06'!G57),"") | AX13: =IFERROR(IF('IND-06'!G58="","",'IND-06'!G58),"") | AY13: =IFERROR(IF('IND-06'!G59="","",'IND-06'!G59),"") | AZ13: =IFERROR(IF('IND-06'!G60="","",'IND-06'!G60),"") | BA13: =IFERROR(IF('IND-06'!G61="","",'IND-06'!G61),"") | BB13: =IFERROR(IF('IND-06'!G62="","",'IND-06'!G62),"") | BC13: =IFERROR(IF('IND-06'!G63="","",'IND-06'!G63),"") | BD13: =IFERROR(IF('IND-06'!G64="","",'IND-06'!G64),"") | BE13: =IFERROR(IF('IND-06'!G65="","",'IND-06'!G65),"") | BF13: =IFERROR(IF('IND-06'!G66="","",'IND-06'!G66),"") | BG13: =IFERROR(IF('IND-06'!G67="","",'IND-06'!G67),"") | BH13: =IFERROR(IF('IND-06'!G68="","",'IND-06'!G68),"") | BI13: =IFERROR(IF('IND-06'!G69="","",'IND-06'!G69),"") | BJ13: =IFERROR(IF('IND-06'!G70="","",'IND-06'!G70),"") | BK13: =IFERROR(IF('IND-06'!G71="","",'IND-06'!G71),"") | BL13: =IFERROR(IF('IND-06'!G72="","",'IND-06'!G72),"") | BM13: =IFERROR(IF('IND-06'!G73="","",'IND-06'!G73),"") | BN13: =IFERROR(IF('IND-06'!G74="","",'IND-06'!G74),"") | BO13: =IFERROR(IF('IND-06'!G75="","",'IND-06'!G75),"") | BP13: =IFERROR(IF('IND-06'!G76="","",'IND-06'!G76),"") | BQ13: =IFERROR(IF('IND-06'!G77="","",'IND-06'!G77),"") | BR13: =IFERROR(IF('IND-06'!G78="","",'IND-06'!G78),"") | BS13: =IFERROR(IF('IND-06'!G79="","",'IND-06'!G79),"") | BT13: =IFERROR(IF('IND-06'!G80="","",'IND-06'!G80),"") | BU13: =IFERROR(IF('IND-06'!G81="","",'IND-06'!G81),"") | BV13: =IFERROR(IF('IND-06'!G82="","",'IND-06'!G82),"") | BW13: =IFERROR(AVERAGE('IND-06'!I23:I34),"") | BX13: =IFERROR(AVERAGE('IND-06'!I35:I46),"") | BY13: =IFERROR(AVERAGE('IND-06'!I47:I58),"") | BZ13: =IFERROR(AVERAGE('IND-06'!I59:I70),"") | CA13: =IFERROR(AVERAGE('IND-06'!I71:I82),"") | CB13: =IFERROR(IF(LOOKUP(2,1/((BW13:CA13<>"")*(ISNUMBER(BW13:CA13))),BW13:CA13)>=0.95,"🟢 Cumple",IF(LOOKUP(2,1/((BW13:CA13<>"")*(ISNUMBER(BW13:CA13))),BW13:CA13)>=0.8,"🟡 En riesgo","🔴 Crítico")),"⚪ Pendiente") -> ⚪ Pendiente
B14: Reducción de mora | C14: Tasa de normalización de cartera | D14: Saldo de normalizaciones al día ÷ Saldo total de normalizaciones | E14: Mide la efectividad de acuerdos de pago y reestructuraciones. | F14: % | G14: Crecer | H14: Mensual | I14: =VLOOKUP("IND-07",Parámetros!$B$6:$F$30,5,FALSE()) -> Por definir | J14: ='IND-07'!C14 -> 0.8 | K14: ='IND-07'!C15 -> 0.8 | L14: ='IND-07'!C16 -> 0.8 | M14: ='IND-07'!C17 -> 0.8 | N14: ='IND-07'!C18 -> 0.8 | O14: =IFERROR(IF('IND-07'!G23="","",'IND-07'!G23),"") | P14: =IFERROR(IF('IND-07'!G24="","",'IND-07'!G24),"") | Q14: =IFERROR(IF('IND-07'!G25="","",'IND-07'!G25),"") | R14: =IFERROR(IF('IND-07'!G26="","",'IND-07'!G26),"") | S14: =IFERROR(IF('IND-07'!G27="","",'IND-07'!G27),"") | T14: =IFERROR(IF('IND-07'!G28="","",'IND-07'!G28),"") | U14: =IFERROR(IF('IND-07'!G29="","",'IND-07'!G29),"") | V14: =IFERROR(IF('IND-07'!G30="","",'IND-07'!G30),"") | W14: =IFERROR(IF('IND-07'!G31="","",'IND-07'!G31),"") | X14: =IFERROR(IF('IND-07'!G32="","",'IND-07'!G32),"") | Y14: =IFERROR(IF('IND-07'!G33="","",'IND-07'!G33),"") | Z14: =IFERROR(IF('IND-07'!G34="","",'IND-07'!G34),"") | AA14: =IFERROR(IF('IND-07'!G35="","",'IND-07'!G35),"") | AB14: =IFERROR(IF('IND-07'!G36="","",'IND-07'!G36),"") | AC14: =IFERROR(IF('IND-07'!G37="","",'IND-07'!G37),"") | AD14: =IFERROR(IF('IND-07'!G38="","",'IND-07'!G38),"") | AE14: =IFERROR(IF('IND-07'!G39="","",'IND-07'!G39),"") | AF14: =IFERROR(IF('IND-07'!G40="","",'IND-07'!G40),"") | AG14: =IFERROR(IF('IND-07'!G41="","",'IND-07'!G41),"") | AH14: =IFERROR(IF('IND-07'!G42="","",'IND-07'!G42),"") | AI14: =IFERROR(IF('IND-07'!G43="","",'IND-07'!G43),"") | AJ14: =IFERROR(IF('IND-07'!G44="","",'IND-07'!G44),"") | AK14: =IFERROR(IF('IND-07'!G45="","",'IND-07'!G45),"") | AL14: =IFERROR(IF('IND-07'!G46="","",'IND-07'!G46),"") | AM14: =IFERROR(IF('IND-07'!G47="","",'IND-07'!G47),"") | AN14: =IFERROR(IF('IND-07'!G48="","",'IND-07'!G48),"") | AO14: =IFERROR(IF('IND-07'!G49="","",'IND-07'!G49),"") | AP14: =IFERROR(IF('IND-07'!G50="","",'IND-07'!G50),"") | AQ14: =IFERROR(IF('IND-07'!G51="","",'IND-07'!G51),"") | AR14: =IFERROR(IF('IND-07'!G52="","",'IND-07'!G52),"") | AS14: =IFERROR(IF('IND-07'!G53="","",'IND-07'!G53),"") | AT14: =IFERROR(IF('IND-07'!G54="","",'IND-07'!G54),"") | AU14: =IFERROR(IF('IND-07'!G55="","",'IND-07'!G55),"") | AV14: =IFERROR(IF('IND-07'!G56="","",'IND-07'!G56),"") | AW14: =IFERROR(IF('IND-07'!G57="","",'IND-07'!G57),"") | AX14: =IFERROR(IF('IND-07'!G58="","",'IND-07'!G58),"") | AY14: =IFERROR(IF('IND-07'!G59="","",'IND-07'!G59),"") | AZ14: =IFERROR(IF('IND-07'!G60="","",'IND-07'!G60),"") | BA14: =IFERROR(IF('IND-07'!G61="","",'IND-07'!G61),"") | BB14: =IFERROR(IF('IND-07'!G62="","",'IND-07'!G62),"") | BC14: =IFERROR(IF('IND-07'!G63="","",'IND-07'!G63),"") | BD14: =IFERROR(IF('IND-07'!G64="","",'IND-07'!G64),"") | BE14: =IFERROR(IF('IND-07'!G65="","",'IND-07'!G65),"") | BF14: =IFERROR(IF('IND-07'!G66="","",'IND-07'!G66),"") | BG14: =IFERROR(IF('IND-07'!G67="","",'IND-07'!G67),"") | BH14: =IFERROR(IF('IND-07'!G68="","",'IND-07'!G68),"") | BI14: =IFERROR(IF('IND-07'!G69="","",'IND-07'!G69),"") | BJ14: =IFERROR(IF('IND-07'!G70="","",'IND-07'!G70),"") | BK14: =IFERROR(IF('IND-07'!G71="","",'IND-07'!G71),"") | BL14: =IFERROR(IF('IND-07'!G72="","",'IND-07'!G72),"") | BM14: =IFERROR(IF('IND-07'!G73="","",'IND-07'!G73),"") | BN14: =IFERROR(IF('IND-07'!G74="","",'IND-07'!G74),"") | BO14: =IFERROR(IF('IND-07'!G75="","",'IND-07'!G75),"") | BP14: =IFERROR(IF('IND-07'!G76="","",'IND-07'!G76),"") | BQ14: =IFERROR(IF('IND-07'!G77="","",'IND-07'!G77),"") | BR14: =IFERROR(IF('IND-07'!G78="","",'IND-07'!G78),"") | BS14: =IFERROR(IF('IND-07'!G79="","",'IND-07'!G79),"") | BT14: =IFERROR(IF('IND-07'!G80="","",'IND-07'!G80),"") | BU14: =IFERROR(IF('IND-07'!G81="","",'IND-07'!G81),"") | BV14: =IFERROR(IF('IND-07'!G82="","",'IND-07'!G82),"") | BW14: =IFERROR(AVERAGE('IND-07'!I23:I34),"") | BX14: =IFERROR(AVERAGE('IND-07'!I35:I46),"") | BY14: =IFERROR(AVERAGE('IND-07'!I47:I58),"") | BZ14: =IFERROR(AVERAGE('IND-07'!I59:I70),"") | CA14: =IFERROR(AVERAGE('IND-07'!I71:I82),"") | CB14: =IFERROR(IF(LOOKUP(2,1/((BW14:CA14<>"")*(ISNUMBER(BW14:CA14))),BW14:CA14)>=0.95,"🟢 Cumple",IF(LOOKUP(2,1/((BW14:CA14<>"")*(ISNUMBER(BW14:CA14))),BW14:CA14)>=0.8,"🟡 En riesgo","🔴 Crítico")),"⚪ Pendiente") -> ⚪ Pendiente
B15: Crecimiento y remuneración de depósitos | C15: Tasa de crecimiento de ahorros | D15: (Saldo final depósitos − Saldo inicial depósitos) ÷ Saldo inicial depósitos | E15: Mide el crecimiento de los depósitos entre periodos. | F15: % | G15: Crecer | H15: Mensual | I15: =VLOOKUP("IND-08",Parámetros!$B$6:$F$30,5,FALSE()) -> Por definir | J15: ='IND-08'!C14 -> ≥ IPC | K15: ='IND-08'!C15 -> ≥ IPC | L15: ='IND-08'!C16 -> ≥ IPC | M15: ='IND-08'!C17 -> ≥ IPC | N15: ='IND-08'!C18 -> ≥ IPC | O15: =IFERROR(IF('IND-08'!F23="","",'IND-08'!F23),"") | P15: =IFERROR(IF('IND-08'!F24="","",'IND-08'!F24),"") | Q15: =IFERROR(IF('IND-08'!F25="","",'IND-08'!F25),"") | R15: =IFERROR(IF('IND-08'!F26="","",'IND-08'!F26),"") | S15: =IFERROR(IF('IND-08'!F27="","",'IND-08'!F27),"") | T15: =IFERROR(IF('IND-08'!F28="","",'IND-08'!F28),"") | U15: =IFERROR(IF('IND-08'!F29="","",'IND-08'!F29),"") | V15: =IFERROR(IF('IND-08'!F30="","",'IND-08'!F30),"") | W15: =IFERROR(IF('IND-08'!F31="","",'IND-08'!F31),"") | X15: =IFERROR(IF('IND-08'!F32="","",'IND-08'!F32),"") | Y15: =IFERROR(IF('IND-08'!F33="","",'IND-08'!F33),"") | Z15: =IFERROR(IF('IND-08'!F34="","",'IND-08'!F34),"") | AA15: =IFERROR(IF('IND-08'!F35="","",'IND-08'!F35),"") | AB15: =IFERROR(IF('IND-08'!F36="","",'IND-08'!F36),"") | AC15: =IFERROR(IF('IND-08'!F37="","",'IND-08'!F37),"") | AD15: =IFERROR(IF('IND-08'!F38="","",'IND-08'!F38),"") | AE15: =IFERROR(IF('IND-08'!F39="","",'IND-08'!F39),"") | AF15: =IFERROR(IF('IND-08'!F40="","",'IND-08'!F40),"") | AG15: =IFERROR(IF('IND-08'!F41="","",'IND-08'!F41),"") | AH15: =IFERROR(IF('IND-08'!F42="","",'IND-08'!F42),"") | AI15: =IFERROR(IF('IND-08'!F43="","",'IND-08'!F43),"") | AJ15: =IFERROR(IF('IND-08'!F44="","",'IND-08'!F44),"") | AK15: =IFERROR(IF('IND-08'!F45="","",'IND-08'!F45),"") | AL15: =IFERROR(IF('IND-08'!F46="","",'IND-08'!F46),"") | AM15: =IFERROR(IF('IND-08'!F47="","",'IND-08'!F47),"") | AN15: =IFERROR(IF('IND-08'!F48="","",'IND-08'!F48),"") | AO15: =IFERROR(IF('IND-08'!F49="","",'IND-08'!F49),"") | AP15: =IFERROR(IF('IND-08'!F50="","",'IND-08'!F50),"") | AQ15: =IFERROR(IF('IND-08'!F51="","",'IND-08'!F51),"") | AR15: =IFERROR(IF('IND-08'!F52="","",'IND-08'!F52),"") | AS15: =IFERROR(IF('IND-08'!F53="","",'IND-08'!F53),"") | AT15: =IFERROR(IF('IND-08'!F54="","",'IND-08'!F54),"") | AU15: =IFERROR(IF('IND-08'!F55="","",'IND-08'!F55),"") | AV15: =IFERROR(IF('IND-08'!F56="","",'IND-08'!F56),"") | AW15: =IFERROR(IF('IND-08'!F57="","",'IND-08'!F57),"") | AX15: =IFERROR(IF('IND-08'!F58="","",'IND-08'!F58),"") | AY15: =IFERROR(IF('IND-08'!F59="","",'IND-08'!F59),"") | AZ15: =IFERROR(IF('IND-08'!F60="","",'IND-08'!F60),"") | BA15: =IFERROR(IF('IND-08'!F61="","",'IND-08'!F61),"") | BB15: =IFERROR(IF('IND-08'!F62="","",'IND-08'!F62),"") | BC15: =IFERROR(IF('IND-08'!F63="","",'IND-08'!F63),"") | BD15: =IFERROR(IF('IND-08'!F64="","",'IND-08'!F64),"") | BE15: =IFERROR(IF('IND-08'!F65="","",'IND-08'!F65),"") | BF15: =IFERROR(IF('IND-08'!F66="","",'IND-08'!F66),"") | BG15: =IFERROR(IF('IND-08'!F67="","",'IND-08'!F67),"") | BH15: =IFERROR(IF('IND-08'!F68="","",'IND-08'!F68),"") | BI15: =IFERROR(IF('IND-08'!F69="","",'IND-08'!F69),"") | BJ15: =IFERROR(IF('IND-08'!F70="","",'IND-08'!F70),"") | BK15: =IFERROR(IF('IND-08'!F71="","",'IND-08'!F71),"") | BL15: =IFERROR(IF('IND-08'!F72="","",'IND-08'!F72),"") | BM15: =IFERROR(IF('IND-08'!F73="","",'IND-08'!F73),"") | BN15: =IFERROR(IF('IND-08'!F74="","",'IND-08'!F74),"") | BO15: =IFERROR(IF('IND-08'!F75="","",'IND-08'!F75),"") | BP15: =IFERROR(IF('IND-08'!F76="","",'IND-08'!F76),"") | BQ15: =IFERROR(IF('IND-08'!F77="","",'IND-08'!F77),"") | BR15: =IFERROR(IF('IND-08'!F78="","",'IND-08'!F78),"") | BS15: =IFERROR(IF('IND-08'!F79="","",'IND-08'!F79),"") | BT15: =IFERROR(IF('IND-08'!F80="","",'IND-08'!F80),"") | BU15: =IFERROR(IF('IND-08'!F81="","",'IND-08'!F81),"") | BV15: =IFERROR(IF('IND-08'!F82="","",'IND-08'!F82),"") | BW15: =IFERROR(AVERAGE('IND-08'!H23:H34),"") | BX15: =IFERROR(AVERAGE('IND-08'!H35:H46),"") | BY15: =IFERROR(AVERAGE('IND-08'!H47:H58),"") | BZ15: =IFERROR(AVERAGE('IND-08'!H59:H70),"") | CA15: =IFERROR(AVERAGE('IND-08'!H71:H82),"") | CB15: =IFERROR(IF(LOOKUP(2,1/((BW15:CA15<>"")*(ISNUMBER(BW15:CA15))),BW15:CA15)>=0.95,"🟢 Cumple",IF(LOOKUP(2,1/((BW15:CA15<>"")*(ISNUMBER(BW15:CA15))),BW15:CA15)>=0.8,"🟡 En riesgo","🔴 Crítico")),"⚪ Pendiente") -> ⚪ Pendiente
B16: Crecimiento y remuneración de depósitos | C16: Rentabilidad real de los depósitos | D16: Tasa promedio ponderada ahorros − IPC | E16: Asegura que la tasa de rendimiento de los depósitos supere la inflación (poder adquisitivo del ahorro). | F16: % vs IPC | G16: Mantener | H16: Mensual | I16: =VLOOKUP("IND-09",Parámetros!$B$6:$F$30,5,FALSE()) -> Por definir | J16: ='IND-09'!C14 -> 0 | K16: ='IND-09'!C15 -> 0 | L16: ='IND-09'!C16 -> 0 | M16: ='IND-09'!C17 -> 0 | N16: ='IND-09'!C18 -> 0 | O16: =IFERROR(IF('IND-09'!G23="","",'IND-09'!G23),"") | P16: =IFERROR(IF('IND-09'!G24="","",'IND-09'!G24),"") | Q16: =IFERROR(IF('IND-09'!G25="","",'IND-09'!G25),"") | R16: =IFERROR(IF('IND-09'!G26="","",'IND-09'!G26),"") | S16: =IFERROR(IF('IND-09'!G27="","",'IND-09'!G27),"") | T16: =IFERROR(IF('IND-09'!G28="","",'IND-09'!G28),"") | U16: =IFERROR(IF('IND-09'!G29="","",'IND-09'!G29),"") | V16: =IFERROR(IF('IND-09'!G30="","",'IND-09'!G30),"") | W16: =IFERROR(IF('IND-09'!G31="","",'IND-09'!G31),"") | X16: =IFERROR(IF('IND-09'!G32="","",'IND-09'!G32),"") | Y16: =IFERROR(IF('IND-09'!G33="","",'IND-09'!G33),"") | Z16: =IFERROR(IF('IND-09'!G34="","",'IND-09'!G34),"") | AA16: =IFERROR(IF('IND-09'!G35="","",'IND-09'!G35),"") | AB16: =IFERROR(IF('IND-09'!G36="","",'IND-09'!G36),"") | AC16: =IFERROR(IF('IND-09'!G37="","",'IND-09'!G37),"") | AD16: =IFERROR(IF('IND-09'!G38="","",'IND-09'!G38),"") | AE16: =IFERROR(IF('IND-09'!G39="","",'IND-09'!G39),"") | AF16: =IFERROR(IF('IND-09'!G40="","",'IND-09'!G40),"") | AG16: =IFERROR(IF('IND-09'!G41="","",'IND-09'!G41),"") | AH16: =IFERROR(IF('IND-09'!G42="","",'IND-09'!G42),"") | AI16: =IFERROR(IF('IND-09'!G43="","",'IND-09'!G43),"") | AJ16: =IFERROR(IF('IND-09'!G44="","",'IND-09'!G44),"") | AK16: =IFERROR(IF('IND-09'!G45="","",'IND-09'!G45),"") | AL16: =IFERROR(IF('IND-09'!G46="","",'IND-09'!G46),"") | AM16: =IFERROR(IF('IND-09'!G47="","",'IND-09'!G47),"") | AN16: =IFERROR(IF('IND-09'!G48="","",'IND-09'!G48),"") | AO16: =IFERROR(IF('IND-09'!G49="","",'IND-09'!G49),"") | AP16: =IFERROR(IF('IND-09'!G50="","",'IND-09'!G50),"") | AQ16: =IFERROR(IF('IND-09'!G51="","",'IND-09'!G51),"") | AR16: =IFERROR(IF('IND-09'!G52="","",'IND-09'!G52),"") | AS16: =IFERROR(IF('IND-09'!G53="","",'IND-09'!G53),"") | AT16: =IFERROR(IF('IND-09'!G54="","",'IND-09'!G54),"") | AU16: =IFERROR(IF('IND-09'!G55="","",'IND-09'!G55),"") | AV16: =IFERROR(IF('IND-09'!G56="","",'IND-09'!G56),"") | AW16: =IFERROR(IF('IND-09'!G57="","",'IND-09'!G57),"") | AX16: =IFERROR(IF('IND-09'!G58="","",'IND-09'!G58),"") | AY16: =IFERROR(IF('IND-09'!G59="","",'IND-09'!G59),"") | AZ16: =IFERROR(IF('IND-09'!G60="","",'IND-09'!G60),"") | BA16: =IFERROR(IF('IND-09'!G61="","",'IND-09'!G61),"") | BB16: =IFERROR(IF('IND-09'!G62="","",'IND-09'!G62),"") | BC16: =IFERROR(IF('IND-09'!G63="","",'IND-09'!G63),"") | BD16: =IFERROR(IF('IND-09'!G64="","",'IND-09'!G64),"") | BE16: =IFERROR(IF('IND-09'!G65="","",'IND-09'!G65),"") | BF16: =IFERROR(IF('IND-09'!G66="","",'IND-09'!G66),"") | BG16: =IFERROR(IF('IND-09'!G67="","",'IND-09'!G67),"") | BH16: =IFERROR(IF('IND-09'!G68="","",'IND-09'!G68),"") | BI16: =IFERROR(IF('IND-09'!G69="","",'IND-09'!G69),"") | BJ16: =IFERROR(IF('IND-09'!G70="","",'IND-09'!G70),"") | BK16: =IFERROR(IF('IND-09'!G71="","",'IND-09'!G71),"") | BL16: =IFERROR(IF('IND-09'!G72="","",'IND-09'!G72),"") | BM16: =IFERROR(IF('IND-09'!G73="","",'IND-09'!G73),"") | BN16: =IFERROR(IF('IND-09'!G74="","",'IND-09'!G74),"") | BO16: =IFERROR(IF('IND-09'!G75="","",'IND-09'!G75),"") | BP16: =IFERROR(IF('IND-09'!G76="","",'IND-09'!G76),"") | BQ16: =IFERROR(IF('IND-09'!G77="","",'IND-09'!G77),"") | BR16: =IFERROR(IF('IND-09'!G78="","",'IND-09'!G78),"") | BS16: =IFERROR(IF('IND-09'!G79="","",'IND-09'!G79),"") | BT16: =IFERROR(IF('IND-09'!G80="","",'IND-09'!G80),"") | BU16: =IFERROR(IF('IND-09'!G81="","",'IND-09'!G81),"") | BV16: =IFERROR(IF('IND-09'!G82="","",'IND-09'!G82),"") | BW16: =IFERROR(AVERAGE('IND-09'!I23:I34),"") | BX16: =IFERROR(AVERAGE('IND-09'!I35:I46),"") | BY16: =IFERROR(AVERAGE('IND-09'!I47:I58),"") | BZ16: =IFERROR(AVERAGE('IND-09'!I59:I70),"") | CA16: =IFERROR(AVERAGE('IND-09'!I71:I82),"") | CB16: =IFERROR(IF(LOOKUP(2,1/((BW16:CA16<>"")*(ISNUMBER(BW16:CA16))),BW16:CA16)>=0.95,"🟢 Cumple",IF(LOOKUP(2,1/((BW16:CA16<>"")*(ISNUMBER(BW16:CA16))),BW16:CA16)>=0.8,"🟡 En riesgo","🔴 Crítico")),"⚪ Pendiente") -> ⚪ Pendiente
B17: Rentabilidad y fortalecimiento patrimonial | C17: Suficiencia del Margen | D17: Margen financiero bruto ÷ Gastos operativos | E17: Evalúa la capacidad del margen financiero bruto para cubrir los gastos operativos. | F17: Veces (x) | G17: Mantener | H17: Mensual | I17: =VLOOKUP("IND-10",Parámetros!$B$6:$F$30,5,FALSE()) -> Por definir | J17: ='IND-10'!C14 -> 1.2 | K17: ='IND-10'!C15 -> 1.2 | L17: ='IND-10'!C16 -> 1.2 | M17: ='IND-10'!C17 -> 1.2 | N17: ='IND-10'!C18 -> 1.2 | O17: =IFERROR(IF('IND-10'!G23="","",'IND-10'!G23),"") | P17: =IFERROR(IF('IND-10'!G24="","",'IND-10'!G24),"") | Q17: =IFERROR(IF('IND-10'!G25="","",'IND-10'!G25),"") | R17: =IFERROR(IF('IND-10'!G26="","",'IND-10'!G26),"") | S17: =IFERROR(IF('IND-10'!G27="","",'IND-10'!G27),"") | T17: =IFERROR(IF('IND-10'!G28="","",'IND-10'!G28),"") | U17: =IFERROR(IF('IND-10'!G29="","",'IND-10'!G29),"") | V17: =IFERROR(IF('IND-10'!G30="","",'IND-10'!G30),"") | W17: =IFERROR(IF('IND-10'!G31="","",'IND-10'!G31),"") | X17: =IFERROR(IF('IND-10'!G32="","",'IND-10'!G32),"") | Y17: =IFERROR(IF('IND-10'!G33="","",'IND-10'!G33),"") | Z17: =IFERROR(IF('IND-10'!G34="","",'IND-10'!G34),"") | AA17: =IFERROR(IF('IND-10'!G35="","",'IND-10'!G35),"") | AB17: =IFERROR(IF('IND-10'!G36="","",'IND-10'!G36),"") | AC17: =IFERROR(IF('IND-10'!G37="","",'IND-10'!G37),"") | AD17: =IFERROR(IF('IND-10'!G38="","",'IND-10'!G38),"") | AE17: =IFERROR(IF('IND-10'!G39="","",'IND-10'!G39),"") | AF17: =IFERROR(IF('IND-10'!G40="","",'IND-10'!G40),"") | AG17: =IFERROR(IF('IND-10'!G41="","",'IND-10'!G41),"") | AH17: =IFERROR(IF('IND-10'!G42="","",'IND-10'!G42),"") | AI17: =IFERROR(IF('IND-10'!G43="","",'IND-10'!G43),"") | AJ17: =IFERROR(IF('IND-10'!G44="","",'IND-10'!G44),"") | AK17: =IFERROR(IF('IND-10'!G45="","",'IND-10'!G45),"") | AL17: =IFERROR(IF('IND-10'!G46="","",'IND-10'!G46),"") | AM17: =IFERROR(IF('IND-10'!G47="","",'IND-10'!G47),"") | AN17: =IFERROR(IF('IND-10'!G48="","",'IND-10'!G48),"") | AO17: =IFERROR(IF('IND-10'!G49="","",'IND-10'!G49),"") | AP17: =IFERROR(IF('IND-10'!G50="","",'IND-10'!G50),"") | AQ17: =IFERROR(IF('IND-10'!G51="","",'IND-10'!G51),"") | AR17: =IFERROR(IF('IND-10'!G52="","",'IND-10'!G52),"") | AS17: =IFERROR(IF('IND-10'!G53="","",'IND-10'!G53),"") | AT17: =IFERROR(IF('IND-10'!G54="","",'IND-10'!G54),"") | AU17: =IFERROR(IF('IND-10'!G55="","",'IND-10'!G55),"") | AV17: =IFERROR(IF('IND-10'!G56="","",'IND-10'!G56),"") | AW17: =IFERROR(IF('IND-10'!G57="","",'IND-10'!G57),"") | AX17: =IFERROR(IF('IND-10'!G58="","",'IND-10'!G58),"") | AY17: =IFERROR(IF('IND-10'!G59="","",'IND-10'!G59),"") | AZ17: =IFERROR(IF('IND-10'!G60="","",'IND-10'!G60),"") | BA17: =IFERROR(IF('IND-10'!G61="","",'IND-10'!G61),"") | BB17: =IFERROR(IF('IND-10'!G62="","",'IND-10'!G62),"") | BC17: =IFERROR(IF('IND-10'!G63="","",'IND-10'!G63),"") | BD17: =IFERROR(IF('IND-10'!G64="","",'IND-10'!G64),"") | BE17: =IFERROR(IF('IND-10'!G65="","",'IND-10'!G65),"") | BF17: =IFERROR(IF('IND-10'!G66="","",'IND-10'!G66),"") | BG17: =IFERROR(IF('IND-10'!G67="","",'IND-10'!G67),"") | BH17: =IFERROR(IF('IND-10'!G68="","",'IND-10'!G68),"") | BI17: =IFERROR(IF('IND-10'!G69="","",'IND-10'!G69),"") | BJ17: =IFERROR(IF('IND-10'!G70="","",'IND-10'!G70),"") | BK17: =IFERROR(IF('IND-10'!G71="","",'IND-10'!G71),"") | BL17: =IFERROR(IF('IND-10'!G72="","",'IND-10'!G72),"") | BM17: =IFERROR(IF('IND-10'!G73="","",'IND-10'!G73),"") | BN17: =IFERROR(IF('IND-10'!G74="","",'IND-10'!G74),"") | BO17: =IFERROR(IF('IND-10'!G75="","",'IND-10'!G75),"") | BP17: =IFERROR(IF('IND-10'!G76="","",'IND-10'!G76),"") | BQ17: =IFERROR(IF('IND-10'!G77="","",'IND-10'!G77),"") | BR17: =IFERROR(IF('IND-10'!G78="","",'IND-10'!G78),"") | BS17: =IFERROR(IF('IND-10'!G79="","",'IND-10'!G79),"") | BT17: =IFERROR(IF('IND-10'!G80="","",'IND-10'!G80),"") | BU17: =IFERROR(IF('IND-10'!G81="","",'IND-10'!G81),"") | BV17: =IFERROR(IF('IND-10'!G82="","",'IND-10'!G82),"") | BW17: =IFERROR(AVERAGE('IND-10'!I23:I34),"") | BX17: =IFERROR(AVERAGE('IND-10'!I35:I46),"") | BY17: =IFERROR(AVERAGE('IND-10'!I47:I58),"") | BZ17: =IFERROR(AVERAGE('IND-10'!I59:I70),"") | CA17: =IFERROR(AVERAGE('IND-10'!I71:I82),"") | CB17: =IFERROR(IF(LOOKUP(2,1/((BW17:CA17<>"")*(ISNUMBER(BW17:CA17))),BW17:CA17)>=0.95,"🟢 Cumple",IF(LOOKUP(2,1/((BW17:CA17<>"")*(ISNUMBER(BW17:CA17))),BW17:CA17)>=0.8,"🟡 En riesgo","🔴 Crítico")),"⚪ Pendiente") -> ⚪ Pendiente
B18: Rentabilidad y fortalecimiento patrimonial | C18: Cumplimiento de pago de aportes sociales | D18: Recaudo real de aportes ÷ Recaudo esperado de aportes | E18: Mide el grado de cumplimiento del recaudo mensual de aportes frente al esperado. | F18: % | G18: Mantener | H18: Mensual | I18: =VLOOKUP("IND-11",Parámetros!$B$6:$F$30,5,FALSE()) -> Por definir | J18: ='IND-11'!C14 -> 0.95 | K18: ='IND-11'!C15 -> 0.95 | L18: ='IND-11'!C16 -> 0.95 | M18: ='IND-11'!C17 -> 0.95 | N18: ='IND-11'!C18 -> 0.95 | O18: =IFERROR(IF('IND-11'!G23="","",'IND-11'!G23),"") | P18: =IFERROR(IF('IND-11'!G24="","",'IND-11'!G24),"") | Q18: =IFERROR(IF('IND-11'!G25="","",'IND-11'!G25),"") | R18: =IFERROR(IF('IND-11'!G26="","",'IND-11'!G26),"") | S18: =IFERROR(IF('IND-11'!G27="","",'IND-11'!G27),"") | T18: =IFERROR(IF('IND-11'!G28="","",'IND-11'!G28),"") | U18: =IFERROR(IF('IND-11'!G29="","",'IND-11'!G29),"") | V18: =IFERROR(IF('IND-11'!G30="","",'IND-11'!G30),"") | W18: =IFERROR(IF('IND-11'!G31="","",'IND-11'!G31),"") | X18: =IFERROR(IF('IND-11'!G32="","",'IND-11'!G32),"") | Y18: =IFERROR(IF('IND-11'!G33="","",'IND-11'!G33),"") | Z18: =IFERROR(IF('IND-11'!G34="","",'IND-11'!G34),"") | AA18: =IFERROR(IF('IND-11'!G35="","",'IND-11'!G35),"") | AB18: =IFERROR(IF('IND-11'!G36="","",'IND-11'!G36),"") | AC18: =IFERROR(IF('IND-11'!G37="","",'IND-11'!G37),"") | AD18: =IFERROR(IF('IND-11'!G38="","",'IND-11'!G38),"") | AE18: =IFERROR(IF('IND-11'!G39="","",'IND-11'!G39),"") | AF18: =IFERROR(IF('IND-11'!G40="","",'IND-11'!G40),"") | AG18: =IFERROR(IF('IND-11'!G41="","",'IND-11'!G41),"") | AH18: =IFERROR(IF('IND-11'!G42="","",'IND-11'!G42),"") | AI18: =IFERROR(IF('IND-11'!G43="","",'IND-11'!G43),"") | AJ18: =IFERROR(IF('IND-11'!G44="","",'IND-11'!G44),"") | AK18: =IFERROR(IF('IND-11'!G45="","",'IND-11'!G45),"") | AL18: =IFERROR(IF('IND-11'!G46="","",'IND-11'!G46),"") | AM18: =IFERROR(IF('IND-11'!G47="","",'IND-11'!G47),"") | AN18: =IFERROR(IF('IND-11'!G48="","",'IND-11'!G48),"") | AO18: =IFERROR(IF('IND-11'!G49="","",'IND-11'!G49),"") | AP18: =IFERROR(IF('IND-11'!G50="","",'IND-11'!G50),"") | AQ18: =IFERROR(IF('IND-11'!G51="","",'IND-11'!G51),"") | AR18: =IFERROR(IF('IND-11'!G52="","",'IND-11'!G52),"") | AS18: =IFERROR(IF('IND-11'!G53="","",'IND-11'!G53),"") | AT18: =IFERROR(IF('IND-11'!G54="","",'IND-11'!G54),"") | AU18: =IFERROR(IF('IND-11'!G55="","",'IND-11'!G55),"") | AV18: =IFERROR(IF('IND-11'!G56="","",'IND-11'!G56),"") | AW18: =IFERROR(IF('IND-11'!G57="","",'IND-11'!G57),"") | AX18: =IFERROR(IF('IND-11'!G58="","",'IND-11'!G58),"") | AY18: =IFERROR(IF('IND-11'!G59="","",'IND-11'!G59),"") | AZ18: =IFERROR(IF('IND-11'!G60="","",'IND-11'!G60),"") | BA18: =IFERROR(IF('IND-11'!G61="","",'IND-11'!G61),"") | BB18: =IFERROR(IF('IND-11'!G62="","",'IND-11'!G62),"") | BC18: =IFERROR(IF('IND-11'!G63="","",'IND-11'!G63),"") | BD18: =IFERROR(IF('IND-11'!G64="","",'IND-11'!G64),"") | BE18: =IFERROR(IF('IND-11'!G65="","",'IND-11'!G65),"") | BF18: =IFERROR(IF('IND-11'!G66="","",'IND-11'!G66),"") | BG18: =IFERROR(IF('IND-11'!G67="","",'IND-11'!G67),"") | BH18: =IFERROR(IF('IND-11'!G68="","",'IND-11'!G68),"") | BI18: =IFERROR(IF('IND-11'!G69="","",'IND-11'!G69),"") | BJ18: =IFERROR(IF('IND-11'!G70="","",'IND-11'!G70),"") | BK18: =IFERROR(IF('IND-11'!G71="","",'IND-11'!G71),"") | BL18: =IFERROR(IF('IND-11'!G72="","",'IND-11'!G72),"") | BM18: =IFERROR(IF('IND-11'!G73="","",'IND-11'!G73),"") | BN18: =IFERROR(IF('IND-11'!G74="","",'IND-11'!G74),"") | BO18: =IFERROR(IF('IND-11'!G75="","",'IND-11'!G75),"") | BP18: =IFERROR(IF('IND-11'!G76="","",'IND-11'!G76),"") | BQ18: =IFERROR(IF('IND-11'!G77="","",'IND-11'!G77),"") | BR18: =IFERROR(IF('IND-11'!G78="","",'IND-11'!G78),"") | BS18: =IFERROR(IF('IND-11'!G79="","",'IND-11'!G79),"") | BT18: =IFERROR(IF('IND-11'!G80="","",'IND-11'!G80),"") | BU18: =IFERROR(IF('IND-11'!G81="","",'IND-11'!G81),"") | BV18: =IFERROR(IF('IND-11'!G82="","",'IND-11'!G82),"") | BW18: =IFERROR(AVERAGE('IND-11'!I23:I34),"") | BX18: =IFERROR(AVERAGE('IND-11'!I35:I46),"") | BY18: =IFERROR(AVERAGE('IND-11'!I47:I58),"") | BZ18: =IFERROR(AVERAGE('IND-11'!I59:I70),"") | CA18: =IFERROR(AVERAGE('IND-11'!I71:I82),"") | CB18: =IFERROR(IF(LOOKUP(2,1/((BW18:CA18<>"")*(ISNUMBER(BW18:CA18))),BW18:CA18)>=0.95,"🟢 Cumple",IF(LOOKUP(2,1/((BW18:CA18<>"")*(ISNUMBER(BW18:CA18))),BW18:CA18)>=0.8,"🟡 En riesgo","🔴 Crítico")),"⚪ Pendiente") -> ⚪ Pendiente
B19: Rentabilidad y fortalecimiento patrimonial | C19: Capital institucional | D19: (Aportes amortizados + Reserva protección aportes + Excedente mes) ÷ Activo | E19: Mide la proporción del patrimonio permanente frente al total de activos. | F19: % | G19: Mantener | H19: Mensual | I19: =VLOOKUP("IND-12",Parámetros!$B$6:$F$30,5,FALSE()) -> Por definir | J19: ='IND-12'!C14 -> 0.15 | K19: ='IND-12'!C15 -> 0.15 | L19: ='IND-12'!C16 -> 0.15 | M19: ='IND-12'!C17 -> 0.15 | N19: ='IND-12'!C18 -> 0.15 | O19: =IFERROR(IF('IND-12'!I23="","",'IND-12'!I23),"") | P19: =IFERROR(IF('IND-12'!I24="","",'IND-12'!I24),"") | Q19: =IFERROR(IF('IND-12'!I25="","",'IND-12'!I25),"") | R19: =IFERROR(IF('IND-12'!I26="","",'IND-12'!I26),"") | S19: =IFERROR(IF('IND-12'!I27="","",'IND-12'!I27),"") | T19: =IFERROR(IF('IND-12'!I28="","",'IND-12'!I28),"") | U19: =IFERROR(IF('IND-12'!I29="","",'IND-12'!I29),"") | V19: =IFERROR(IF('IND-12'!I30="","",'IND-12'!I30),"") | W19: =IFERROR(IF('IND-12'!I31="","",'IND-12'!I31),"") | X19: =IFERROR(IF('IND-12'!I32="","",'IND-12'!I32),"") | Y19: =IFERROR(IF('IND-12'!I33="","",'IND-12'!I33),"") | Z19: =IFERROR(IF('IND-12'!I34="","",'IND-12'!I34),"") | AA19: =IFERROR(IF('IND-12'!I35="","",'IND-12'!I35),"") | AB19: =IFERROR(IF('IND-12'!I36="","",'IND-12'!I36),"") | AC19: =IFERROR(IF('IND-12'!I37="","",'IND-12'!I37),"") | AD19: =IFERROR(IF('IND-12'!I38="","",'IND-12'!I38),"") | AE19: =IFERROR(IF('IND-12'!I39="","",'IND-12'!I39),"") | AF19: =IFERROR(IF('IND-12'!I40="","",'IND-12'!I40),"") | AG19: =IFERROR(IF('IND-12'!I41="","",'IND-12'!I41),"") | AH19: =IFERROR(IF('IND-12'!I42="","",'IND-12'!I42),"") | AI19: =IFERROR(IF('IND-12'!I43="","",'IND-12'!I43),"") | AJ19: =IFERROR(IF('IND-12'!I44="","",'IND-12'!I44),"") | AK19: =IFERROR(IF('IND-12'!I45="","",'IND-12'!I45),"") | AL19: =IFERROR(IF('IND-12'!I46="","",'IND-12'!I46),"") | AM19: =IFERROR(IF('IND-12'!I47="","",'IND-12'!I47),"") | AN19: =IFERROR(IF('IND-12'!I48="","",'IND-12'!I48),"") | AO19: =IFERROR(IF('IND-12'!I49="","",'IND-12'!I49),"") | AP19: =IFERROR(IF('IND-12'!I50="","",'IND-12'!I50),"") | AQ19: =IFERROR(IF('IND-12'!I51="","",'IND-12'!I51),"") | AR19: =IFERROR(IF('IND-12'!I52="","",'IND-12'!I52),"") | AS19: =IFERROR(IF('IND-12'!I53="","",'IND-12'!I53),"") | AT19: =IFERROR(IF('IND-12'!I54="","",'IND-12'!I54),"") | AU19: =IFERROR(IF('IND-12'!I55="","",'IND-12'!I55),"") | AV19: =IFERROR(IF('IND-12'!I56="","",'IND-12'!I56),"") | AW19: =IFERROR(IF('IND-12'!I57="","",'IND-12'!I57),"") | AX19: =IFERROR(IF('IND-12'!I58="","",'IND-12'!I58),"") | AY19: =IFERROR(IF('IND-12'!I59="","",'IND-12'!I59),"") | AZ19: =IFERROR(IF('IND-12'!I60="","",'IND-12'!I60),"") | BA19: =IFERROR(IF('IND-12'!I61="","",'IND-12'!I61),"") | BB19: =IFERROR(IF('IND-12'!I62="","",'IND-12'!I62),"") | BC19: =IFERROR(IF('IND-12'!I63="","",'IND-12'!I63),"") | BD19: =IFERROR(IF('IND-12'!I64="","",'IND-12'!I64),"") | BE19: =IFERROR(IF('IND-12'!I65="","",'IND-12'!I65),"") | BF19: =IFERROR(IF('IND-12'!I66="","",'IND-12'!I66),"") | BG19: =IFERROR(IF('IND-12'!I67="","",'IND-12'!I67),"") | BH19: =IFERROR(IF('IND-12'!I68="","",'IND-12'!I68),"") | BI19: =IFERROR(IF('IND-12'!I69="","",'IND-12'!I69),"") | BJ19: =IFERROR(IF('IND-12'!I70="","",'IND-12'!I70),"") | BK19: =IFERROR(IF('IND-12'!I71="","",'IND-12'!I71),"") | BL19: =IFERROR(IF('IND-12'!I72="","",'IND-12'!I72),"") | BM19: =IFERROR(IF('IND-12'!I73="","",'IND-12'!I73),"") | BN19: =IFERROR(IF('IND-12'!I74="","",'IND-12'!I74),"") | BO19: =IFERROR(IF('IND-12'!I75="","",'IND-12'!I75),"") | BP19: =IFERROR(IF('IND-12'!I76="","",'IND-12'!I76),"") | BQ19: =IFERROR(IF('IND-12'!I77="","",'IND-12'!I77),"") | BR19: =IFERROR(IF('IND-12'!I78="","",'IND-12'!I78),"") | BS19: =IFERROR(IF('IND-12'!I79="","",'IND-12'!I79),"") | BT19: =IFERROR(IF('IND-12'!I80="","",'IND-12'!I80),"") | BU19: =IFERROR(IF('IND-12'!I81="","",'IND-12'!I81),"") | BV19: =IFERROR(IF('IND-12'!I82="","",'IND-12'!I82),"") | BW19: =IFERROR(AVERAGE('IND-12'!K23:K34),"") | BX19: =IFERROR(AVERAGE('IND-12'!K35:K46),"") | BY19: =IFERROR(AVERAGE('IND-12'!K47:K58),"") | BZ19: =IFERROR(AVERAGE('IND-12'!K59:K70),"") | CA19: =IFERROR(AVERAGE('IND-12'!K71:K82),"") | CB19: =IFERROR(IF(LOOKUP(2,1/((BW19:CA19<>"")*(ISNUMBER(BW19:CA19))),BW19:CA19)>=0.95,"🟢 Cumple",IF(LOOKUP(2,1/((BW19:CA19<>"")*(ISNUMBER(BW19:CA19))),BW19:CA19)>=0.8,"🟡 En riesgo","🔴 Crítico")),"⚪ Pendiente") -> ⚪ Pendiente
B20: Rentabilidad y fortalecimiento patrimonial | C20: ROE | D20: Excedente ÷ Patrimonio | E20: Rentabilidad sobre el patrimonio. | F20: % | G20: Mantener | H20: Mensual | I20: =VLOOKUP("IND-13",Parámetros!$B$6:$F$30,5,FALSE()) -> Por definir | J20: ='IND-13'!C14 -> > IPC | K20: ='IND-13'!C15 -> > IPC | L20: ='IND-13'!C16 -> > IPC | M20: ='IND-13'!C17 -> > IPC | N20: ='IND-13'!C18 -> > IPC | O20: =IFERROR(IF('IND-13'!G23="","",'IND-13'!G23),"") | P20: =IFERROR(IF('IND-13'!G24="","",'IND-13'!G24),"") | Q20: =IFERROR(IF('IND-13'!G25="","",'IND-13'!G25),"") | R20: =IFERROR(IF('IND-13'!G26="","",'IND-13'!G26),"") | S20: =IFERROR(IF('IND-13'!G27="","",'IND-13'!G27),"") | T20: =IFERROR(IF('IND-13'!G28="","",'IND-13'!G28),"") | U20: =IFERROR(IF('IND-13'!G29="","",'IND-13'!G29),"") | V20: =IFERROR(IF('IND-13'!G30="","",'IND-13'!G30),"") | W20: =IFERROR(IF('IND-13'!G31="","",'IND-13'!G31),"") | X20: =IFERROR(IF('IND-13'!G32="","",'IND-13'!G32),"") | Y20: =IFERROR(IF('IND-13'!G33="","",'IND-13'!G33),"") | Z20: =IFERROR(IF('IND-13'!G34="","",'IND-13'!G34),"") | AA20: =IFERROR(IF('IND-13'!G35="","",'IND-13'!G35),"") | AB20: =IFERROR(IF('IND-13'!G36="","",'IND-13'!G36),"") | AC20: =IFERROR(IF('IND-13'!G37="","",'IND-13'!G37),"") | AD20: =IFERROR(IF('IND-13'!G38="","",'IND-13'!G38),"") | AE20: =IFERROR(IF('IND-13'!G39="","",'IND-13'!G39),"") | AF20: =IFERROR(IF('IND-13'!G40="","",'IND-13'!G40),"") | AG20: =IFERROR(IF('IND-13'!G41="","",'IND-13'!G41),"") | AH20: =IFERROR(IF('IND-13'!G42="","",'IND-13'!G42),"") | AI20: =IFERROR(IF('IND-13'!G43="","",'IND-13'!G43),"") | AJ20: =IFERROR(IF('IND-13'!G44="","",'IND-13'!G44),"") | AK20: =IFERROR(IF('IND-13'!G45="","",'IND-13'!G45),"") | AL20: =IFERROR(IF('IND-13'!G46="","",'IND-13'!G46),"") | AM20: =IFERROR(IF('IND-13'!G47="","",'IND-13'!G47),"") | AN20: =IFERROR(IF('IND-13'!G48="","",'IND-13'!G48),"") | AO20: =IFERROR(IF('IND-13'!G49="","",'IND-13'!G49),"") | AP20: =IFERROR(IF('IND-13'!G50="","",'IND-13'!G50),"") | AQ20: =IFERROR(IF('IND-13'!G51="","",'IND-13'!G51),"") | AR20: =IFERROR(IF('IND-13'!G52="","",'IND-13'!G52),"") | AS20: =IFERROR(IF('IND-13'!G53="","",'IND-13'!G53),"") | AT20: =IFERROR(IF('IND-13'!G54="","",'IND-13'!G54),"") | AU20: =IFERROR(IF('IND-13'!G55="","",'IND-13'!G55),"") | AV20: =IFERROR(IF('IND-13'!G56="","",'IND-13'!G56),"") | AW20: =IFERROR(IF('IND-13'!G57="","",'IND-13'!G57),"") | AX20: =IFERROR(IF('IND-13'!G58="","",'IND-13'!G58),"") | AY20: =IFERROR(IF('IND-13'!G59="","",'IND-13'!G59),"") | AZ20: =IFERROR(IF('IND-13'!G60="","",'IND-13'!G60),"") | BA20: =IFERROR(IF('IND-13'!G61="","",'IND-13'!G61),"") | BB20: =IFERROR(IF('IND-13'!G62="","",'IND-13'!G62),"") | BC20: =IFERROR(IF('IND-13'!G63="","",'IND-13'!G63),"") | BD20: =IFERROR(IF('IND-13'!G64="","",'IND-13'!G64),"") | BE20: =IFERROR(IF('IND-13'!G65="","",'IND-13'!G65),"") | BF20: =IFERROR(IF('IND-13'!G66="","",'IND-13'!G66),"") | BG20: =IFERROR(IF('IND-13'!G67="","",'IND-13'!G67),"") | BH20: =IFERROR(IF('IND-13'!G68="","",'IND-13'!G68),"") | BI20: =IFERROR(IF('IND-13'!G69="","",'IND-13'!G69),"") | BJ20: =IFERROR(IF('IND-13'!G70="","",'IND-13'!G70),"") | BK20: =IFERROR(IF('IND-13'!G71="","",'IND-13'!G71),"") | BL20: =IFERROR(IF('IND-13'!G72="","",'IND-13'!G72),"") | BM20: =IFERROR(IF('IND-13'!G73="","",'IND-13'!G73),"") | BN20: =IFERROR(IF('IND-13'!G74="","",'IND-13'!G74),"") | BO20: =IFERROR(IF('IND-13'!G75="","",'IND-13'!G75),"") | BP20: =IFERROR(IF('IND-13'!G76="","",'IND-13'!G76),"") | BQ20: =IFERROR(IF('IND-13'!G77="","",'IND-13'!G77),"") | BR20: =IFERROR(IF('IND-13'!G78="","",'IND-13'!G78),"") | BS20: =IFERROR(IF('IND-13'!G79="","",'IND-13'!G79),"") | BT20: =IFERROR(IF('IND-13'!G80="","",'IND-13'!G80),"") | BU20: =IFERROR(IF('IND-13'!G81="","",'IND-13'!G81),"") | BV20: =IFERROR(IF('IND-13'!G82="","",'IND-13'!G82),"") | BW20: =IFERROR(AVERAGE('IND-13'!I23:I34),"") | BX20: =IFERROR(AVERAGE('IND-13'!I35:I46),"") | BY20: =IFERROR(AVERAGE('IND-13'!I47:I58),"") | BZ20: =IFERROR(AVERAGE('IND-13'!I59:I70),"") | CA20: =IFERROR(AVERAGE('IND-13'!I71:I82),"") | CB20: =IFERROR(IF(LOOKUP(2,1/((BW20:CA20<>"")*(ISNUMBER(BW20:CA20))),BW20:CA20)>=0.95,"🟢 Cumple",IF(LOOKUP(2,1/((BW20:CA20<>"")*(ISNUMBER(BW20:CA20))),BW20:CA20)>=0.8,"🟡 En riesgo","🔴 Crítico")),"⚪ Pendiente") -> ⚪ Pendiente
B21: 🤝 PERSPECTIVA ASOCIADOS
B22: Crecimiento de la base social | C22: Crecimiento de la base social | D22: ((Asociados periodo actual − periodo anterior) ÷ periodo anterior); meta = total asociados | E22: Evalúa el incremento de asociados y el cumplimiento de la meta de base social. | F22: N° asociados | G22: Crecer | H22: Semestral | I22: =VLOOKUP("IND-14",Parámetros!$B$6:$F$30,5,FALSE()) -> Por definir | J22: ='IND-14'!C14 -> 5846 | K22: ='IND-14'!C15 -> 6384 | L22: ='IND-14'!C16 -> 6923 | M22: ='IND-14'!C17 -> 7461 | N22: ='IND-14'!C18 -> 8000 | O22: =IFERROR(IF('IND-14'!F23="","",'IND-14'!F23),"") | P22: =IFERROR(IF('IND-14'!F24="","",'IND-14'!F24),"") | Q22: =IFERROR(IF('IND-14'!F25="","",'IND-14'!F25),"") | R22: =IFERROR(IF('IND-14'!F26="","",'IND-14'!F26),"") | S22: =IFERROR(IF('IND-14'!F27="","",'IND-14'!F27),"") | T22: =IFERROR(IF('IND-14'!F28="","",'IND-14'!F28),"") -> 5500 | U22: =IFERROR(IF('IND-14'!F29="","",'IND-14'!F29),"") | V22: =IFERROR(IF('IND-14'!F30="","",'IND-14'!F30),"") | W22: =IFERROR(IF('IND-14'!F31="","",'IND-14'!F31),"") | X22: =IFERROR(IF('IND-14'!F32="","",'IND-14'!F32),"") | Y22: =IFERROR(IF('IND-14'!F33="","",'IND-14'!F33),"") | Z22: =IFERROR(IF('IND-14'!F34="","",'IND-14'!F34),"") -> 5846 | AA22: =IFERROR(IF('IND-14'!F35="","",'IND-14'!F35),"") | AB22: =IFERROR(IF('IND-14'!F36="","",'IND-14'!F36),"") | AC22: =IFERROR(IF('IND-14'!F37="","",'IND-14'!F37),"") | AD22: =IFERROR(IF('IND-14'!F38="","",'IND-14'!F38),"") | AE22: =IFERROR(IF('IND-14'!F39="","",'IND-14'!F39),"") | AF22: =IFERROR(IF('IND-14'!F40="","",'IND-14'!F40),"") -> 6100 | AG22: =IFERROR(IF('IND-14'!F41="","",'IND-14'!F41),"") | AH22: =IFERROR(IF('IND-14'!F42="","",'IND-14'!F42),"") | AI22: =IFERROR(IF('IND-14'!F43="","",'IND-14'!F43),"") | AJ22: =IFERROR(IF('IND-14'!F44="","",'IND-14'!F44),"") | AK22: =IFERROR(IF('IND-14'!F45="","",'IND-14'!F45),"") | AL22: =IFERROR(IF('IND-14'!F46="","",'IND-14'!F46),"") -> 6384 | AM22: =IFERROR(IF('IND-14'!F47="","",'IND-14'!F47),"") | AN22: =IFERROR(IF('IND-14'!F48="","",'IND-14'!F48),"") | AO22: =IFERROR(IF('IND-14'!F49="","",'IND-14'!F49),"") | AP22: =IFERROR(IF('IND-14'!F50="","",'IND-14'!F50),"") | AQ22: =IFERROR(IF('IND-14'!F51="","",'IND-14'!F51),"") | AR22: =IFERROR(IF('IND-14'!F52="","",'IND-14'!F52),"") | AS22: =IFERROR(IF('IND-14'!F53="","",'IND-14'!F53),"") | AT22: =IFERROR(IF('IND-14'!F54="","",'IND-14'!F54),"") | AU22: =IFERROR(IF('IND-14'!F55="","",'IND-14'!F55),"") | AV22: =IFERROR(IF('IND-14'!F56="","",'IND-14'!F56),"") | AW22: =IFERROR(IF('IND-14'!F57="","",'IND-14'!F57),"") | AX22: =IFERROR(IF('IND-14'!F58="","",'IND-14'!F58),"") | AY22: =IFERROR(IF('IND-14'!F59="","",'IND-14'!F59),"") | AZ22: =IFERROR(IF('IND-14'!F60="","",'IND-14'!F60),"") | BA22: =IFERROR(IF('IND-14'!F61="","",'IND-14'!F61),"") | BB22: =IFERROR(IF('IND-14'!F62="","",'IND-14'!F62),"") | BC22: =IFERROR(IF('IND-14'!F63="","",'IND-14'!F63),"") | BD22: =IFERROR(IF('IND-14'!F64="","",'IND-14'!F64),"") | BE22: =IFERROR(IF('IND-14'!F65="","",'IND-14'!F65),"") | BF22: =IFERROR(IF('IND-14'!F66="","",'IND-14'!F66),"") | BG22: =IFERROR(IF('IND-14'!F67="","",'IND-14'!F67),"") | BH22: =IFERROR(IF('IND-14'!F68="","",'IND-14'!F68),"") | BI22: =IFERROR(IF('IND-14'!F69="","",'IND-14'!F69),"") | BJ22: =IFERROR(IF('IND-14'!F70="","",'IND-14'!F70),"") | BK22: =IFERROR(IF('IND-14'!F71="","",'IND-14'!F71),"") | BL22: =IFERROR(IF('IND-14'!F72="","",'IND-14'!F72),"") | BM22: =IFERROR(IF('IND-14'!F73="","",'IND-14'!F73),"") | BN22: =IFERROR(IF('IND-14'!F74="","",'IND-14'!F74),"") | BO22: =IFERROR(IF('IND-14'!F75="","",'IND-14'!F75),"") | BP22: =IFERROR(IF('IND-14'!F76="","",'IND-14'!F76),"") | BQ22: =IFERROR(IF('IND-14'!F77="","",'IND-14'!F77),"") | BR22: =IFERROR(IF('IND-14'!F78="","",'IND-14'!F78),"") | BS22: =IFERROR(IF('IND-14'!F79="","",'IND-14'!F79),"") | BT22: =IFERROR(IF('IND-14'!F80="","",'IND-14'!F80),"") | BU22: =IFERROR(IF('IND-14'!F81="","",'IND-14'!F81),"") | BV22: =IFERROR(IF('IND-14'!F82="","",'IND-14'!F82),"") | BW22: =IFERROR(AVERAGE('IND-14'!H23:H34),"") -> 0.97040712 | BX22: =IFERROR(AVERAGE('IND-14'!H35:H46),"") -> 0.97775689 | BY22: =IFERROR(AVERAGE('IND-14'!H47:H58),"") | BZ22: =IFERROR(AVERAGE('IND-14'!H59:H70),"") | CA22: =IFERROR(AVERAGE('IND-14'!H71:H82),"") | CB22: =IFERROR(IF(LOOKUP(2,1/((BW22:CA22<>"")*(ISNUMBER(BW22:CA22))),BW22:CA22)>=0.95,"🟢 Cumple",IF(LOOKUP(2,1/((BW22:CA22<>"")*(ISNUMBER(BW22:CA22))),BW22:CA22)>=0.8,"🟡 En riesgo","🔴 Crítico")),"⚪ Pendiente") -> 🟢 Cumple
B23: Retención y profundización | C23: Tasa de retención de asociados anual | D23: (Total asociados final − asociados nuevos) ÷ Total asociados inicial | E23: Mide la capacidad de la cooperativa para mantener su base social activa. | F23: % | G23: Crecer | H23: Anual | I23: =VLOOKUP("IND-15",Parámetros!$B$6:$F$30,5,FALSE()) -> Por definir | J23: ='IND-15'!C14 -> 0.98 | K23: ='IND-15'!C15 -> 0.98 | L23: ='IND-15'!C16 -> 0.98 | M23: ='IND-15'!C17 -> 0.98 | N23: ='IND-15'!C18 -> 0.98 | O23: =IFERROR(IF('IND-15'!H23="","",'IND-15'!H23),"") | P23: =IFERROR(IF('IND-15'!H24="","",'IND-15'!H24),"") | Q23: =IFERROR(IF('IND-15'!H25="","",'IND-15'!H25),"") | R23: =IFERROR(IF('IND-15'!H26="","",'IND-15'!H26),"") | S23: =IFERROR(IF('IND-15'!H27="","",'IND-15'!H27),"") | T23: =IFERROR(IF('IND-15'!H28="","",'IND-15'!H28),"") | U23: =IFERROR(IF('IND-15'!H29="","",'IND-15'!H29),"") | V23: =IFERROR(IF('IND-15'!H30="","",'IND-15'!H30),"") | W23: =IFERROR(IF('IND-15'!H31="","",'IND-15'!H31),"") | X23: =IFERROR(IF('IND-15'!H32="","",'IND-15'!H32),"") | Y23: =IFERROR(IF('IND-15'!H33="","",'IND-15'!H33),"") | Z23: =IFERROR(IF('IND-15'!H34="","",'IND-15'!H34),"") | AA23: =IFERROR(IF('IND-15'!H35="","",'IND-15'!H35),"") | AB23: =IFERROR(IF('IND-15'!H36="","",'IND-15'!H36),"") | AC23: =IFERROR(IF('IND-15'!H37="","",'IND-15'!H37),"") | AD23: =IFERROR(IF('IND-15'!H38="","",'IND-15'!H38),"") | AE23: =IFERROR(IF('IND-15'!H39="","",'IND-15'!H39),"") | AF23: =IFERROR(IF('IND-15'!H40="","",'IND-15'!H40),"") | AG23: =IFERROR(IF('IND-15'!H41="","",'IND-15'!H41),"") | AH23: =IFERROR(IF('IND-15'!H42="","",'IND-15'!H42),"") | AI23: =IFERROR(IF('IND-15'!H43="","",'IND-15'!H43),"") | AJ23: =IFERROR(IF('IND-15'!H44="","",'IND-15'!H44),"") | AK23: =IFERROR(IF('IND-15'!H45="","",'IND-15'!H45),"") | AL23: =IFERROR(IF('IND-15'!H46="","",'IND-15'!H46),"") | AM23: =IFERROR(IF('IND-15'!H47="","",'IND-15'!H47),"") | AN23: =IFERROR(IF('IND-15'!H48="","",'IND-15'!H48),"") | AO23: =IFERROR(IF('IND-15'!H49="","",'IND-15'!H49),"") | AP23: =IFERROR(IF('IND-15'!H50="","",'IND-15'!H50),"") | AQ23: =IFERROR(IF('IND-15'!H51="","",'IND-15'!H51),"") | AR23: =IFERROR(IF('IND-15'!H52="","",'IND-15'!H52),"") | AS23: =IFERROR(IF('IND-15'!H53="","",'IND-15'!H53),"") | AT23: =IFERROR(IF('IND-15'!H54="","",'IND-15'!H54),"") | AU23: =IFERROR(IF('IND-15'!H55="","",'IND-15'!H55),"") | AV23: =IFERROR(IF('IND-15'!H56="","",'IND-15'!H56),"") | AW23: =IFERROR(IF('IND-15'!H57="","",'IND-15'!H57),"") | AX23: =IFERROR(IF('IND-15'!H58="","",'IND-15'!H58),"") | AY23: =IFERROR(IF('IND-15'!H59="","",'IND-15'!H59),"") | AZ23: =IFERROR(IF('IND-15'!H60="","",'IND-15'!H60),"") | BA23: =IFERROR(IF('IND-15'!H61="","",'IND-15'!H61),"") | BB23: =IFERROR(IF('IND-15'!H62="","",'IND-15'!H62),"") | BC23: =IFERROR(IF('IND-15'!H63="","",'IND-15'!H63),"") | BD23: =IFERROR(IF('IND-15'!H64="","",'IND-15'!H64),"") | BE23: =IFERROR(IF('IND-15'!H65="","",'IND-15'!H65),"") | BF23: =IFERROR(IF('IND-15'!H66="","",'IND-15'!H66),"") | BG23: =IFERROR(IF('IND-15'!H67="","",'IND-15'!H67),"") | BH23: =IFERROR(IF('IND-15'!H68="","",'IND-15'!H68),"") | BI23: =IFERROR(IF('IND-15'!H69="","",'IND-15'!H69),"") | BJ23: =IFERROR(IF('IND-15'!H70="","",'IND-15'!H70),"") | BK23: =IFERROR(IF('IND-15'!H71="","",'IND-15'!H71),"") | BL23: =IFERROR(IF('IND-15'!H72="","",'IND-15'!H72),"") | BM23: =IFERROR(IF('IND-15'!H73="","",'IND-15'!H73),"") | BN23: =IFERROR(IF('IND-15'!H74="","",'IND-15'!H74),"") | BO23: =IFERROR(IF('IND-15'!H75="","",'IND-15'!H75),"") | BP23: =IFERROR(IF('IND-15'!H76="","",'IND-15'!H76),"") | BQ23: =IFERROR(IF('IND-15'!H77="","",'IND-15'!H77),"") | BR23: =IFERROR(IF('IND-15'!H78="","",'IND-15'!H78),"") | BS23: =IFERROR(IF('IND-15'!H79="","",'IND-15'!H79),"") | BT23: =IFERROR(IF('IND-15'!H80="","",'IND-15'!H80),"") | BU23: =IFERROR(IF('IND-15'!H81="","",'IND-15'!H81),"") | BV23: =IFERROR(IF('IND-15'!H82="","",'IND-15'!H82),"") | BW23: =IFERROR(AVERAGE('IND-15'!J23:J34),"") | BX23: =IFERROR(AVERAGE('IND-15'!J35:J46),"") | BY23: =IFERROR(AVERAGE('IND-15'!J47:J58),"") | BZ23: =IFERROR(AVERAGE('IND-15'!J59:J70),"") | CA23: =IFERROR(AVERAGE('IND-15'!J71:J82),"") | CB23: =IFERROR(IF(LOOKUP(2,1/((BW23:CA23<>"")*(ISNUMBER(BW23:CA23))),BW23:CA23)>=0.95,"🟢 Cumple",IF(LOOKUP(2,1/((BW23:CA23<>"")*(ISNUMBER(BW23:CA23))),BW23:CA23)>=0.8,"🟡 En riesgo","🔴 Crítico")),"⚪ Pendiente") -> ⚪ Pendiente
B24: Retención y profundización | C24: Índice de satisfacción del asociado | D24: Promedio ponderado de encuestas de satisfacción | E24: Evalúa la percepción del servicio para identificar oportunidades de mejora. | F24: Puntos (escala) | G24: Crecer | H24: Mensual | I24: =VLOOKUP("IND-16",Parámetros!$B$6:$F$30,5,FALSE()) -> Por definir | J24: ='IND-16'!C14 -> 0.95 | K24: ='IND-16'!C15 -> 0.95 | L24: ='IND-16'!C16 -> 0.95 | M24: ='IND-16'!C17 -> 0.95 | N24: ='IND-16'!C18 -> 0.95 | O24: =IFERROR(IF('IND-16'!F23="","",'IND-16'!F23),"") -> 0.92 | P24: =IFERROR(IF('IND-16'!F24="","",'IND-16'!F24),"") -> 0.93 | Q24: =IFERROR(IF('IND-16'!F25="","",'IND-16'!F25),"") -> 0.94 | R24: =IFERROR(IF('IND-16'!F26="","",'IND-16'!F26),"") -> 0.95 | S24: =IFERROR(IF('IND-16'!F27="","",'IND-16'!F27),"") -> 0.96 | T24: =IFERROR(IF('IND-16'!F28="","",'IND-16'!F28),"") -> 0.97 | U24: =IFERROR(IF('IND-16'!F29="","",'IND-16'!F29),"") -> 0.98 | V24: =IFERROR(IF('IND-16'!F30="","",'IND-16'!F30),"") -> 0.99 | W24: =IFERROR(IF('IND-16'!F31="","",'IND-16'!F31),"") -> 1 | X24: =IFERROR(IF('IND-16'!F32="","",'IND-16'!F32),"") -> 1.01 | Y24: =IFERROR(IF('IND-16'!F33="","",'IND-16'!F33),"") -> 1.02 | Z24: =IFERROR(IF('IND-16'!F34="","",'IND-16'!F34),"") -> 1.03 | AA24: =IFERROR(IF('IND-16'!F35="","",'IND-16'!F35),"") | AB24: =IFERROR(IF('IND-16'!F36="","",'IND-16'!F36),"") | AC24: =IFERROR(IF('IND-16'!F37="","",'IND-16'!F37),"") | AD24: =IFERROR(IF('IND-16'!F38="","",'IND-16'!F38),"") | AE24: =IFERROR(IF('IND-16'!F39="","",'IND-16'!F39),"") | AF24: =IFERROR(IF('IND-16'!F40="","",'IND-16'!F40),"") | AG24: =IFERROR(IF('IND-16'!F41="","",'IND-16'!F41),"") | AH24: =IFERROR(IF('IND-16'!F42="","",'IND-16'!F42),"") | AI24: =IFERROR(IF('IND-16'!F43="","",'IND-16'!F43),"") | AJ24: =IFERROR(IF('IND-16'!F44="","",'IND-16'!F44),"") | AK24: =IFERROR(IF('IND-16'!F45="","",'IND-16'!F45),"") | AL24: =IFERROR(IF('IND-16'!F46="","",'IND-16'!F46),"") | AM24: =IFERROR(IF('IND-16'!F47="","",'IND-16'!F47),"") | AN24: =IFERROR(IF('IND-16'!F48="","",'IND-16'!F48),"") | AO24: =IFERROR(IF('IND-16'!F49="","",'IND-16'!F49),"") | AP24: =IFERROR(IF('IND-16'!F50="","",'IND-16'!F50),"") | AQ24: =IFERROR(IF('IND-16'!F51="","",'IND-16'!F51),"") | AR24: =IFERROR(IF('IND-16'!F52="","",'IND-16'!F52),"") | AS24: =IFERROR(IF('IND-16'!F53="","",'IND-16'!F53),"") | AT24: =IFERROR(IF('IND-16'!F54="","",'IND-16'!F54),"") | AU24: =IFERROR(IF('IND-16'!F55="","",'IND-16'!F55),"") | AV24: =IFERROR(IF('IND-16'!F56="","",'IND-16'!F56),"") | AW24: =IFERROR(IF('IND-16'!F57="","",'IND-16'!F57),"") | AX24: =IFERROR(IF('IND-16'!F58="","",'IND-16'!F58),"") | AY24: =IFERROR(IF('IND-16'!F59="","",'IND-16'!F59),"") | AZ24: =IFERROR(IF('IND-16'!F60="","",'IND-16'!F60),"") | BA24: =IFERROR(IF('IND-16'!F61="","",'IND-16'!F61),"") | BB24: =IFERROR(IF('IND-16'!F62="","",'IND-16'!F62),"") | BC24: =IFERROR(IF('IND-16'!F63="","",'IND-16'!F63),"") | BD24: =IFERROR(IF('IND-16'!F64="","",'IND-16'!F64),"") | BE24: =IFERROR(IF('IND-16'!F65="","",'IND-16'!F65),"") | BF24: =IFERROR(IF('IND-16'!F66="","",'IND-16'!F66),"") | BG24: =IFERROR(IF('IND-16'!F67="","",'IND-16'!F67),"") | BH24: =IFERROR(IF('IND-16'!F68="","",'IND-16'!F68),"") | BI24: =IFERROR(IF('IND-16'!F69="","",'IND-16'!F69),"") | BJ24: =IFERROR(IF('IND-16'!F70="","",'IND-16'!F70),"") | BK24: =IFERROR(IF('IND-16'!F71="","",'IND-16'!F71),"") | BL24: =IFERROR(IF('IND-16'!F72="","",'IND-16'!F72),"") | BM24: =IFERROR(IF('IND-16'!F73="","",'IND-16'!F73),"") | BN24: =IFERROR(IF('IND-16'!F74="","",'IND-16'!F74),"") | BO24: =IFERROR(IF('IND-16'!F75="","",'IND-16'!F75),"") | BP24: =IFERROR(IF('IND-16'!F76="","",'IND-16'!F76),"") | BQ24: =IFERROR(IF('IND-16'!F77="","",'IND-16'!F77),"") | BR24: =IFERROR(IF('IND-16'!F78="","",'IND-16'!F78),"") | BS24: =IFERROR(IF('IND-16'!F79="","",'IND-16'!F79),"") | BT24: =IFERROR(IF('IND-16'!F80="","",'IND-16'!F80),"") | BU24: =IFERROR(IF('IND-16'!F81="","",'IND-16'!F81),"") | BV24: =IFERROR(IF('IND-16'!F82="","",'IND-16'!F82),"") | BW24: =IFERROR(AVERAGE('IND-16'!H23:H34),"") -> 1.0263158 | BX24: =IFERROR(AVERAGE('IND-16'!H35:H46),"") | BY24: =IFERROR(AVERAGE('IND-16'!H47:H58),"") | BZ24: =IFERROR(AVERAGE('IND-16'!H59:H70),"") | CA24: =IFERROR(AVERAGE('IND-16'!H71:H82),"") | CB24: =IFERROR(IF(LOOKUP(2,1/((BW24:CA24<>"")*(ISNUMBER(BW24:CA24))),BW24:CA24)>=0.95,"🟢 Cumple",IF(LOOKUP(2,1/((BW24:CA24<>"")*(ISNUMBER(BW24:CA24))),BW24:CA24)>=0.8,"🟡 En riesgo","🔴 Crítico")),"⚪ Pendiente") -> 🟢 Cumple
B25: Retención y profundización | C25: Promedio de productos por asociado | D25: Total de productos activos ÷ Total de asociados activos | E25: Mide el nivel de profundización comercial en la base social. | F25: Productos | G25: Crecer | H25: Mensual | I25: =VLOOKUP("IND-17",Parámetros!$B$6:$F$30,5,FALSE()) -> Por definir | J25: ='IND-17'!C14 -> 3 | K25: ='IND-17'!C15 -> 3 | L25: ='IND-17'!C16 -> 3 | M25: ='IND-17'!C17 -> 3 | N25: ='IND-17'!C18 -> 3 | O25: =IFERROR(IF('IND-17'!G23="","",'IND-17'!G23),"") | P25: =IFERROR(IF('IND-17'!G24="","",'IND-17'!G24),"") | Q25: =IFERROR(IF('IND-17'!G25="","",'IND-17'!G25),"") | R25: =IFERROR(IF('IND-17'!G26="","",'IND-17'!G26),"") | S25: =IFERROR(IF('IND-17'!G27="","",'IND-17'!G27),"") | T25: =IFERROR(IF('IND-17'!G28="","",'IND-17'!G28),"") | U25: =IFERROR(IF('IND-17'!G29="","",'IND-17'!G29),"") | V25: =IFERROR(IF('IND-17'!G30="","",'IND-17'!G30),"") | W25: =IFERROR(IF('IND-17'!G31="","",'IND-17'!G31),"") | X25: =IFERROR(IF('IND-17'!G32="","",'IND-17'!G32),"") | Y25: =IFERROR(IF('IND-17'!G33="","",'IND-17'!G33),"") | Z25: =IFERROR(IF('IND-17'!G34="","",'IND-17'!G34),"") | AA25: =IFERROR(IF('IND-17'!G35="","",'IND-17'!G35),"") | AB25: =IFERROR(IF('IND-17'!G36="","",'IND-17'!G36),"") | AC25: =IFERROR(IF('IND-17'!G37="","",'IND-17'!G37),"") | AD25: =IFERROR(IF('IND-17'!G38="","",'IND-17'!G38),"") | AE25: =IFERROR(IF('IND-17'!G39="","",'IND-17'!G39),"") | AF25: =IFERROR(IF('IND-17'!G40="","",'IND-17'!G40),"") | AG25: =IFERROR(IF('IND-17'!G41="","",'IND-17'!G41),"") | AH25: =IFERROR(IF('IND-17'!G42="","",'IND-17'!G42),"") | AI25: =IFERROR(IF('IND-17'!G43="","",'IND-17'!G43),"") | AJ25: =IFERROR(IF('IND-17'!G44="","",'IND-17'!G44),"") | AK25: =IFERROR(IF('IND-17'!G45="","",'IND-17'!G45),"") | AL25: =IFERROR(IF('IND-17'!G46="","",'IND-17'!G46),"") | AM25: =IFERROR(IF('IND-17'!G47="","",'IND-17'!G47),"") | AN25: =IFERROR(IF('IND-17'!G48="","",'IND-17'!G48),"") | AO25: =IFERROR(IF('IND-17'!G49="","",'IND-17'!G49),"") | AP25: =IFERROR(IF('IND-17'!G50="","",'IND-17'!G50),"") | AQ25: =IFERROR(IF('IND-17'!G51="","",'IND-17'!G51),"") | AR25: =IFERROR(IF('IND-17'!G52="","",'IND-17'!G52),"") | AS25: =IFERROR(IF('IND-17'!G53="","",'IND-17'!G53),"") | AT25: =IFERROR(IF('IND-17'!G54="","",'IND-17'!G54),"") | AU25: =IFERROR(IF('IND-17'!G55="","",'IND-17'!G55),"") | AV25: =IFERROR(IF('IND-17'!G56="","",'IND-17'!G56),"") | AW25: =IFERROR(IF('IND-17'!G57="","",'IND-17'!G57),"") | AX25: =IFERROR(IF('IND-17'!G58="","",'IND-17'!G58),"") | AY25: =IFERROR(IF('IND-17'!G59="","",'IND-17'!G59),"") | AZ25: =IFERROR(IF('IND-17'!G60="","",'IND-17'!G60),"") | BA25: =IFERROR(IF('IND-17'!G61="","",'IND-17'!G61),"") | BB25: =IFERROR(IF('IND-17'!G62="","",'IND-17'!G62),"") | BC25: =IFERROR(IF('IND-17'!G63="","",'IND-17'!G63),"") | BD25: =IFERROR(IF('IND-17'!G64="","",'IND-17'!G64),"") | BE25: =IFERROR(IF('IND-17'!G65="","",'IND-17'!G65),"") | BF25: =IFERROR(IF('IND-17'!G66="","",'IND-17'!G66),"") | BG25: =IFERROR(IF('IND-17'!G67="","",'IND-17'!G67),"") | BH25: =IFERROR(IF('IND-17'!G68="","",'IND-17'!G68),"") | BI25: =IFERROR(IF('IND-17'!G69="","",'IND-17'!G69),"") | BJ25: =IFERROR(IF('IND-17'!G70="","",'IND-17'!G70),"") | BK25: =IFERROR(IF('IND-17'!G71="","",'IND-17'!G71),"") | BL25: =IFERROR(IF('IND-17'!G72="","",'IND-17'!G72),"") | BM25: =IFERROR(IF('IND-17'!G73="","",'IND-17'!G73),"") | BN25: =IFERROR(IF('IND-17'!G74="","",'IND-17'!G74),"") | BO25: =IFERROR(IF('IND-17'!G75="","",'IND-17'!G75),"") | BP25: =IFERROR(IF('IND-17'!G76="","",'IND-17'!G76),"") | BQ25: =IFERROR(IF('IND-17'!G77="","",'IND-17'!G77),"") | BR25: =IFERROR(IF('IND-17'!G78="","",'IND-17'!G78),"") | BS25: =IFERROR(IF('IND-17'!G79="","",'IND-17'!G79),"") | BT25: =IFERROR(IF('IND-17'!G80="","",'IND-17'!G80),"") | BU25: =IFERROR(IF('IND-17'!G81="","",'IND-17'!G81),"") | BV25: =IFERROR(IF('IND-17'!G82="","",'IND-17'!G82),"") | BW25: =IFERROR(AVERAGE('IND-17'!I23:I34),"") | BX25: =IFERROR(AVERAGE('IND-17'!I35:I46),"") | BY25: =IFERROR(AVERAGE('IND-17'!I47:I58),"") | BZ25: =IFERROR(AVERAGE('IND-17'!I59:I70),"") | CA25: =IFERROR(AVERAGE('IND-17'!I71:I82),"") | CB25: =IFERROR(IF(LOOKUP(2,1/((BW25:CA25<>"")*(ISNUMBER(BW25:CA25))),BW25:CA25)>=0.95,"🟢 Cumple",IF(LOOKUP(2,1/((BW25:CA25<>"")*(ISNUMBER(BW25:CA25))),BW25:CA25)>=0.8,"🟡 En riesgo","🔴 Crítico")),"⚪ Pendiente") -> ⚪ Pendiente
B26: Operatividad digital y canales | C26: Tasa de contacto efectivo por canal | D26: Contactos efectivos ÷ Total contactos realizados | E26: Evalúa la efectividad de los canales en la interacción con los asociados. | F26: % | G26: Crecer | H26: Mensual | I26: =VLOOKUP("IND-18",Parámetros!$B$6:$F$30,5,FALSE()) -> Por definir | J26: ='IND-18'!C14 -> Por definir | K26: ='IND-18'!C15 -> Por definir | L26: ='IND-18'!C16 -> Por definir | M26: ='IND-18'!C17 -> Por definir | N26: ='IND-18'!C18 -> Por definir | O26: =IFERROR(IF('IND-18'!G23="","",'IND-18'!G23),"") | P26: =IFERROR(IF('IND-18'!G24="","",'IND-18'!G24),"") | Q26: =IFERROR(IF('IND-18'!G25="","",'IND-18'!G25),"") | R26: =IFERROR(IF('IND-18'!G26="","",'IND-18'!G26),"") | S26: =IFERROR(IF('IND-18'!G27="","",'IND-18'!G27),"") | T26: =IFERROR(IF('IND-18'!G28="","",'IND-18'!G28),"") | U26: =IFERROR(IF('IND-18'!G29="","",'IND-18'!G29),"") | V26: =IFERROR(IF('IND-18'!G30="","",'IND-18'!G30),"") | W26: =IFERROR(IF('IND-18'!G31="","",'IND-18'!G31),"") | X26: =IFERROR(IF('IND-18'!G32="","",'IND-18'!G32),"") | Y26: =IFERROR(IF('IND-18'!G33="","",'IND-18'!G33),"") | Z26: =IFERROR(IF('IND-18'!G34="","",'IND-18'!G34),"") | AA26: =IFERROR(IF('IND-18'!G35="","",'IND-18'!G35),"") | AB26: =IFERROR(IF('IND-18'!G36="","",'IND-18'!G36),"") | AC26: =IFERROR(IF('IND-18'!G37="","",'IND-18'!G37),"") | AD26: =IFERROR(IF('IND-18'!G38="","",'IND-18'!G38),"") | AE26: =IFERROR(IF('IND-18'!G39="","",'IND-18'!G39),"") | AF26: =IFERROR(IF('IND-18'!G40="","",'IND-18'!G40),"") | AG26: =IFERROR(IF('IND-18'!G41="","",'IND-18'!G41),"") | AH26: =IFERROR(IF('IND-18'!G42="","",'IND-18'!G42),"") | AI26: =IFERROR(IF('IND-18'!G43="","",'IND-18'!G43),"") | AJ26: =IFERROR(IF('IND-18'!G44="","",'IND-18'!G44),"") | AK26: =IFERROR(IF('IND-18'!G45="","",'IND-18'!G45),"") | AL26: =IFERROR(IF('IND-18'!G46="","",'IND-18'!G46),"") | AM26: =IFERROR(IF('IND-18'!G47="","",'IND-18'!G47),"") | AN26: =IFERROR(IF('IND-18'!G48="","",'IND-18'!G48),"") | AO26: =IFERROR(IF('IND-18'!G49="","",'IND-18'!G49),"") | AP26: =IFERROR(IF('IND-18'!G50="","",'IND-18'!G50),"") | AQ26: =IFERROR(IF('IND-18'!G51="","",'IND-18'!G51),"") | AR26: =IFERROR(IF('IND-18'!G52="","",'IND-18'!G52),"") | AS26: =IFERROR(IF('IND-18'!G53="","",'IND-18'!G53),"") | AT26: =IFERROR(IF('IND-18'!G54="","",'IND-18'!G54),"") | AU26: =IFERROR(IF('IND-18'!G55="","",'IND-18'!G55),"") | AV26: =IFERROR(IF('IND-18'!G56="","",'IND-18'!G56),"") | AW26: =IFERROR(IF('IND-18'!G57="","",'IND-18'!G57),"") | AX26: =IFERROR(IF('IND-18'!G58="","",'IND-18'!G58),"") | AY26: =IFERROR(IF('IND-18'!G59="","",'IND-18'!G59),"") | AZ26: =IFERROR(IF('IND-18'!G60="","",'IND-18'!G60),"") | BA26: =IFERROR(IF('IND-18'!G61="","",'IND-18'!G61),"") | BB26: =IFERROR(IF('IND-18'!G62="","",'IND-18'!G62),"") | BC26: =IFERROR(IF('IND-18'!G63="","",'IND-18'!G63),"") | BD26: =IFERROR(IF('IND-18'!G64="","",'IND-18'!G64),"") | BE26: =IFERROR(IF('IND-18'!G65="","",'IND-18'!G65),"") | BF26: =IFERROR(IF('IND-18'!G66="","",'IND-18'!G66),"") | BG26: =IFERROR(IF('IND-18'!G67="","",'IND-18'!G67),"") | BH26: =IFERROR(IF('IND-18'!G68="","",'IND-18'!G68),"") | BI26: =IFERROR(IF('IND-18'!G69="","",'IND-18'!G69),"") | BJ26: =IFERROR(IF('IND-18'!G70="","",'IND-18'!G70),"") | BK26: =IFERROR(IF('IND-18'!G71="","",'IND-18'!G71),"") | BL26: =IFERROR(IF('IND-18'!G72="","",'IND-18'!G72),"") | BM26: =IFERROR(IF('IND-18'!G73="","",'IND-18'!G73),"") | BN26: =IFERROR(IF('IND-18'!G74="","",'IND-18'!G74),"") | BO26: =IFERROR(IF('IND-18'!G75="","",'IND-18'!G75),"") | BP26: =IFERROR(IF('IND-18'!G76="","",'IND-18'!G76),"") | BQ26: =IFERROR(IF('IND-18'!G77="","",'IND-18'!G77),"") | BR26: =IFERROR(IF('IND-18'!G78="","",'IND-18'!G78),"") | BS26: =IFERROR(IF('IND-18'!G79="","",'IND-18'!G79),"") | BT26: =IFERROR(IF('IND-18'!G80="","",'IND-18'!G80),"") | BU26: =IFERROR(IF('IND-18'!G81="","",'IND-18'!G81),"") | BV26: =IFERROR(IF('IND-18'!G82="","",'IND-18'!G82),"") | BW26: =IFERROR(AVERAGE('IND-18'!I23:I34),"") | BX26: =IFERROR(AVERAGE('IND-18'!I35:I46),"") | BY26: =IFERROR(AVERAGE('IND-18'!I47:I58),"") | BZ26: =IFERROR(AVERAGE('IND-18'!I59:I70),"") | CA26: =IFERROR(AVERAGE('IND-18'!I71:I82),"") | CB26: =IFERROR(IF(LOOKUP(2,1/((BW26:CA26<>"")*(ISNUMBER(BW26:CA26))),BW26:CA26)>=0.95,"🟢 Cumple",IF(LOOKUP(2,1/((BW26:CA26<>"")*(ISNUMBER(BW26:CA26))),BW26:CA26)>=0.8,"🟡 En riesgo","🔴 Crítico")),"⚪ Pendiente") -> ⚪ Pendiente
B27: Operatividad digital y canales | C27: Índice de satisfacción por canal | D27: Promedio de calificación obtenida en encuestas por canal | E27: Mide la percepción del asociado frente a cada canal de atención. | F27: Puntos (escala) | G27: Crecer | H27: Trimestral | I27: =VLOOKUP("IND-19",Parámetros!$B$6:$F$30,5,FALSE()) -> Por definir | J27: ='IND-19'!C14 -> Por definir | K27: ='IND-19'!C15 -> Por definir | L27: ='IND-19'!C16 -> Por definir | M27: ='IND-19'!C17 -> Por definir | N27: ='IND-19'!C18 -> Por definir | O27: =IFERROR(IF('IND-19'!F23="","",'IND-19'!F23),"") | P27: =IFERROR(IF('IND-19'!F24="","",'IND-19'!F24),"") | Q27: =IFERROR(IF('IND-19'!F25="","",'IND-19'!F25),"") | R27: =IFERROR(IF('IND-19'!F26="","",'IND-19'!F26),"") | S27: =IFERROR(IF('IND-19'!F27="","",'IND-19'!F27),"") | T27: =IFERROR(IF('IND-19'!F28="","",'IND-19'!F28),"") | U27: =IFERROR(IF('IND-19'!F29="","",'IND-19'!F29),"") | V27: =IFERROR(IF('IND-19'!F30="","",'IND-19'!F30),"") | W27: =IFERROR(IF('IND-19'!F31="","",'IND-19'!F31),"") | X27: =IFERROR(IF('IND-19'!F32="","",'IND-19'!F32),"") | Y27: =IFERROR(IF('IND-19'!F33="","",'IND-19'!F33),"") | Z27: =IFERROR(IF('IND-19'!F34="","",'IND-19'!F34),"") | AA27: =IFERROR(IF('IND-19'!F35="","",'IND-19'!F35),"") | AB27: =IFERROR(IF('IND-19'!F36="","",'IND-19'!F36),"") | AC27: =IFERROR(IF('IND-19'!F37="","",'IND-19'!F37),"") | AD27: =IFERROR(IF('IND-19'!F38="","",'IND-19'!F38),"") | AE27: =IFERROR(IF('IND-19'!F39="","",'IND-19'!F39),"") | AF27: =IFERROR(IF('IND-19'!F40="","",'IND-19'!F40),"") | AG27: =IFERROR(IF('IND-19'!F41="","",'IND-19'!F41),"") | AH27: =IFERROR(IF('IND-19'!F42="","",'IND-19'!F42),"") | AI27: =IFERROR(IF('IND-19'!F43="","",'IND-19'!F43),"") | AJ27: =IFERROR(IF('IND-19'!F44="","",'IND-19'!F44),"") | AK27: =IFERROR(IF('IND-19'!F45="","",'IND-19'!F45),"") | AL27: =IFERROR(IF('IND-19'!F46="","",'IND-19'!F46),"") | AM27: =IFERROR(IF('IND-19'!F47="","",'IND-19'!F47),"") | AN27: =IFERROR(IF('IND-19'!F48="","",'IND-19'!F48),"") | AO27: =IFERROR(IF('IND-19'!F49="","",'IND-19'!F49),"") | AP27: =IFERROR(IF('IND-19'!F50="","",'IND-19'!F50),"") | AQ27: =IFERROR(IF('IND-19'!F51="","",'IND-19'!F51),"") | AR27: =IFERROR(IF('IND-19'!F52="","",'IND-19'!F52),"") | AS27: =IFERROR(IF('IND-19'!F53="","",'IND-19'!F53),"") | AT27: =IFERROR(IF('IND-19'!F54="","",'IND-19'!F54),"") | AU27: =IFERROR(IF('IND-19'!F55="","",'IND-19'!F55),"") | AV27: =IFERROR(IF('IND-19'!F56="","",'IND-19'!F56),"") | AW27: =IFERROR(IF('IND-19'!F57="","",'IND-19'!F57),"") | AX27: =IFERROR(IF('IND-19'!F58="","",'IND-19'!F58),"") | AY27: =IFERROR(IF('IND-19'!F59="","",'IND-19'!F59),"") | AZ27: =IFERROR(IF('IND-19'!F60="","",'IND-19'!F60),"") | BA27: =IFERROR(IF('IND-19'!F61="","",'IND-19'!F61),"") | BB27: =IFERROR(IF('IND-19'!F62="","",'IND-19'!F62),"") | BC27: =IFERROR(IF('IND-19'!F63="","",'IND-19'!F63),"") | BD27: =IFERROR(IF('IND-19'!F64="","",'IND-19'!F64),"") | BE27: =IFERROR(IF('IND-19'!F65="","",'IND-19'!F65),"") | BF27: =IFERROR(IF('IND-19'!F66="","",'IND-19'!F66),"") | BG27: =IFERROR(IF('IND-19'!F67="","",'IND-19'!F67),"") | BH27: =IFERROR(IF('IND-19'!F68="","",'IND-19'!F68),"") | BI27: =IFERROR(IF('IND-19'!F69="","",'IND-19'!F69),"") | BJ27: =IFERROR(IF('IND-19'!F70="","",'IND-19'!F70),"") | BK27: =IFERROR(IF('IND-19'!F71="","",'IND-19'!F71),"") | BL27: =IFERROR(IF('IND-19'!F72="","",'IND-19'!F72),"") | BM27: =IFERROR(IF('IND-19'!F73="","",'IND-19'!F73),"") | BN27: =IFERROR(IF('IND-19'!F74="","",'IND-19'!F74),"") | BO27: =IFERROR(IF('IND-19'!F75="","",'IND-19'!F75),"") | BP27: =IFERROR(IF('IND-19'!F76="","",'IND-19'!F76),"") | BQ27: =IFERROR(IF('IND-19'!F77="","",'IND-19'!F77),"") | BR27: =IFERROR(IF('IND-19'!F78="","",'IND-19'!F78),"") | BS27: =IFERROR(IF('IND-19'!F79="","",'IND-19'!F79),"") | BT27: =IFERROR(IF('IND-19'!F80="","",'IND-19'!F80),"") | BU27: =IFERROR(IF('IND-19'!F81="","",'IND-19'!F81),"") | BV27: =IFERROR(IF('IND-19'!F82="","",'IND-19'!F82),"") | BW27: =IFERROR(AVERAGE('IND-19'!H23:H34),"") | BX27: =IFERROR(AVERAGE('IND-19'!H35:H46),"") | BY27: =IFERROR(AVERAGE('IND-19'!H47:H58),"") | BZ27: =IFERROR(AVERAGE('IND-19'!H59:H70),"") | CA27: =IFERROR(AVERAGE('IND-19'!H71:H82),"") | CB27: =IFERROR(IF(LOOKUP(2,1/((BW27:CA27<>"")*(ISNUMBER(BW27:CA27))),BW27:CA27)>=0.95,"🟢 Cumple",IF(LOOKUP(2,1/((BW27:CA27<>"")*(ISNUMBER(BW27:CA27))),BW27:CA27)>=0.8,"🟡 En riesgo","🔴 Crítico")),"⚪ Pendiente") -> ⚪ Pendiente
B28: ⚙️ PERSPECTIVA PROCESOS
B29: Automatización de procesos | C29: Nivel de automatización de procesos | D29: Tareas automatizadas ÷ Total procesos identificados | E29: Mide el porcentaje de procesos operativos y de servicio que han sido automatizados. | F29: % | G29: Crecer | H29: Semestral | I29: =VLOOKUP("IND-20",Parámetros!$B$6:$F$30,5,FALSE()) -> Tecnología | J29: ='IND-20'!C14 -> 0.3 | K29: ='IND-20'!C15 -> 0.45 | L29: ='IND-20'!C16 -> 0.55 | M29: ='IND-20'!C17 -> 0.65 | N29: ='IND-20'!C18 -> 0.7 | O29: =IFERROR(IF('IND-20'!G23="","",'IND-20'!G23),"") | P29: =IFERROR(IF('IND-20'!G24="","",'IND-20'!G24),"") | Q29: =IFERROR(IF('IND-20'!G25="","",'IND-20'!G25),"") | R29: =IFERROR(IF('IND-20'!G26="","",'IND-20'!G26),"") | S29: =IFERROR(IF('IND-20'!G27="","",'IND-20'!G27),"") | T29: =IFERROR(IF('IND-20'!G28="","",'IND-20'!G28),"") -> 0.16 | U29: =IFERROR(IF('IND-20'!G29="","",'IND-20'!G29),"") | V29: =IFERROR(IF('IND-20'!G30="","",'IND-20'!G30),"") | W29: =IFERROR(IF('IND-20'!G31="","",'IND-20'!G31),"") | X29: =IFERROR(IF('IND-20'!G32="","",'IND-20'!G32),"") | Y29: =IFERROR(IF('IND-20'!G33="","",'IND-20'!G33),"") | Z29: =IFERROR(IF('IND-20'!G34="","",'IND-20'!G34),"") -> 0.24 | AA29: =IFERROR(IF('IND-20'!G35="","",'IND-20'!G35),"") | AB29: =IFERROR(IF('IND-20'!G36="","",'IND-20'!G36),"") | AC29: =IFERROR(IF('IND-20'!G37="","",'IND-20'!G37),"") | AD29: =IFERROR(IF('IND-20'!G38="","",'IND-20'!G38),"") | AE29: =IFERROR(IF('IND-20'!G39="","",'IND-20'!G39),"") | AF29: =IFERROR(IF('IND-20'!G40="","",'IND-20'!G40),"") -> 0.32 | AG29: =IFERROR(IF('IND-20'!G41="","",'IND-20'!G41),"") | AH29: =IFERROR(IF('IND-20'!G42="","",'IND-20'!G42),"") | AI29: =IFERROR(IF('IND-20'!G43="","",'IND-20'!G43),"") | AJ29: =IFERROR(IF('IND-20'!G44="","",'IND-20'!G44),"") | AK29: =IFERROR(IF('IND-20'!G45="","",'IND-20'!G45),"") | AL29: =IFERROR(IF('IND-20'!G46="","",'IND-20'!G46),"") | AM29: =IFERROR(IF('IND-20'!G47="","",'IND-20'!G47),"") | AN29: =IFERROR(IF('IND-20'!G48="","",'IND-20'!G48),"") | AO29: =IFERROR(IF('IND-20'!G49="","",'IND-20'!G49),"") | AP29: =IFERROR(IF('IND-20'!G50="","",'IND-20'!G50),"") | AQ29: =IFERROR(IF('IND-20'!G51="","",'IND-20'!G51),"") | AR29: =IFERROR(IF('IND-20'!G52="","",'IND-20'!G52),"") | AS29: =IFERROR(IF('IND-20'!G53="","",'IND-20'!G53),"") | AT29: =IFERROR(IF('IND-20'!G54="","",'IND-20'!G54),"") | AU29: =IFERROR(IF('IND-20'!G55="","",'IND-20'!G55),"") | AV29: =IFERROR(IF('IND-20'!G56="","",'IND-20'!G56),"") | AW29: =IFERROR(IF('IND-20'!G57="","",'IND-20'!G57),"") | AX29: =IFERROR(IF('IND-20'!G58="","",'IND-20'!G58),"") | AY29: =IFERROR(IF('IND-20'!G59="","",'IND-20'!G59),"") | AZ29: =IFERROR(IF('IND-20'!G60="","",'IND-20'!G60),"") | BA29: =IFERROR(IF('IND-20'!G61="","",'IND-20'!G61),"") | BB29: =IFERROR(IF('IND-20'!G62="","",'IND-20'!G62),"") | BC29: =IFERROR(IF('IND-20'!G63="","",'IND-20'!G63),"") | BD29: =IFERROR(IF('IND-20'!G64="","",'IND-20'!G64),"") | BE29: =IFERROR(IF('IND-20'!G65="","",'IND-20'!G65),"") | BF29: =IFERROR(IF('IND-20'!G66="","",'IND-20'!G66),"") | BG29: =IFERROR(IF('IND-20'!G67="","",'IND-20'!G67),"") | BH29: =IFERROR(IF('IND-20'!G68="","",'IND-20'!G68),"") | BI29: =IFERROR(IF('IND-20'!G69="","",'IND-20'!G69),"") | BJ29: =IFERROR(IF('IND-20'!G70="","",'IND-20'!G70),"") | BK29: =IFERROR(IF('IND-20'!G71="","",'IND-20'!G71),"") | BL29: =IFERROR(IF('IND-20'!G72="","",'IND-20'!G72),"") | BM29: =IFERROR(IF('IND-20'!G73="","",'IND-20'!G73),"") | BN29: =IFERROR(IF('IND-20'!G74="","",'IND-20'!G74),"") | BO29: =IFERROR(IF('IND-20'!G75="","",'IND-20'!G75),"") | BP29: =IFERROR(IF('IND-20'!G76="","",'IND-20'!G76),"") | BQ29: =IFERROR(IF('IND-20'!G77="","",'IND-20'!G77),"") | BR29: =IFERROR(IF('IND-20'!G78="","",'IND-20'!G78),"") | BS29: =IFERROR(IF('IND-20'!G79="","",'IND-20'!G79),"") | BT29: =IFERROR(IF('IND-20'!G80="","",'IND-20'!G80),"") | BU29: =IFERROR(IF('IND-20'!G81="","",'IND-20'!G81),"") | BV29: =IFERROR(IF('IND-20'!G82="","",'IND-20'!G82),"") | BW29: =IFERROR(AVERAGE('IND-20'!I23:I34),"") -> 0.66666667 | BX29: =IFERROR(AVERAGE('IND-20'!I35:I46),"") -> 0.71111111 | BY29: =IFERROR(AVERAGE('IND-20'!I47:I58),"") | BZ29: =IFERROR(AVERAGE('IND-20'!I59:I70),"") | CA29: =IFERROR(AVERAGE('IND-20'!I71:I82),"") | CB29: =IFERROR(IF(LOOKUP(2,1/((BW29:CA29<>"")*(ISNUMBER(BW29:CA29))),BW29:CA29)>=0.95,"🟢 Cumple",IF(LOOKUP(2,1/((BW29:CA29<>"")*(ISNUMBER(BW29:CA29))),BW29:CA29)>=0.8,"🟡 En riesgo","🔴 Crítico")),"⚪ Pendiente") -> 🔴 Crítico
B30: Transformación digital del asociado | C30: Uso y adopción de canales transaccionales digitales | D30: Transacciones digitales (<70 años) ÷ Total transacciones (<70 años) | E30: Mide el uso de canales digitales (Coop Digital y App) por asociados menores de 70 años. | F30: % | G30: Crecer | H30: Trimestral | I30: =VLOOKUP("IND-21",Parámetros!$B$6:$F$30,5,FALSE()) -> Por definir | J30: ='IND-21'!C14 -> 0.8 | K30: ='IND-21'!C15 -> 0.8 | L30: ='IND-21'!C16 -> 0.8 | M30: ='IND-21'!C17 -> 0.8 | N30: ='IND-21'!C18 -> 0.8 | O30: =IFERROR(IF('IND-21'!G23="","",'IND-21'!G23),"") | P30: =IFERROR(IF('IND-21'!G24="","",'IND-21'!G24),"") | Q30: =IFERROR(IF('IND-21'!G25="","",'IND-21'!G25),"") | R30: =IFERROR(IF('IND-21'!G26="","",'IND-21'!G26),"") | S30: =IFERROR(IF('IND-21'!G27="","",'IND-21'!G27),"") | T30: =IFERROR(IF('IND-21'!G28="","",'IND-21'!G28),"") | U30: =IFERROR(IF('IND-21'!G29="","",'IND-21'!G29),"") | V30: =IFERROR(IF('IND-21'!G30="","",'IND-21'!G30),"") | W30: =IFERROR(IF('IND-21'!G31="","",'IND-21'!G31),"") | X30: =IFERROR(IF('IND-21'!G32="","",'IND-21'!G32),"") | Y30: =IFERROR(IF('IND-21'!G33="","",'IND-21'!G33),"") | Z30: =IFERROR(IF('IND-21'!G34="","",'IND-21'!G34),"") | AA30: =IFERROR(IF('IND-21'!G35="","",'IND-21'!G35),"") | AB30: =IFERROR(IF('IND-21'!G36="","",'IND-21'!G36),"") | AC30: =IFERROR(IF('IND-21'!G37="","",'IND-21'!G37),"") | AD30: =IFERROR(IF('IND-21'!G38="","",'IND-21'!G38),"") | AE30: =IFERROR(IF('IND-21'!G39="","",'IND-21'!G39),"") | AF30: =IFERROR(IF('IND-21'!G40="","",'IND-21'!G40),"") | AG30: =IFERROR(IF('IND-21'!G41="","",'IND-21'!G41),"") | AH30: =IFERROR(IF('IND-21'!G42="","",'IND-21'!G42),"") | AI30: =IFERROR(IF('IND-21'!G43="","",'IND-21'!G43),"") | AJ30: =IFERROR(IF('IND-21'!G44="","",'IND-21'!G44),"") | AK30: =IFERROR(IF('IND-21'!G45="","",'IND-21'!G45),"") | AL30: =IFERROR(IF('IND-21'!G46="","",'IND-21'!G46),"") | AM30: =IFERROR(IF('IND-21'!G47="","",'IND-21'!G47),"") | AN30: =IFERROR(IF('IND-21'!G48="","",'IND-21'!G48),"") | AO30: =IFERROR(IF('IND-21'!G49="","",'IND-21'!G49),"") | AP30: =IFERROR(IF('IND-21'!G50="","",'IND-21'!G50),"") | AQ30: =IFERROR(IF('IND-21'!G51="","",'IND-21'!G51),"") | AR30: =IFERROR(IF('IND-21'!G52="","",'IND-21'!G52),"") | AS30: =IFERROR(IF('IND-21'!G53="","",'IND-21'!G53),"") | AT30: =IFERROR(IF('IND-21'!G54="","",'IND-21'!G54),"") | AU30: =IFERROR(IF('IND-21'!G55="","",'IND-21'!G55),"") | AV30: =IFERROR(IF('IND-21'!G56="","",'IND-21'!G56),"") | AW30: =IFERROR(IF('IND-21'!G57="","",'IND-21'!G57),"") | AX30: =IFERROR(IF('IND-21'!G58="","",'IND-21'!G58),"") | AY30: =IFERROR(IF('IND-21'!G59="","",'IND-21'!G59),"") | AZ30: =IFERROR(IF('IND-21'!G60="","",'IND-21'!G60),"") | BA30: =IFERROR(IF('IND-21'!G61="","",'IND-21'!G61),"") | BB30: =IFERROR(IF('IND-21'!G62="","",'IND-21'!G62),"") | BC30: =IFERROR(IF('IND-21'!G63="","",'IND-21'!G63),"") | BD30: =IFERROR(IF('IND-21'!G64="","",'IND-21'!G64),"") | BE30: =IFERROR(IF('IND-21'!G65="","",'IND-21'!G65),"") | BF30: =IFERROR(IF('IND-21'!G66="","",'IND-21'!G66),"") | BG30: =IFERROR(IF('IND-21'!G67="","",'IND-21'!G67),"") | BH30: =IFERROR(IF('IND-21'!G68="","",'IND-21'!G68),"") | BI30: =IFERROR(IF('IND-21'!G69="","",'IND-21'!G69),"") | BJ30: =IFERROR(IF('IND-21'!G70="","",'IND-21'!G70),"") | BK30: =IFERROR(IF('IND-21'!G71="","",'IND-21'!G71),"") | BL30: =IFERROR(IF('IND-21'!G72="","",'IND-21'!G72),"") | BM30: =IFERROR(IF('IND-21'!G73="","",'IND-21'!G73),"") | BN30: =IFERROR(IF('IND-21'!G74="","",'IND-21'!G74),"") | BO30: =IFERROR(IF('IND-21'!G75="","",'IND-21'!G75),"") | BP30: =IFERROR(IF('IND-21'!G76="","",'IND-21'!G76),"") | BQ30: =IFERROR(IF('IND-21'!G77="","",'IND-21'!G77),"") | BR30: =IFERROR(IF('IND-21'!G78="","",'IND-21'!G78),"") | BS30: =IFERROR(IF('IND-21'!G79="","",'IND-21'!G79),"") | BT30: =IFERROR(IF('IND-21'!G80="","",'IND-21'!G80),"") | BU30: =IFERROR(IF('IND-21'!G81="","",'IND-21'!G81),"") | BV30: =IFERROR(IF('IND-21'!G82="","",'IND-21'!G82),"") | BW30: =IFERROR(AVERAGE('IND-21'!I23:I34),"") | BX30: =IFERROR(AVERAGE('IND-21'!I35:I46),"") | BY30: =IFERROR(AVERAGE('IND-21'!I47:I58),"") | BZ30: =IFERROR(AVERAGE('IND-21'!I59:I70),"") | CA30: =IFERROR(AVERAGE('IND-21'!I71:I82),"") | CB30: =IFERROR(IF(LOOKUP(2,1/((BW30:CA30<>"")*(ISNUMBER(BW30:CA30))),BW30:CA30)>=0.95,"🟢 Cumple",IF(LOOKUP(2,1/((BW30:CA30<>"")*(ISNUMBER(BW30:CA30))),BW30:CA30)>=0.8,"🟡 En riesgo","🔴 Crítico")),"⚪ Pendiente") -> ⚪ Pendiente
B31: 🎓 PERSPECTIVA APRENDIZAJE
B32: Formación de asociados | C32: Formación de asociados por temáticas (financiera - solidaria) | D32: Asociados capacitados ÷ Total de asociados | E32: Mide el porcentaje de asociados que participan en programas de educación financiera y cooperativa. | F32: % | G32: Crecer | H32: Trimestral | I32: =VLOOKUP("IND-22",Parámetros!$B$6:$F$30,5,FALSE()) -> Por definir | J32: ='IND-22'!C14 -> 0.4 | K32: ='IND-22'!C15 -> 0.4 | L32: ='IND-22'!C16 -> 0.4 | M32: ='IND-22'!C17 -> 0.4 | N32: ='IND-22'!C18 -> 0.4 | O32: =IFERROR(IF('IND-22'!G23="","",'IND-22'!G23),"") | P32: =IFERROR(IF('IND-22'!G24="","",'IND-22'!G24),"") | Q32: =IFERROR(IF('IND-22'!G25="","",'IND-22'!G25),"") | R32: =IFERROR(IF('IND-22'!G26="","",'IND-22'!G26),"") | S32: =IFERROR(IF('IND-22'!G27="","",'IND-22'!G27),"") | T32: =IFERROR(IF('IND-22'!G28="","",'IND-22'!G28),"") | U32: =IFERROR(IF('IND-22'!G29="","",'IND-22'!G29),"") | V32: =IFERROR(IF('IND-22'!G30="","",'IND-22'!G30),"") | W32: =IFERROR(IF('IND-22'!G31="","",'IND-22'!G31),"") | X32: =IFERROR(IF('IND-22'!G32="","",'IND-22'!G32),"") | Y32: =IFERROR(IF('IND-22'!G33="","",'IND-22'!G33),"") | Z32: =IFERROR(IF('IND-22'!G34="","",'IND-22'!G34),"") | AA32: =IFERROR(IF('IND-22'!G35="","",'IND-22'!G35),"") | AB32: =IFERROR(IF('IND-22'!G36="","",'IND-22'!G36),"") | AC32: =IFERROR(IF('IND-22'!G37="","",'IND-22'!G37),"") | AD32: =IFERROR(IF('IND-22'!G38="","",'IND-22'!G38),"") | AE32: =IFERROR(IF('IND-22'!G39="","",'IND-22'!G39),"") | AF32: =IFERROR(IF('IND-22'!G40="","",'IND-22'!G40),"") | AG32: =IFERROR(IF('IND-22'!G41="","",'IND-22'!G41),"") | AH32: =IFERROR(IF('IND-22'!G42="","",'IND-22'!G42),"") | AI32: =IFERROR(IF('IND-22'!G43="","",'IND-22'!G43),"") | AJ32: =IFERROR(IF('IND-22'!G44="","",'IND-22'!G44),"") | AK32: =IFERROR(IF('IND-22'!G45="","",'IND-22'!G45),"") | AL32: =IFERROR(IF('IND-22'!G46="","",'IND-22'!G46),"") | AM32: =IFERROR(IF('IND-22'!G47="","",'IND-22'!G47),"") | AN32: =IFERROR(IF('IND-22'!G48="","",'IND-22'!G48),"") | AO32: =IFERROR(IF('IND-22'!G49="","",'IND-22'!G49),"") | AP32: =IFERROR(IF('IND-22'!G50="","",'IND-22'!G50),"") | AQ32: =IFERROR(IF('IND-22'!G51="","",'IND-22'!G51),"") | AR32: =IFERROR(IF('IND-22'!G52="","",'IND-22'!G52),"") | AS32: =IFERROR(IF('IND-22'!G53="","",'IND-22'!G53),"") | AT32: =IFERROR(IF('IND-22'!G54="","",'IND-22'!G54),"") | AU32: =IFERROR(IF('IND-22'!G55="","",'IND-22'!G55),"") | AV32: =IFERROR(IF('IND-22'!G56="","",'IND-22'!G56),"") | AW32: =IFERROR(IF('IND-22'!G57="","",'IND-22'!G57),"") | AX32: =IFERROR(IF('IND-22'!G58="","",'IND-22'!G58),"") | AY32: =IFERROR(IF('IND-22'!G59="","",'IND-22'!G59),"") | AZ32: =IFERROR(IF('IND-22'!G60="","",'IND-22'!G60),"") | BA32: =IFERROR(IF('IND-22'!G61="","",'IND-22'!G61),"") | BB32: =IFERROR(IF('IND-22'!G62="","",'IND-22'!G62),"") | BC32: =IFERROR(IF('IND-22'!G63="","",'IND-22'!G63),"") | BD32: =IFERROR(IF('IND-22'!G64="","",'IND-22'!G64),"") | BE32: =IFERROR(IF('IND-22'!G65="","",'IND-22'!G65),"") | BF32: =IFERROR(IF('IND-22'!G66="","",'IND-22'!G66),"") | BG32: =IFERROR(IF('IND-22'!G67="","",'IND-22'!G67),"") | BH32: =IFERROR(IF('IND-22'!G68="","",'IND-22'!G68),"") | BI32: =IFERROR(IF('IND-22'!G69="","",'IND-22'!G69),"") | BJ32: =IFERROR(IF('IND-22'!G70="","",'IND-22'!G70),"") | BK32: =IFERROR(IF('IND-22'!G71="","",'IND-22'!G71),"") | BL32: =IFERROR(IF('IND-22'!G72="","",'IND-22'!G72),"") | BM32: =IFERROR(IF('IND-22'!G73="","",'IND-22'!G73),"") | BN32: =IFERROR(IF('IND-22'!G74="","",'IND-22'!G74),"") | BO32: =IFERROR(IF('IND-22'!G75="","",'IND-22'!G75),"") | BP32: =IFERROR(IF('IND-22'!G76="","",'IND-22'!G76),"") | BQ32: =IFERROR(IF('IND-22'!G77="","",'IND-22'!G77),"") | BR32: =IFERROR(IF('IND-22'!G78="","",'IND-22'!G78),"") | BS32: =IFERROR(IF('IND-22'!G79="","",'IND-22'!G79),"") | BT32: =IFERROR(IF('IND-22'!G80="","",'IND-22'!G80),"") | BU32: =IFERROR(IF('IND-22'!G81="","",'IND-22'!G81),"") | BV32: =IFERROR(IF('IND-22'!G82="","",'IND-22'!G82),"") | BW32: =IFERROR(AVERAGE('IND-22'!I23:I34),"") | BX32: =IFERROR(AVERAGE('IND-22'!I35:I46),"") | BY32: =IFERROR(AVERAGE('IND-22'!I47:I58),"") | BZ32: =IFERROR(AVERAGE('IND-22'!I59:I70),"") | CA32: =IFERROR(AVERAGE('IND-22'!I71:I82),"") | CB32: =IFERROR(IF(LOOKUP(2,1/((BW32:CA32<>"")*(ISNUMBER(BW32:CA32))),BW32:CA32)>=0.95,"🟢 Cumple",IF(LOOKUP(2,1/((BW32:CA32<>"")*(ISNUMBER(BW32:CA32))),BW32:CA32)>=0.8,"🟡 En riesgo","🔴 Crítico")),"⚪ Pendiente") -> ⚪ Pendiente
B33: Formación de asociados | C33: Formación en economía solidaria (20 hrs mínimo) | D33: Asociados con horas mínimas de formación ÷ Total de asociados | E33: Mide el porcentaje de asociados que han cumplido con la formación básica de economía solidaria. | F33: % | G33: Crecer | H33: Trimestral | I33: =VLOOKUP("IND-23",Parámetros!$B$6:$F$30,5,FALSE()) -> Por definir | J33: ='IND-23'!C14 -> 0.4 | K33: ='IND-23'!C15 -> 0.4 | L33: ='IND-23'!C16 -> 0.4 | M33: ='IND-23'!C17 -> 0.4 | N33: ='IND-23'!C18 -> 0.4 | O33: =IFERROR(IF('IND-23'!G23="","",'IND-23'!G23),"") | P33: =IFERROR(IF('IND-23'!G24="","",'IND-23'!G24),"") | Q33: =IFERROR(IF('IND-23'!G25="","",'IND-23'!G25),"") | R33: =IFERROR(IF('IND-23'!G26="","",'IND-23'!G26),"") | S33: =IFERROR(IF('IND-23'!G27="","",'IND-23'!G27),"") | T33: =IFERROR(IF('IND-23'!G28="","",'IND-23'!G28),"") | U33: =IFERROR(IF('IND-23'!G29="","",'IND-23'!G29),"") | V33: =IFERROR(IF('IND-23'!G30="","",'IND-23'!G30),"") | W33: =IFERROR(IF('IND-23'!G31="","",'IND-23'!G31),"") | X33: =IFERROR(IF('IND-23'!G32="","",'IND-23'!G32),"") | Y33: =IFERROR(IF('IND-23'!G33="","",'IND-23'!G33),"") | Z33: =IFERROR(IF('IND-23'!G34="","",'IND-23'!G34),"") | AA33: =IFERROR(IF('IND-23'!G35="","",'IND-23'!G35),"") | AB33: =IFERROR(IF('IND-23'!G36="","",'IND-23'!G36),"") | AC33: =IFERROR(IF('IND-23'!G37="","",'IND-23'!G37),"") | AD33: =IFERROR(IF('IND-23'!G38="","",'IND-23'!G38),"") | AE33: =IFERROR(IF('IND-23'!G39="","",'IND-23'!G39),"") | AF33: =IFERROR(IF('IND-23'!G40="","",'IND-23'!G40),"") | AG33: =IFERROR(IF('IND-23'!G41="","",'IND-23'!G41),"") | AH33: =IFERROR(IF('IND-23'!G42="","",'IND-23'!G42),"") | AI33: =IFERROR(IF('IND-23'!G43="","",'IND-23'!G43),"") | AJ33: =IFERROR(IF('IND-23'!G44="","",'IND-23'!G44),"") | AK33: =IFERROR(IF('IND-23'!G45="","",'IND-23'!G45),"") | AL33: =IFERROR(IF('IND-23'!G46="","",'IND-23'!G46),"") | AM33: =IFERROR(IF('IND-23'!G47="","",'IND-23'!G47),"") | AN33: =IFERROR(IF('IND-23'!G48="","",'IND-23'!G48),"") | AO33: =IFERROR(IF('IND-23'!G49="","",'IND-23'!G49),"") | AP33: =IFERROR(IF('IND-23'!G50="","",'IND-23'!G50),"") | AQ33: =IFERROR(IF('IND-23'!G51="","",'IND-23'!G51),"") | AR33: =IFERROR(IF('IND-23'!G52="","",'IND-23'!G52),"") | AS33: =IFERROR(IF('IND-23'!G53="","",'IND-23'!G53),"") | AT33: =IFERROR(IF('IND-23'!G54="","",'IND-23'!G54),"") | AU33: =IFERROR(IF('IND-23'!G55="","",'IND-23'!G55),"") | AV33: =IFERROR(IF('IND-23'!G56="","",'IND-23'!G56),"") | AW33: =IFERROR(IF('IND-23'!G57="","",'IND-23'!G57),"") | AX33: =IFERROR(IF('IND-23'!G58="","",'IND-23'!G58),"") | AY33: =IFERROR(IF('IND-23'!G59="","",'IND-23'!G59),"") | AZ33: =IFERROR(IF('IND-23'!G60="","",'IND-23'!G60),"") | BA33: =IFERROR(IF('IND-23'!G61="","",'IND-23'!G61),"") | BB33: =IFERROR(IF('IND-23'!G62="","",'IND-23'!G62),"") | BC33: =IFERROR(IF('IND-23'!G63="","",'IND-23'!G63),"") | BD33: =IFERROR(IF('IND-23'!G64="","",'IND-23'!G64),"") | BE33: =IFERROR(IF('IND-23'!G65="","",'IND-23'!G65),"") | BF33: =IFERROR(IF('IND-23'!G66="","",'IND-23'!G66),"") | BG33: =IFERROR(IF('IND-23'!G67="","",'IND-23'!G67),"") | BH33: =IFERROR(IF('IND-23'!G68="","",'IND-23'!G68),"") | BI33: =IFERROR(IF('IND-23'!G69="","",'IND-23'!G69),"") | BJ33: =IFERROR(IF('IND-23'!G70="","",'IND-23'!G70),"") | BK33: =IFERROR(IF('IND-23'!G71="","",'IND-23'!G71),"") | BL33: =IFERROR(IF('IND-23'!G72="","",'IND-23'!G72),"") | BM33: =IFERROR(IF('IND-23'!G73="","",'IND-23'!G73),"") | BN33: =IFERROR(IF('IND-23'!G74="","",'IND-23'!G74),"") | BO33: =IFERROR(IF('IND-23'!G75="","",'IND-23'!G75),"") | BP33: =IFERROR(IF('IND-23'!G76="","",'IND-23'!G76),"") | BQ33: =IFERROR(IF('IND-23'!G77="","",'IND-23'!G77),"") | BR33: =IFERROR(IF('IND-23'!G78="","",'IND-23'!G78),"") | BS33: =IFERROR(IF('IND-23'!G79="","",'IND-23'!G79),"") | BT33: =IFERROR(IF('IND-23'!G80="","",'IND-23'!G80),"") | BU33: =IFERROR(IF('IND-23'!G81="","",'IND-23'!G81),"") | BV33: =IFERROR(IF('IND-23'!G82="","",'IND-23'!G82),"") | BW33: =IFERROR(AVERAGE('IND-23'!I23:I34),"") | BX33: =IFERROR(AVERAGE('IND-23'!I35:I46),"") | BY33: =IFERROR(AVERAGE('IND-23'!I47:I58),"") | BZ33: =IFERROR(AVERAGE('IND-23'!I59:I70),"") | CA33: =IFERROR(AVERAGE('IND-23'!I71:I82),"") | CB33: =IFERROR(IF(LOOKUP(2,1/((BW33:CA33<>"")*(ISNUMBER(BW33:CA33))),BW33:CA33)>=0.95,"🟢 Cumple",IF(LOOKUP(2,1/((BW33:CA33<>"")*(ISNUMBER(BW33:CA33))),BW33:CA33)>=0.8,"🟡 En riesgo","🔴 Crítico")),"⚪ Pendiente") -> ⚪ Pendiente
B34: Formación y desarrollo del personal | C34: Cumplimiento del plan de formación de personal | D34: Actividades de formación ejecutadas ÷ Actividades planificadas | E34: Mide el grado de ejecución del plan de capacitación definido. | F34: % | G34: Crecer | H34: Semestral | I34: =VLOOKUP("IND-24",Parámetros!$B$6:$F$30,5,FALSE()) -> Por definir | J34: ='IND-24'!C14 -> 1 | K34: ='IND-24'!C15 -> 1 | L34: ='IND-24'!C16 -> 1 | M34: ='IND-24'!C17 -> 1 | N34: ='IND-24'!C18 -> 1 | O34: =IFERROR(IF('IND-24'!G23="","",'IND-24'!G23),"") | P34: =IFERROR(IF('IND-24'!G24="","",'IND-24'!G24),"") | Q34: =IFERROR(IF('IND-24'!G25="","",'IND-24'!G25),"") | R34: =IFERROR(IF('IND-24'!G26="","",'IND-24'!G26),"") | S34: =IFERROR(IF('IND-24'!G27="","",'IND-24'!G27),"") | T34: =IFERROR(IF('IND-24'!G28="","",'IND-24'!G28),"") | U34: =IFERROR(IF('IND-24'!G29="","",'IND-24'!G29),"") | V34: =IFERROR(IF('IND-24'!G30="","",'IND-24'!G30),"") | W34: =IFERROR(IF('IND-24'!G31="","",'IND-24'!G31),"") | X34: =IFERROR(IF('IND-24'!G32="","",'IND-24'!G32),"") | Y34: =IFERROR(IF('IND-24'!G33="","",'IND-24'!G33),"") | Z34: =IFERROR(IF('IND-24'!G34="","",'IND-24'!G34),"") | AA34: =IFERROR(IF('IND-24'!G35="","",'IND-24'!G35),"") | AB34: =IFERROR(IF('IND-24'!G36="","",'IND-24'!G36),"") | AC34: =IFERROR(IF('IND-24'!G37="","",'IND-24'!G37),"") | AD34: =IFERROR(IF('IND-24'!G38="","",'IND-24'!G38),"") | AE34: =IFERROR(IF('IND-24'!G39="","",'IND-24'!G39),"") | AF34: =IFERROR(IF('IND-24'!G40="","",'IND-24'!G40),"") | AG34: =IFERROR(IF('IND-24'!G41="","",'IND-24'!G41),"") | AH34: =IFERROR(IF('IND-24'!G42="","",'IND-24'!G42),"") | AI34: =IFERROR(IF('IND-24'!G43="","",'IND-24'!G43),"") | AJ34: =IFERROR(IF('IND-24'!G44="","",'IND-24'!G44),"") | AK34: =IFERROR(IF('IND-24'!G45="","",'IND-24'!G45),"") | AL34: =IFERROR(IF('IND-24'!G46="","",'IND-24'!G46),"") | AM34: =IFERROR(IF('IND-24'!G47="","",'IND-24'!G47),"") | AN34: =IFERROR(IF('IND-24'!G48="","",'IND-24'!G48),"") | AO34: =IFERROR(IF('IND-24'!G49="","",'IND-24'!G49),"") | AP34: =IFERROR(IF('IND-24'!G50="","",'IND-24'!G50),"") | AQ34: =IFERROR(IF('IND-24'!G51="","",'IND-24'!G51),"") | AR34: =IFERROR(IF('IND-24'!G52="","",'IND-24'!G52),"") | AS34: =IFERROR(IF('IND-24'!G53="","",'IND-24'!G53),"") | AT34: =IFERROR(IF('IND-24'!G54="","",'IND-24'!G54),"") | AU34: =IFERROR(IF('IND-24'!G55="","",'IND-24'!G55),"") | AV34: =IFERROR(IF('IND-24'!G56="","",'IND-24'!G56),"") | AW34: =IFERROR(IF('IND-24'!G57="","",'IND-24'!G57),"") | AX34: =IFERROR(IF('IND-24'!G58="","",'IND-24'!G58),"") | AY34: =IFERROR(IF('IND-24'!G59="","",'IND-24'!G59),"") | AZ34: =IFERROR(IF('IND-24'!G60="","",'IND-24'!G60),"") | BA34: =IFERROR(IF('IND-24'!G61="","",'IND-24'!G61),"") | BB34: =IFERROR(IF('IND-24'!G62="","",'IND-24'!G62),"") | BC34: =IFERROR(IF('IND-24'!G63="","",'IND-24'!G63),"") | BD34: =IFERROR(IF('IND-24'!G64="","",'IND-24'!G64),"") | BE34: =IFERROR(IF('IND-24'!G65="","",'IND-24'!G65),"") | BF34: =IFERROR(IF('IND-24'!G66="","",'IND-24'!G66),"") | BG34: =IFERROR(IF('IND-24'!G67="","",'IND-24'!G67),"") | BH34: =IFERROR(IF('IND-24'!G68="","",'IND-24'!G68),"") | BI34: =IFERROR(IF('IND-24'!G69="","",'IND-24'!G69),"") | BJ34: =IFERROR(IF('IND-24'!G70="","",'IND-24'!G70),"") | BK34: =IFERROR(IF('IND-24'!G71="","",'IND-24'!G71),"") | BL34: =IFERROR(IF('IND-24'!G72="","",'IND-24'!G72),"") | BM34: =IFERROR(IF('IND-24'!G73="","",'IND-24'!G73),"") | BN34: =IFERROR(IF('IND-24'!G74="","",'IND-24'!G74),"") | BO34: =IFERROR(IF('IND-24'!G75="","",'IND-24'!G75),"") | BP34: =IFERROR(IF('IND-24'!G76="","",'IND-24'!G76),"") | BQ34: =IFERROR(IF('IND-24'!G77="","",'IND-24'!G77),"") | BR34: =IFERROR(IF('IND-24'!G78="","",'IND-24'!G78),"") | BS34: =IFERROR(IF('IND-24'!G79="","",'IND-24'!G79),"") | BT34: =IFERROR(IF('IND-24'!G80="","",'IND-24'!G80),"") | BU34: =IFERROR(IF('IND-24'!G81="","",'IND-24'!G81),"") | BV34: =IFERROR(IF('IND-24'!G82="","",'IND-24'!G82),"") | BW34: =IFERROR(AVERAGE('IND-24'!I23:I34),"") | BX34: =IFERROR(AVERAGE('IND-24'!I35:I46),"") | BY34: =IFERROR(AVERAGE('IND-24'!I47:I58),"") | BZ34: =IFERROR(AVERAGE('IND-24'!I59:I70),"") | CA34: =IFERROR(AVERAGE('IND-24'!I71:I82),"") | CB34: =IFERROR(IF(LOOKUP(2,1/((BW34:CA34<>"")*(ISNUMBER(BW34:CA34))),BW34:CA34)>=0.95,"🟢 Cumple",IF(LOOKUP(2,1/((BW34:CA34<>"")*(ISNUMBER(BW34:CA34))),BW34:CA34)>=0.8,"🟡 En riesgo","🔴 Crítico")),"⚪ Pendiente") -> ⚪ Pendiente
B35: Formación y desarrollo del personal | C35: Clima organizacional y compromiso del personal | D35: Promedio de resultados de la encuesta de clima organizacional | E35: Mide la percepción de los colaboradores sobre el ambiente laboral. | F35: Puntos (escala) | G35: Mantener | H35: Anual | I35: =VLOOKUP("IND-25",Parámetros!$B$6:$F$30,5,FALSE()) -> Por definir | J35: ='IND-25'!C14 -> 1 | K35: ='IND-25'!C15 -> 1 | L35: ='IND-25'!C16 -> 1 | M35: ='IND-25'!C17 -> 1 | N35: ='IND-25'!C18 -> 1 | O35: =IFERROR(IF('IND-25'!F23="","",'IND-25'!F23),"") | P35: =IFERROR(IF('IND-25'!F24="","",'IND-25'!F24),"") | Q35: =IFERROR(IF('IND-25'!F25="","",'IND-25'!F25),"") | R35: =IFERROR(IF('IND-25'!F26="","",'IND-25'!F26),"") | S35: =IFERROR(IF('IND-25'!F27="","",'IND-25'!F27),"") | T35: =IFERROR(IF('IND-25'!F28="","",'IND-25'!F28),"") | U35: =IFERROR(IF('IND-25'!F29="","",'IND-25'!F29),"") | V35: =IFERROR(IF('IND-25'!F30="","",'IND-25'!F30),"") | W35: =IFERROR(IF('IND-25'!F31="","",'IND-25'!F31),"") | X35: =IFERROR(IF('IND-25'!F32="","",'IND-25'!F32),"") | Y35: =IFERROR(IF('IND-25'!F33="","",'IND-25'!F33),"") | Z35: =IFERROR(IF('IND-25'!F34="","",'IND-25'!F34),"") -> 0.83 | AA35: =IFERROR(IF('IND-25'!F35="","",'IND-25'!F35),"") | AB35: =IFERROR(IF('IND-25'!F36="","",'IND-25'!F36),"") | AC35: =IFERROR(IF('IND-25'!F37="","",'IND-25'!F37),"") | AD35: =IFERROR(IF('IND-25'!F38="","",'IND-25'!F38),"") | AE35: =IFERROR(IF('IND-25'!F39="","",'IND-25'!F39),"") | AF35: =IFERROR(IF('IND-25'!F40="","",'IND-25'!F40),"") | AG35: =IFERROR(IF('IND-25'!F41="","",'IND-25'!F41),"") | AH35: =IFERROR(IF('IND-25'!F42="","",'IND-25'!F42),"") | AI35: =IFERROR(IF('IND-25'!F43="","",'IND-25'!F43),"") | AJ35: =IFERROR(IF('IND-25'!F44="","",'IND-25'!F44),"") | AK35: =IFERROR(IF('IND-25'!F45="","",'IND-25'!F45),"") | AL35: =IFERROR(IF('IND-25'!F46="","",'IND-25'!F46),"") | AM35: =IFERROR(IF('IND-25'!F47="","",'IND-25'!F47),"") | AN35: =IFERROR(IF('IND-25'!F48="","",'IND-25'!F48),"") | AO35: =IFERROR(IF('IND-25'!F49="","",'IND-25'!F49),"") | AP35: =IFERROR(IF('IND-25'!F50="","",'IND-25'!F50),"") | AQ35: =IFERROR(IF('IND-25'!F51="","",'IND-25'!F51),"") | AR35: =IFERROR(IF('IND-25'!F52="","",'IND-25'!F52),"") | AS35: =IFERROR(IF('IND-25'!F53="","",'IND-25'!F53),"") | AT35: =IFERROR(IF('IND-25'!F54="","",'IND-25'!F54),"") | AU35: =IFERROR(IF('IND-25'!F55="","",'IND-25'!F55),"") | AV35: =IFERROR(IF('IND-25'!F56="","",'IND-25'!F56),"") | AW35: =IFERROR(IF('IND-25'!F57="","",'IND-25'!F57),"") | AX35: =IFERROR(IF('IND-25'!F58="","",'IND-25'!F58),"") | AY35: =IFERROR(IF('IND-25'!F59="","",'IND-25'!F59),"") | AZ35: =IFERROR(IF('IND-25'!F60="","",'IND-25'!F60),"") | BA35: =IFERROR(IF('IND-25'!F61="","",'IND-25'!F61),"") | BB35: =IFERROR(IF('IND-25'!F62="","",'IND-25'!F62),"") | BC35: =IFERROR(IF('IND-25'!F63="","",'IND-25'!F63),"") | BD35: =IFERROR(IF('IND-25'!F64="","",'IND-25'!F64),"") | BE35: =IFERROR(IF('IND-25'!F65="","",'IND-25'!F65),"") | BF35: =IFERROR(IF('IND-25'!F66="","",'IND-25'!F66),"") | BG35: =IFERROR(IF('IND-25'!F67="","",'IND-25'!F67),"") | BH35: =IFERROR(IF('IND-25'!F68="","",'IND-25'!F68),"") | BI35: =IFERROR(IF('IND-25'!F69="","",'IND-25'!F69),"") | BJ35: =IFERROR(IF('IND-25'!F70="","",'IND-25'!F70),"") | BK35: =IFERROR(IF('IND-25'!F71="","",'IND-25'!F71),"") | BL35: =IFERROR(IF('IND-25'!F72="","",'IND-25'!F72),"") | BM35: =IFERROR(IF('IND-25'!F73="","",'IND-25'!F73),"") | BN35: =IFERROR(IF('IND-25'!F74="","",'IND-25'!F74),"") | BO35: =IFERROR(IF('IND-25'!F75="","",'IND-25'!F75),"") | BP35: =IFERROR(IF('IND-25'!F76="","",'IND-25'!F76),"") | BQ35: =IFERROR(IF('IND-25'!F77="","",'IND-25'!F77),"") | BR35: =IFERROR(IF('IND-25'!F78="","",'IND-25'!F78),"") | BS35: =IFERROR(IF('IND-25'!F79="","",'IND-25'!F79),"") | BT35: =IFERROR(IF('IND-25'!F80="","",'IND-25'!F80),"") | BU35: =IFERROR(IF('IND-25'!F81="","",'IND-25'!F81),"") | BV35: =IFERROR(IF('IND-25'!F82="","",'IND-25'!F82),"") | BW35: =IFERROR(AVERAGE('IND-25'!H23:H34),"") -> 0.83 | BX35: =IFERROR(AVERAGE('IND-25'!H35:H46),"") | BY35: =IFERROR(AVERAGE('IND-25'!H47:H58),"") | BZ35: =IFERROR(AVERAGE('IND-25'!H59:H70),"") | CA35: =IFERROR(AVERAGE('IND-25'!H71:H82),"") | CB35: =IFERROR(IF(LOOKUP(2,1/((BW35:CA35<>"")*(ISNUMBER(BW35:CA35))),BW35:CA35)>=0.95,"🟢 Cumple",IF(LOOKUP(2,1/((BW35:CA35<>"")*(ISNUMBER(BW35:CA35))),BW35:CA35)>=0.8,"🟡 En riesgo","🔴 Crítico")),"⚪ Pendiente") -> 🟡 En riesgo

Sheet Parámetros
B2: ⚙️ PARÁMETROS DE CONFIGURACIÓN
B4: 👤 CATÁLOGO DE RESPONSABLES POR INDICADOR (editable)
B5: Código | C5: Perspectiva | D5: Objetivo Específico | E5: Indicador | F5: Responsable
B6: IND-01 | C6: 💰 Financiera | D6: Aumento de ingresos | E6: Crecimiento de cartera en líneas de mayor rendimiento | F6: Gerencia Financiera
B7: IND-02 | C7: 💰 Financiera | D7: Aumento de ingresos | E7: Crecimiento de ingresos operativos | F7: Gerencia Financiera
B8: IND-03 | C8: 💰 Financiera | D8: Aumento de ingresos | E8: Crecimiento de ingresos por comisiones | F8: Cartera
B9: IND-04 | C9: 💰 Financiera | D9: Aumento de ingresos | E9: Rentabilidad Fondo de Liquidez | F9: Tesorería
B10: IND-05 | C10: 💰 Financiera | D10: Reducción de mora | E10: Índice de mora | F10: Cartera
B11: IND-06 | C11: 💰 Financiera | D11: Reducción de mora | E11: Tasa de recuperación | F11: Por definir
B12: IND-07 | C12: 💰 Financiera | D12: Reducción de mora | E12: Tasa de normalización de cartera | F12: Por definir
B13: IND-08 | C13: 💰 Financiera | D13: Crecimiento y remuneración de depósitos | E13: Tasa de crecimiento de ahorros | F13: Por definir
B14: IND-09 | C14: 💰 Financiera | D14: Crecimiento y remuneración de depósitos | E14: Rentabilidad real de los depósitos | F14: Por definir
B15: IND-10 | C15: 💰 Financiera | D15: Rentabilidad y fortalecimiento patrimonial | E15: Suficiencia del Margen | F15: Por definir
B16: IND-11 | C16: 💰 Financiera | D16: Rentabilidad y fortalecimiento patrimonial | E16: Cumplimiento de pago de aportes sociales | F16: Por definir
... B30: IND-25 | C30: 🎓 Aprendizaje | D30: Formación y desarrollo del personal | E30: Clima organizacional y compromiso del personal | F30: Por definir
B32: 📊 REFERENCIAS MENSUALES (IPC / IBR — usadas en indicadores que las requieren)
B33: Año | C33: Mes | D33: IPC (%) | E33: IBR (%)
B34: 2026 | C34: Ene
B35: 2026 | C35: Feb
B36: 2026 | C36: Mar
B37: 2026 | C37: Abr
B38: 2026 | C38: May
B39: 2026 | C39: Jun
B40: 2026 | C40: Jul
B41: 2026 | C41: Ago
B42: 2026 | C42: Sep
B43: 2026 | C43: Oct
B44: 2026 | C44: Nov
B45: 2026 | C45: Dic
... B93: 2030 | C93: Dic

Sheet IND-01
B2: 💰 IND-01 · CRECIMIENTO DE CARTERA EN LÍNEAS DE MAYOR RENDIMIENTO
B3: Perspectiva: Financiera · Objetivo específico: 📈 Aumento de ingresos
B5: Fórmula | D5: Saldo de cartera de líneas de mayor rendimiento ÷ Saldo total de cartera
B6: Descripción | D6: Mide la participación de las líneas de crédito con mayor tasa efectiva y contribución al margen financiero. Por el momento, Rotativo y Tarjeta de Crédito.
B7: Unidad | D7: %
B8: Tendencia objetivo | D8: Crecer
B9: Frecuencia | D9: Mensual
B10: Responsable | D10: =VLOOKUP("IND-01",Parámetros!$B$6:$F$30,5,FALSE()) -> Gerencia Financiera
B12: 🎯 METAS ANUALES (editable)
B13: Año | C13: Meta | E13: Notas
B14: 2026 | C14: 0.08
B15: 2027 | C15: 0.1
B16: 2028 | C16: 0.12
B17: 2029 | C17: 0.14
B18: 2030 | C18: 0.16
B20: 📝 CAPTURA MENSUAL DE VARIABLES (Ene-2026 → Dic-2030)
B21: Ingrese los valores en las celdas azules. El resultado, % cumplimiento y semáforo se calculan automáticamente. Solo se habilitan los meses según la frecuencia del indicador.
B22: # | C22: Año | D22: Mes | E22: Saldo cartera líneas mayor rendimiento ($) | F22: Saldo total de cartera ($) | G22: Resultado | H22: Meta año | I22: % Cumpl. | J22: Estado
B23: 1 | C23: 2026 | D23: Enero | E23: 80 | F23: 1000 | G23: =IFERROR(IF(F23=0,"",E23/F23),"") -> 0.08 | H23: =IFERROR(VLOOKUP(C23,$B$14:$C$18,2,FALSE()),"") -> 0.08 | I23: =IFERROR(IF(OR(G23="",NOT(ISNUMBER(H23))),"",G23/H23),"") -> 1 | J23: =IFERROR(IF(I23="","Pendiente",IF(I23>=0.95,"Cumple",IF(I23>=0.8,"En riesgo","Crítico"))),"Pendiente") -> Cumple
B24: 2 | C24: 2026 | D24: Febrero | E24: 80 | F24: 1000 | G24: =IFERROR(IF(F24=0,"",E24/F24),"") -> 0.08 | H24: =IFERROR(VLOOKUP(C24,$B$14:$C$18,2,FALSE()),"") -> 0.08 | I24: =IFERROR(IF(OR(G24="",NOT(ISNUMBER(H24))),"",G24/H24),"") -> 1 | J24: =IFERROR(IF(I24="","Pendiente",IF(I24>=0.95,"Cumple",IF(I24>=0.8,"En riesgo","Crítico"))),"Pendiente") -> Cumple
B25: 3 | C25: 2026 | D25: Marzo | E25: 80 | F25: 1000 | G25: =IFERROR(IF(F25=0,"",E25/F25),"") -> 0.08 | H25: =IFERROR(VLOOKUP(C25,$B$14:$C$18,2,FALSE()),"") -> 0.08 | I25: =IFERROR(IF(OR(G25="",NOT(ISNUMBER(H25))),"",G25/H25),"") -> 1 | J25: =IFERROR(IF(I25="","Pendiente",IF(I25>=0.95,"Cumple",IF(I25>=0.8,"En riesgo","Crítico"))),"Pendiente") -> Cumple
B26: 4 | C26: 2026 | D26: Abril | E26: 80 | F26: 1000 | G26: =IFERROR(IF(F26=0,"",E26/F26),"") -> 0.08 | H26: =IFERROR(VLOOKUP(C26,$B$14:$C$18,2,FALSE()),"") -> 0.08 | I26: =IFERROR(IF(OR(G26="",NOT(ISNUMBER(H26))),"",G26/H26),"") -> 1 | J26: =IFERROR(IF(I26="","Pendiente",IF(I26>=0.95,"Cumple",IF(I26>=0.8,"En riesgo","Crítico"))),"Pendiente") -> Cumple
B27: 5 | C27: 2026 | D27: Mayo | E27: 80 | F27: 1000 | G27: =IFERROR(IF(F27=0,"",E27/F27),"") -> 0.08 | H27: =IFERROR(VLOOKUP(C27,$B$14:$C$18,2,FALSE()),"") -> 0.08 | I27: =IFERROR(IF(OR(G27="",NOT(ISNUMBER(H27))),"",G27/H27),"") -> 1 | J27: =IFERROR(IF(I27="","Pendiente",IF(I27>=0.95,"Cumple",IF(I27>=0.8,"En riesgo","Crítico"))),"Pendiente") -> Cumple
B28: 6 | C28: 2026 | D28: Junio | E28: 80 | F28: 1000 | G28: =IFERROR(IF(F28=0,"",E28/F28),"") -> 0.08 | H28: =IFERROR(VLOOKUP(C28,$B$14:$C$18,2,FALSE()),"") -> 0.08 | I28: =IFERROR(IF(OR(G28="",NOT(ISNUMBER(H28))),"",G28/H28),"") -> 1 | J28: =IFERROR(IF(I28="","Pendiente",IF(I28>=0.95,"Cumple",IF(I28>=0.8,"En riesgo","Crítico"))),"Pendiente") -> Cumple
B29: 7 | C29: 2026 | D29: Julio | E29: 80 | F29: 1000 | G29: =IFERROR(IF(F29=0,"",E29/F29),"") -> 0.08 | H29: =IFERROR(VLOOKUP(C29,$B$14:$C$18,2,FALSE()),"") -> 0.08 | I29: =IFERROR(IF(OR(G29="",NOT(ISNUMBER(H29))),"",G29/H29),"") -> 1 | J29: =IFERROR(IF(I29="","Pendiente",IF(I29>=0.95,"Cumple",IF(I29>=0.8,"En riesgo","Crítico"))),"Pendiente") -> Cumple
B30: 8 | C30: 2026 | D30: Agosto | E30: 80 | F30: 1000 | G30: =IFERROR(IF(F30=0,"",E30/F30),"") -> 0.08 | H30: =IFERROR(VLOOKUP(C30,$B$14:$C$18,2,FALSE()),"") -> 0.08 | I30: =IFERROR(IF(OR(G30="",NOT(ISNUMBER(H30))),"",G30/H30),"") -> 1 | J30: =IFERROR(IF(I30="","Pendiente",IF(I30>=0.95,"Cumple",IF(I30>=0.8,"En riesgo","Crítico"))),"Pendiente") -> Cumple
B31: 9 | C31: 2026 | D31: Septiembre | E31: 80 | F31: 1000 | G31: =IFERROR(IF(F31=0,"",E31/F31),"") -> 0.08 | H31: =IFERROR(VLOOKUP(C31,$B$14:$C$18,2,FALSE()),"") -> 0.08 | I31: =IFERROR(IF(OR(G31="",NOT(ISNUMBER(H31))),"",G31/H31),"") -> 1 | J31: =IFERROR(IF(I31="","Pendiente",IF(I31>=0.95,"Cumple",IF(I31>=0.8,"En riesgo","Crítico"))),"Pendiente") -> Cumple
B32: 10 | C32: 2026 | D32: Octubre | E32: 80 | F32: 1000 | G32: =IFERROR(IF(F32=0,"",E32/F32),"") -> 0.08 | H32: =IFERROR(VLOOKUP(C32,$B$14:$C$18,2,FALSE()),"") -> 0.08 | I32: =IFERROR(IF(OR(G32="",NOT(ISNUMBER(H32))),"",G32/H32),"") -> 1 | J32: =IFERROR(IF(I32="","Pendiente",IF(I32>=0.95,"Cumple",IF(I32>=0.8,"En riesgo","Crítico"))),"Pendiente") -> Cumple
B33: 11 | C33: 2026 | D33: Noviembre | E33: 80 | F33: 1000 | G33: =IFERROR(IF(F33=0,"",E33/F33),"") -> 0.08 | H33: =IFERROR(VLOOKUP(C33,$B$14:$C$18,2,FALSE()),"") -> 0.08 | I33: =IFERROR(IF(OR(G33="",NOT(ISNUMBER(H33))),"",G33/H33),"") -> 1 | J33: =IFERROR(IF(I33="","Pendiente",IF(I33>=0.95,"Cumple",IF(I33>=0.8,"En riesgo","Crítico"))),"Pendiente") -> Cumple
B34: 12 | C34: 2026 | D34: Diciembre | E34: 80 | F34: 1000 | G34: =IFERROR(IF(F34=0,"",E34/F34),"") -> 0.08 | H34: =IFERROR(VLOOKUP(C34,$B$14:$C$18,2,FALSE()),"") -> 0.08 | I34: =IFERROR(IF(OR(G34="",NOT(ISNUMBER(H34))),"",G34/H34),"") -> 1 | J34: =IFERROR(IF(I34="","Pendiente",IF(I34>=0.95,"Cumple",IF(I34>=0.8,"En riesgo","Crítico"))),"Pendiente") -> Cumple
... B40: 18 | C40: 2027 | D40: Junio | E40: 95 | F40: 1000 | G40: =IFERROR(IF(F40=0,"",E40/F40),"") -> 0.095 | H40: =IFERROR(VLOOKUP(C40,$B$14:$C$18,2,FALSE()),"") -> 0.1 | I40: =IFERROR(IF(OR(G40="",NOT(ISNUMBER(H40))),"",G40/H40),"") -> 0.95 | J40: =IFERROR(IF(I40="","Pendiente",IF(I40>=0.95,"Cumple",IF(I40>=0.8,"En riesgo","Crítico"))),"Pendiente") -> Cumple
B41: 19 | C41: 2027 | D41: Julio | G41: =IFERROR(IF(F41=0,"",E41/F41),"") | H41: =IFERROR(VLOOKUP(C41,$B$14:$C$18,2,FALSE()),"") -> 0.1 | I41: =IFERROR(IF(OR(G41="",NOT(ISNUMBER(H41))),"",G41/H41),"") | J41: =IFERROR(IF(I41="","Pendiente",IF(I41>=0.95,"Cumple",IF(I41>=0.8,"En riesgo","Crítico"))),"Pendiente") -> Pendiente
B42: 20 | C42: 2027 | D42: Agosto | G42: =IFERROR(IF(F42=0,"",E42/F42),"") | H42: =IFERROR(VLOOKUP(C42,$B$14:$C$18,2,FALSE()),"") -> 0.1 | I42: =IFERROR(IF(OR(G42="",NOT(ISNUMBER(H42))),"",G42/H42),"") | J42: =IFERROR(IF(I42="","Pendiente",IF(I42>=0.95,"Cumple",IF(I42>=0.8,"En riesgo","Crítico"))),"Pendiente") -> Pendiente
B43: 21 | C43: 2027 | D43: Septiembre | G43: =IFERROR(IF(F43=0,"",E43/F43),"") | H43: =IFERROR(VLOOKUP(C43,$B$14:$C$18,2,FALSE()),"") -> 0.1 | I43: =IFERROR(IF(OR(G43="",NOT(ISNUMBER(H43))),"",G43/H43),"") | J43: =IFERROR(IF(I43="","Pendiente",IF(I43>=0.95,"Cumple",IF(I43>=0.8,"En riesgo","Crítico"))),"Pendiente") -> Pendiente
B44: 22 | C44: 2027 | D44: Octubre | G44: =IFERROR(IF(F44=0,"",E44/F44),"") | H44: =IFERROR(VLOOKUP(C44,$B$14:$C$18,2,FALSE()),"") -> 0.1 | I44: =IFERROR(IF(OR(G44="",NOT(ISNUMBER(H44))),"",G44/H44),"") | J44: =IFERROR(IF(I44="","Pendiente",IF(I44>=0.95,"Cumple",IF(I44>=0.8,"En riesgo","Crítico"))),"Pendiente") -> Pendiente
B45: 23 | C45: 2027 | D45: Noviembre | G45: =IFERROR(IF(F45=0,"",E45/F45),"") | H45: =IFERROR(VLOOKUP(C45,$B$14:$C$18,2,FALSE()),"") -> 0.1 | I45: =IFERROR(IF(OR(G45="",NOT(ISNUMBER(H45))),"",G45/H45),"") | J45: =IFERROR(IF(I45="","Pendiente",IF(I45>=0.95,"Cumple",IF(I45>=0.8,"En riesgo","Crítico"))),"Pendiente") -> Pendiente
B46: 24 | C46: 2027 | D46: Diciembre | G46: =IFERROR(IF(F46=0,"",E46/F46),"") | H46: =IFERROR(VLOOKUP(C46,$B$14:$C$18,2,FALSE()),"") -> 0.1 | I46: =IFERROR(IF(OR(G46="",NOT(ISNUMBER(H46))),"",G46/H46),"") | J46: =IFERROR(IF(I46="","Pendiente",IF(I46>=0.95,"Cumple",IF(I46>=0.8,"En riesgo","Crítico"))),"Pendiente") -> Pendiente
B47: 25 | C47: 2028 | D47: Enero | G47: =IFERROR(IF(F47=0,"",E47/F47),"") | H47: =IFERROR(VLOOKUP(C47,$B$14:$C$18,2,FALSE()),"") -> 0.12 | I47: =IFERROR(IF(OR(G47="",NOT(ISNUMBER(H47))),"",G47/H47),"") | J47: =IFERROR(IF(I47="","Pendiente",IF(I47>=0.95,"Cumple",IF(I47>=0.8,"En riesgo","Crítico"))),"Pendiente") -> Pendiente
B48: 26 | C48: 2028 | D48: Febrero | G48: =IFERROR(IF(F48=0,"",E48/F48),"") | H48: =IFERROR(VLOOKUP(C48,$B$14:$C$18,2,FALSE()),"") -> 0.12 | I48: =IFERROR(IF(OR(G48="",NOT(ISNUMBER(H48))),"",G48/H48),"") | J48: =IFERROR(IF(I48="","Pendiente",IF(I48>=0.95,"Cumple",IF(I48>=0.8,"En riesgo","Crítico"))),"Pendiente") -> Pendiente
B49: 27 | C49: 2028 | D49: Marzo | G49: =IFERROR(IF(F49=0,"",E49/F49),"") | H49: =IFERROR(VLOOKUP(C49,$B$14:$C$18,2,FALSE()),"") -> 0.12 | I49: =IFERROR(IF(OR(G49="",NOT(ISNUMBER(H49))),"",G49/H49),"") | J49: =IFERROR(IF(I49="","Pendiente",IF(I49>=0.95,"Cumple",IF(I49>=0.8,"En riesgo","Crítico"))),"Pendiente") -> Pendiente
B50: 28 | C50: 2028 | D50: Abril | G50: =IFERROR(IF(F50=0,"",E50/F50),"") | H50: =IFERROR(VLOOKUP(C50,$B$14:$C$18,2,FALSE()),"") -> 0.12 | I50: =IFERROR(IF(OR(G50="",NOT(ISNUMBER(H50))),"",G50/H50),"") | J50: =IFERROR(IF(I50="","Pendiente",IF(I50>=0.95,"Cumple",IF(I50>=0.8,"En riesgo","Crítico"))),"Pendiente") -> Pendiente
B51: 29 | C51: 2028 | D51: Mayo | G51: =IFERROR(IF(F51=0,"",E51/F51),"") | H51: =IFERROR(VLOOKUP(C51,$B$14:$C$18,2,FALSE()),"") -> 0.12 | I51: =IFERROR(IF(OR(G51="",NOT(ISNUMBER(H51))),"",G51/H51),"") | J51: =IFERROR(IF(I51="","Pendiente",IF(I51>=0.95,"Cumple",IF(I51>=0.8,"En riesgo","Crítico"))),"Pendiente") -> Pendiente
B52: 30 | C52: 2028 | D52: Junio | G52: =IFERROR(IF(F52=0,"",E52/F52),"") | H52: =IFERROR(VLOOKUP(C52,$B$14:$C$18,2,FALSE()),"") -> 0.12 | I52: =IFERROR(IF(OR(G52="",NOT(ISNUMBER(H52))),"",G52/H52),"") | J52: =IFERROR(IF(I52="","Pendiente",IF(I52>=0.95,"Cumple",IF(I52>=0.8,"En riesgo","Crítico"))),"Pendiente") -> Pendiente
... B82: 60 | C82: 2030 | D82: Diciembre | G82: =IFERROR(IF(F82=0,"",E82/F82),"") | H82: =IFERROR(VLOOKUP(C82,$B$14:$C$18,2,FALSE()),"") -> 0.16 | I82: =IFERROR(IF(OR(G82="",NOT(ISNUMBER(H82))),"",G82/H82),"") | J82: =IFERROR(IF(I82="","Pendiente",IF(I82>=0.95,"Cumple",IF(I82>=0.8,"En riesgo","Crítico"))),"Pendiente") -> Pendiente

Sheet IND-02
B2: 💰 IND-02 · CRECIMIENTO DE INGRESOS OPERATIVOS
B3: Perspectiva: Financiera · Objetivo específico: 📈 Aumento de ingresos
B5: Fórmula | D5: (Ingresos de cartera final − Ingresos de cartera inicial) ÷ Ingresos de cartera inicial
B6: Descripción | D6: Refleja el impacto directo de la colocación sobre los ingresos financieros.
B7: Unidad | D7: %
B8: Tendencia objetivo | D8: Crecer
B9: Frecuencia | D9: Mensual
B10: Responsable | D10: =VLOOKUP("IND-02",Parámetros!$B$6:$F$30,5,FALSE()) -> Gerencia Financiera
B12: 🎯 METAS ANUALES (editable)
B13: Año | C13: Meta | E13: Notas
B14: 2026 | C14: 0.1
B15: 2027 | C15: 0.1
B16: 2028 | C16: 0.1
B17: 2029 | C17: 0.1
B18: 2030 | C18: 0.1
B20: 📝 CAPTURA MENSUAL DE VARIABLES (Ene-2026 → Dic-2030)
B21: Ingrese los valores en las celdas azules. El resultado, % cumplimiento y semáforo se calculan automáticamente. Solo se habilitan los meses según la frecuencia del indicador.
B22: # | C22: Año | D22: Mes | E22: Ingresos de cartera del mes ($) | F22: Resultado | G22: Meta año | H22: % Cumpl. | I22: Estado
B23: 1 | C23: 2026 | D23: Enero | E23: 1000000 | G23: =IFERROR(VLOOKUP(C23,$B$14:$C$18,2,FALSE()),"") -> 0.1 | H23: =IFERROR(IF(OR(F23="",NOT(ISNUMBER(G23))),"",F23/G23),"") | I23: =IFERROR(IF(H23="","Pendiente",IF(H23>=0.95,"Cumple",IF(H23>=0.8,"En riesgo","Crítico"))),"Pendiente") -> Pendiente
B24: 2 | C24: 2026 | D24: Febrero | E24: 1008000 | F24: =IFERROR(IF(OR(E24="",E23="",E23=0),"",(E24-E23)/E23),"") -> 0.008 | G24: =IFERROR(VLOOKUP(C24,$B$14:$C$18,2,FALSE()),"") -> 0.1 | H24: =IFERROR(IF(OR(F24="",NOT(ISNUMBER(G24))),"",F24/G24),"") -> 0.08 | I24: =IFERROR(IF(H24="","Pendiente",IF(H24>=0.95,"Cumple",IF(H24>=0.8,"En riesgo","Crítico"))),"Pendiente") -> Crítico
B25: 3 | C25: 2026 | D25: Marzo | E25: 1016064 | F25: =IFERROR(IF(OR(E25="",E24="",E24=0),"",(E25-E24)/E24),"") -> 0.008 | G25: =IFERROR(VLOOKUP(C25,$B$14:$C$18,2,FALSE()),"") -> 0.1 | H25: =IFERROR(IF(OR(F25="",NOT(ISNUMBER(G25))),"",F25/G25),"") -> 0.08 | I25: =IFERROR(IF(H25="","Pendiente",IF(H25>=0.95,"Cumple",IF(H25>=0.8,"En riesgo","Crítico"))),"Pendiente") -> Crítico
B26: 4 | C26: 2026 | D26: Abril | E26: 1024192.5 | F26: =IFERROR(IF(OR(E26="",E25="",E25=0),"",(E26-E25)/E25),"") -> 0.008 | G26: =IFERROR(VLOOKUP(C26,$B$14:$C$18,2,FALSE()),"") -> 0.1 | H26: =IFERROR(IF(OR(F26="",NOT(ISNUMBER(G26))),"",F26/G26),"") -> 0.08 | I26: =IFERROR(IF(H26="","Pendiente",IF(H26>=0.95,"Cumple",IF(H26>=0.8,"En riesgo","Crítico"))),"Pendiente") -> Crítico
B27: 5 | C27: 2026 | D27: Mayo | E27: 1032386.1 | F27: =IFERROR(IF(OR(E27="",E26="",E26=0),"",(E27-E26)/E26),"") -> 0.008 | G27: =IFERROR(VLOOKUP(C27,$B$14:$C$18,2,FALSE()),"") -> 0.1 | H27: =IFERROR(IF(OR(F27="",NOT(ISNUMBER(G27))),"",F27/G27),"") -> 0.08 | I27: =IFERROR(IF(H27="","Pendiente",IF(H27>=0.95,"Cumple",IF(H27>=0.8,"En riesgo","Crítico"))),"Pendiente") -> Crítico
B28: 6 | C28: 2026 | D28: Junio | E28: 1040645.1 | F28: =IFERROR(IF(OR(E28="",E27="",E27=0),"",(E28-E27)/E27),"") -> 0.008 | G28: =IFERROR(VLOOKUP(C28,$B$14:$C$18,2,FALSE()),"") -> 0.1 | H28: =IFERROR(IF(OR(F28="",NOT(ISNUMBER(G28))),"",F28/G28),"") -> 0.08 | I28: =IFERROR(IF(H28="","Pendiente",IF(H28>=0.95,"Cumple",IF(H28>=0.8,"En riesgo","Crítico"))),"Pendiente") -> Crítico
B29: 7 | C29: 2026 | D29: Julio | E29: 1048970.3 | F29: =IFERROR(IF(OR(E29="",E28="",E28=0),"",(E29-E28)/E28),"") -> 0.008 | G29: =IFERROR(VLOOKUP(C29,$B$14:$C$18,2,FALSE()),"") -> 0.1 | H29: =IFERROR(IF(OR(F29="",NOT(ISNUMBER(G29))),"",F29/G29),"") -> 0.08 | I29: =IFERROR(IF(H29="","Pendiente",IF(H29>=0.95,"Cumple",IF(H29>=0.8,"En riesgo","Crítico"))),"Pendiente") -> Crítico
B30: 8 | C30: 2026 | D30: Agosto | E30: 1057362.1 | F30: =IFERROR(IF(OR(E30="",E29="",E29=0),"",(E30-E29)/E29),"") -> 0.008 | G30: =IFERROR(VLOOKUP(C30,$B$14:$C$18,2,FALSE()),"") -> 0.1 | H30: =IFERROR(IF(OR(F30="",NOT(ISNUMBER(G30))),"",F30/G30),"") -> 0.08 | I30: =IFERROR(IF(H30="","Pendiente",IF(H30>=0.95,"Cumple",IF(H30>=0.8,"En riesgo","Crítico"))),"Pendiente") -> Crítico
B31: 9 | C31: 2026 | D31: Septiembre | E31: 1065821 | F31: =IFERROR(IF(OR(E31="",E30="",E30=0),"",(E31-E30)/E30),"") -> 0.008 | G31: =IFERROR(VLOOKUP(C31,$B$14:$C$18,2,FALSE()),"") -> 0.1 | H31: =IFERROR(IF(OR(F31="",NOT(ISNUMBER(G31))),"",F31/G31),"") -> 0.08 | I31: =IFERROR(IF(H31="","Pendiente",IF(H31>=0.95,"Cumple",IF(H31>=0.8,"En riesgo","Crítico"))),"Pendiente") -> Crítico
B32: 10 | C32: 2026 | D32: Octubre | E32: 1074347.5 | F32: =IFERROR(IF(OR(E32="",E31="",E31=0),"",(E32-E31)/E31),"") -> 0.008 | G32: =IFERROR(VLOOKUP(C32,$B$14:$C$18,2,FALSE()),"") -> 0.1 | H32: =IFERROR(IF(OR(F32="",NOT(ISNUMBER(G32))),"",F32/G32),"") -> 0.08 | I32: =IFERROR(IF(H32="","Pendiente",IF(H32>=0.95,"Cumple",IF(H32>=0.8,"En riesgo","Crítico"))),"Pendiente") -> Crítico
B33: 11 | C33: 2026 | D33: Noviembre | E33: 1082942.3 | F33: =IFERROR(IF(OR(E33="",E32="",E32=0),"",(E33-E32)/E32),"") -> 0.008 | G33: =IFERROR(VLOOKUP(C33,$B$14:$C$18,2,FALSE()),"") -> 0.1 | H33: =IFERROR(IF(OR(F33="",NOT(ISNUMBER(G33))),"",F33/G33),"") -> 0.08 | I33: =IFERROR(IF(H33="","Pendiente",IF(H33>=0.95,"Cumple",IF(H33>=0.8,"En riesgo","Crítico"))),"Pendiente") -> Crítico
B34: 12 | C34: 2026 | D34: Diciembre | E34: 1091605.8 | F34: =IFERROR(IF(OR(E34="",E33="",E33=0),"",(E34-E33)/E33),"") -> 0.008 | G34: =IFERROR(VLOOKUP(C34,$B$14:$C$18,2,FALSE()),"") -> 0.1 | H34: =IFERROR(IF(OR(F34="",NOT(ISNUMBER(G34))),"",F34/G34),"") -> 0.08 | I34: =IFERROR(IF(H34="","Pendiente",IF(H34>=0.95,"Cumple",IF(H34>=0.8,"En riesgo","Crítico"))),"Pendiente") -> Crítico
B35: 13 | C35: 2027 | D35: Enero | E35: 1100338.7 | F35: =IFERROR(IF(OR(E35="",E34="",E34=0),"",(E35-E34)/E34),"") -> 0.008 | G35: =IFERROR(VLOOKUP(C35,$B$14:$C$18,2,FALSE()),"") -> 0.1 | H35: =IFERROR(IF(OR(F35="",NOT(ISNUMBER(G35))),"",F35/G35),"") -> 0.08 | I35: =IFERROR(IF(H35="","Pendiente",IF(H35>=0.95,"Cumple",IF(H35>=0.8,"En riesgo","Crítico"))),"Pendiente") -> Crítico
... B40: 18 | C40: 2027 | D40: Junio | E40: 1145062.1 | F40: =IFERROR(IF(OR(E40="",E39="",E39=0),"",(E40-E39)/E39),"") -> 0.008 | G40: =IFERROR(VLOOKUP(C40,$B$14:$C$18,2,FALSE()),"") -> 0.1 | H40: =IFERROR(IF(OR(F40="",NOT(ISNUMBER(G40))),"",F40/G40),"") -> 0.08 | I40: =IFERROR(IF(H40="","Pendiente",IF(H40>=0.95,"Cumple",IF(H40>=0.8,"En riesgo","Crítico"))),"Pendiente") -> Crítico
B41: 19 | C41: 2027 | D41: Julio | F41: =IFERROR(IF(OR(E41="",E40="",E40=0),"",(E41-E40)/E40),"") | G41: =IFERROR(VLOOKUP(C41,$B$14:$C$18,2,FALSE()),"") -> 0.1 | H41: =IFERROR(IF(OR(F41="",NOT(ISNUMBER(G41))),"",F41/G41),"") | I41: =IFERROR(IF(H41="","Pendiente",IF(H41>=0.95,"Cumple",IF(H41>=0.8,"En riesgo","Crítico"))),"Pendiente") -> Pendiente
B42: 20 | C42: 2027 | D42: Agosto | F42: =IFERROR(IF(OR(E42="",E41="",E41=0),"",(E42-E41)/E41),"") | G42: =IFERROR(VLOOKUP(C42,$B$14:$C$18,2,FALSE()),"") -> 0.1 | H42: =IFERROR(IF(OR(F42="",NOT(ISNUMBER(G42))),"",F42/G42),"") | I42: =IFERROR(IF(H42="","Pendiente",IF(H42>=0.95,"Cumple",IF(H42>=0.8,"En riesgo","Crítico"))),"Pendiente") -> Pendiente
B43: 21 | C43: 2027 | D43: Septiembre | F43: =IFERROR(IF(OR(E43="",E42="",E42=0),"",(E43-E42)/E42),"") | G43: =IFERROR(VLOOKUP(C43,$B$14:$C$18,2,FALSE()),"") -> 0.1 | H43: =IFERROR(IF(OR(F43="",NOT(ISNUMBER(G43))),"",F43/G43),"") | I43: =IFERROR(IF(H43="","Pendiente",IF(H43>=0.95,"Cumple",IF(H43>=0.8,"En riesgo","Crítico"))),"Pendiente") -> Pendiente
B44: 22 | C44: 2027 | D44: Octubre | F44: =IFERROR(IF(OR(E44="",E43="",E43=0),"",(E44-E43)/E43),"") | G44: =IFERROR(VLOOKUP(C44,$B$14:$C$18,2,FALSE()),"") -> 0.1 | H44: =IFERROR(IF(OR(F44="",NOT(ISNUMBER(G44))),"",F44/G44),"") | I44: =IFERROR(IF(H44="","Pendiente",IF(H44>=0.95,"Cumple",IF(H44>=0.8,"En riesgo","Crítico"))),"Pendiente") -> Pendiente
B45: 23 | C45: 2027 | D45: Noviembre | F45: =IFERROR(IF(OR(E45="",E44="",E44=0),"",(E45-E44)/E44),"") | G45: =IFERROR(VLOOKUP(C45,$B$14:$C$18,2,FALSE()),"") -> 0.1 | H45: =IFERROR(IF(OR(F45="",NOT(ISNUMBER(G45))),"",F45/G45),"") | I45: =IFERROR(IF(H45="","Pendiente",IF(H45>=0.95,"Cumple",IF(H45>=0.8,"En riesgo","Crítico"))),"Pendiente") -> Pendiente
B46: 24 | C46: 2027 | D46: Diciembre | F46: =IFERROR(IF(OR(E46="",E45="",E45=0),"",(E46-E45)/E45),"") | G46: =IFERROR(VLOOKUP(C46,$B$14:$C$18,2,FALSE()),"") -> 0.1 | H46: =IFERROR(IF(OR(F46="",NOT(ISNUMBER(G46))),"",F46/G46),"") | I46: =IFERROR(IF(H46="","Pendiente",IF(H46>=0.95,"Cumple",IF(H46>=0.8,"En riesgo","Crítico"))),"Pendiente") -> Pendiente
B47: 25 | C47: 2028 | D47: Enero | F47: =IFERROR(IF(OR(E47="",E46="",E46=0),"",(E47-E46)/E46),"") | G47: =IFERROR(VLOOKUP(C47,$B$14:$C$18,2,FALSE()),"") -> 0.1 | H47: =IFERROR(IF(OR(F47="",NOT(ISNUMBER(G47))),"",F47/G47),"") | I47: =IFERROR(IF(H47="","Pendiente",IF(H47>=0.95,"Cumple",IF(H47>=0.8,"En riesgo","Crítico"))),"Pendiente") -> Pendiente
B48: 26 | C48: 2028 | D48: Febrero | F48: =IFERROR(IF(OR(E48="",E47="",E47=0),"",(E48-E47)/E47),"") | G48: =IFERROR(VLOOKUP(C48,$B$14:$C$18,2,FALSE()),"") -> 0.1 | H48: =IFERROR(IF(OR(F48="",NOT(ISNUMBER(G48))),"",F48/G48),"") | I48: =IFERROR(IF(H48="","Pendiente",IF(H48>=0.95,"Cumple",IF(H48>=0.8,"En riesgo","Crítico"))),"Pendiente") -> Pendiente
B49: 27 | C49: 2028 | D49: Marzo | F49: =IFERROR(IF(OR(E49="",E48="",E48=0),"",(E49-E48)/E48),"") | G49: =IFERROR(VLOOKUP(C49,$B$14:$C$18,2,FALSE()),"") -> 0.1 | H49: =IFERROR(IF(OR(F49="",NOT(ISNUMBER(G49))),"",F49/G49),"") | I49: =IFERROR(IF(H49="","Pendiente",IF(H49>=0.95,"Cumple",IF(H49>=0.8,"En riesgo","Crítico"))),"Pendiente") -> Pendiente
B50: 28 | C50: 2028 | D50: Abril | F50: =IFERROR(IF(OR(E50="",E49="",E49=0),"",(E50-E49)/E49),"") | G50: =IFERROR(VLOOKUP(C50,$B$14:$C$18,2,FALSE()),"") -> 0.1 | H50: =IFERROR(IF(OR(F50="",NOT(ISNUMBER(G50))),"",F50/G50),"") | I50: =IFERROR(IF(H50="","Pendiente",IF(H50>=0.95,"Cumple",IF(H50>=0.8,"En riesgo","Crítico"))),"Pendiente") -> Pendiente
B51: 29 | C51: 2028 | D51: Mayo | F51: =IFERROR(IF(OR(E51="",E50="",E50=0),"",(E51-E50)/E50),"") | G51: =IFERROR(VLOOKUP(C51,$B$14:$C$18,2,FALSE()),"") -> 0.1 | H51: =IFERROR(IF(OR(F51="",NOT(ISNUMBER(G51))),"",F51/G51),"") | I51: =IFERROR(IF(H51="","Pendiente",IF(H51>=0.95,"Cumple",IF(H51>=0.8,"En riesgo","Crítico"))),"Pendiente") -> Pendiente
B52: 30 | C52: 2028 | D52: Junio | F52: =IFERROR(IF(OR(E52="",E51="",E51=0),"",(E52-E51)/E51),"") | G52: =IFERROR(VLOOKUP(C52,$B$14:$C$18,2,FALSE()),"") -> 0.1 | H52: =IFERROR(IF(OR(F52="",NOT(ISNUMBER(G52))),"",F52/G52),"") | I52: =IFERROR(IF(H52="","Pendiente",IF(H52>=0.95,"Cumple",IF(H52>=0.8,"En riesgo","Crítico"))),"Pendiente") -> Pendiente
... B82: 60 | C82: 2030 | D82: Diciembre | F82: =IFERROR(IF(OR(E82="",E81="",E81=0),"",(E82-E81)/E81),"") | G82: =IFERROR(VLOOKUP(C82,$B$14:$C$18,2,FALSE()),"") -> 0.1 | H82: =IFERROR(IF(OR(F82="",NOT(ISNUMBER(G82))),"",F82/G82),"") | I82: =IFERROR(IF(H82="","Pendiente",IF(H82>=0.95,"Cumple",IF(H82>=0.8,"En riesgo","Crítico"))),"Pendiente") -> Pendiente

Sheet IND-03
B2: 💰 IND-03 · CRECIMIENTO DE INGRESOS POR COMISIONES
B3: Perspectiva: Financiera · Objetivo específico: 📈 Aumento de ingresos
B5: Fórmula | D5: (Ingresos por comisiones final − Ingresos por comisiones inicial) ÷ Ingresos por comisiones inicial
B6: Descripción | D6: Mide el incremento de ingresos derivados del uso de servicios no financieros (convenios).
B7: Unidad | D7: %
B8: Tendencia objetivo | D8: Crecer
B9: Frecuencia | D9: Mensual
B10: Responsable | D10: =VLOOKUP("IND-03",Parámetros!$B$6:$F$30,5,FALSE()) -> Cartera
B12: 🎯 METAS ANUALES (editable)
B13: Año | C13: Meta | E13: Notas
B14: 2026 | C14: 0.035
B15: 2027 | C15: 0.035
B16: 2028 | C16: 0.035
B17: 2029 | C17: 0.035
B18: 2030 | C18: 0.035
B20: 📝 CAPTURA MENSUAL DE VARIABLES (Ene-2026 → Dic-2030)
B21: Ingrese los valores en las celdas azules. El resultado, % cumplimiento y semáforo se calculan automáticamente. Solo se habilitan los meses según la frecuencia del indicador.
B22: # | C22: Año | D22: Mes | E22: Ingresos por comisiones del mes ($) | F22: Resultado | G22: Meta año | H22: % Cumpl. | I22: Estado
B23: 1 | C23: 2026 | D23: Enero | G23: =IFERROR(VLOOKUP(C23,$B$14:$C$18,2,FALSE()),"") -> 0.035 | H23: =IFERROR(IF(OR(F23="",NOT(ISNUMBER(G23))),"",F23/G23),"") | I23: =IFERROR(IF(H23="","Pendiente",IF(H23>=0.95,"Cumple",IF(H23>=0.8,"En riesgo","Crítico"))),"Pendiente") -> Pendiente
B24: 2 | C24: 2026 | D24: Febrero | F24: =IFERROR(IF(OR(E24="",E23="",E23=0),"",(E24-E23)/E23),"") | G24: =IFERROR(VLOOKUP(C24,$B$14:$C$18,2,FALSE()),"") -> 0.035 | H24: =IFERROR(IF(OR(F24="",NOT(ISNUMBER(G24))),"",F24/G24),"") | I24: =IFERROR(IF(H24="","Pendiente",IF(H24>=0.95,"Cumple",IF(H24>=0.8,"En riesgo","Crítico"))),"Pendiente") -> Pendiente
B25: 3 | C25: 2026 | D25: Marzo | F25: =IFERROR(IF(OR(E25="",E24="",E24=0),"",(E25-E24)/E24),"") | G25: =IFERROR(VLOOKUP(C25,$B$14:$C$18,2,FALSE()),"") -> 0.035 | H25: =IFERROR(IF(OR(F25="",NOT(ISNUMBER(G25))),"",F25/G25),"") | I25: =IFERROR(IF(H25="","Pendiente",IF(H25>=0.95,"Cumple",IF(H25>=0.8,"En riesgo","Crítico"))),"Pendiente") -> Pendiente
B26: 4 | C26: 2026 | D26: Abril | F26: =IFERROR(IF(OR(E26="",E25="",E25=0),"",(E26-E25)/E25),"") | G26: =IFERROR(VLOOKUP(C26,$B$14:$C$18,2,FALSE()),"") -> 0.035 | H26: =IFERROR(IF(OR(F26="",NOT(ISNUMBER(G26))),"",F26/G26),"") | I26: =IFERROR(IF(H26="","Pendiente",IF(H26>=0.95,"Cumple",IF(H26>=0.8,"En riesgo","Crítico"))),"Pendiente") -> Pendiente
B27: 5 | C27: 2026 | D27: Mayo | F27: =IFERROR(IF(OR(E27="",E26="",E26=0),"",(E27-E26)/E26),"") | G27: =IFERROR(VLOOKUP(C27,$B$14:$C$18,2,FALSE()),"") -> 0.035 | H27: =IFERROR(IF(OR(F27="",NOT(ISNUMBER(G27))),"",F27/G27),"") | I27: =IFERROR(IF(H27="","Pendiente",IF(H27>=0.95,"Cumple",IF(H27>=0.8,"En riesgo","Crítico"))),"Pendiente") -> Pendiente
B28: 6 | C28: 2026 | D28: Junio | F28: =IFERROR(IF(OR(E28="",E27="",E27=0),"",(E28-E27)/E27),"") | G28: =IFERROR(VLOOKUP(C28,$B$14:$C$18,2,FALSE()),"") -> 0.035 | H28: =IFERROR(IF(OR(F28="",NOT(ISNUMBER(G28))),"",F28/G28),"") | I28: =IFERROR(IF(H28="","Pendiente",IF(H28>=0.95,"Cumple",IF(H28>=0.8,"En riesgo","Crítico"))),"Pendiente") -> Pendiente
B29: 7 | C29: 2026 | D29: Julio | F29: =IFERROR(IF(OR(E29="",E28="",E28=0),"",(E29-E28)/E28),"") | G29: =IFERROR(VLOOKUP(C29,$B$14:$C$18,2,FALSE()),"") -> 0.035 | H29: =IFERROR(IF(OR(F29="",NOT(ISNUMBER(G29))),"",F29/G29),"") | I29: =IFERROR(IF(H29="","Pendiente",IF(H29>=0.95,"Cumple",IF(H29>=0.8,"En riesgo","Crítico"))),"Pendiente") -> Pendiente
B30: 8 | C30: 2026 | D30: Agosto | F30: =IFERROR(IF(OR(E30="",E29="",E29=0),"",(E30-E29)/E29),"") | G30: =IFERROR(VLOOKUP(C30,$B$14:$C$18,2,FALSE()),"") -> 0.035 | H30: =IFERROR(IF(OR(F30="",NOT(ISNUMBER(G30))),"",F30/G30),"") | I30: =IFERROR(IF(H30="","Pendiente",IF(H30>=0.95,"Cumple",IF(H30>=0.8,"En riesgo","Crítico"))),"Pendiente") -> Pendiente
B31: 9 | C31: 2026 | D31: Septiembre | F31: =IFERROR(IF(OR(E31="",E30="",E30=0),"",(E31-E30)/E30),"") | G31: =IFERROR(VLOOKUP(C31,$B$14:$C$18,2,FALSE()),"") -> 0.035 | H31: =IFERROR(IF(OR(F31="",NOT(ISNUMBER(G31))),"",F31/G31),"") | I31: =IFERROR(IF(H31="","Pendiente",IF(H31>=0.95,"Cumple",IF(H31>=0.8,"En riesgo","Crítico"))),"Pendiente") -> Pendiente
B32: 10 | C32: 2026 | D32: Octubre | F32: =IFERROR(IF(OR(E32="",E31="",E31=0),"",(E32-E31)/E31),"") | G32: =IFERROR(VLOOKUP(C32,$B$14:$C$18,2,FALSE()),"") -> 0.035 | H32: =IFERROR(IF(OR(F32="",NOT(ISNUMBER(G32))),"",F32/G32),"") | I32: =IFERROR(IF(H32="","Pendiente",IF(H32>=0.95,"Cumple",IF(H32>=0.8,"En riesgo","Crítico"))),"Pendiente") -> Pendiente
B33: 11 | C33: 2026 | D33: Noviembre | F33: =IFERROR(IF(OR(E33="",E32="",E32=0),"",(E33-E32)/E32),"") | G33: =IFERROR(VLOOKUP(C33,$B$14:$C$18,2,FALSE()),"") -> 0.035 | H33: =IFERROR(IF(OR(F33="",NOT(ISNUMBER(G33))),"",F33/G33),"") | I33: =IFERROR(IF(H33="","Pendiente",IF(H33>=0.95,"Cumple",IF(H33>=0.8,"En riesgo","Crítico"))),"Pendiente") -> Pendiente
B34: 12 | C34: 2026 | D34: Diciembre | F34: =IFERROR(IF(OR(E34="",E33="",E33=0),"",(E34-E33)/E33),"") | G34: =IFERROR(VLOOKUP(C34,$B$14:$C$18,2,FALSE()),"") -> 0.035 | H34: =IFERROR(IF(OR(F34="",NOT(ISNUMBER(G34))),"",F34/G34),"") | I34: =IFERROR(IF(H34="","Pendiente",IF(H34>=0.95,"Cumple",IF(H34>=0.8,"En riesgo","Crítico"))),"Pendiente") -> Pendiente
B35: 13 | C35: 2027 | D35: Enero | F35: =IFERROR(IF(OR(E35="",E34="",E34=0),"",(E35-E34)/E34),"") | G35: =IFERROR(VLOOKUP(C35,$B$14:$C$18,2,FALSE()),"") -> 0.035 | H35: =IFERROR(IF(OR(F35="",NOT(ISNUMBER(G35))),"",F35/G35),"") | I35: =IFERROR(IF(H35="","Pendiente",IF(H35>=0.95,"Cumple",IF(H35>=0.8,"En riesgo","Crítico"))),"Pendiente") -> Pendiente
... B82: 60 | C82: 2030 | D82: Diciembre | F82: =IFERROR(IF(OR(E82="",E81="",E81=0),"",(E82-E81)/E81),"") | G82: =IFERROR(VLOOKUP(C82,$B$14:$C$18,2,FALSE()),"") -> 0.035 | H82: =IFERROR(IF(OR(F82="",NOT(ISNUMBER(G82))),"",F82/G82),"") | I82: =IFERROR(IF(H82="","Pendiente",IF(H82>=0.95,"Cumple",IF(H82>=0.8,"En riesgo","Crítico"))),"Pendiente") -> Pendiente

Sheet IND-04
B2: 💰 IND-04 · RENTABILIDAD FONDO DE LIQUIDEZ
B3: Perspectiva: Financiera · Objetivo específico: 📈 Aumento de ingresos
B5: Fórmula | D5: Tasa promedio ponderada de rentabilidad del fondo de liquidez − IBR
B6: Descripción | D6: Mide la capacidad de generar rentabilidad por encima del mercado.
B7: Unidad | D7: Puntos básicos
B8: Tendencia objetivo | D8: Crecer
B9: Frecuencia | D9: Mensual
B10: Responsable | D10: =VLOOKUP("IND-04",Parámetros!$B$6:$F$30,5,FALSE()) -> Tesorería
B12: 🎯 METAS ANUALES (editable)
B13: Año | C13: Meta | E13: Notas
B14: 2026 | C14: -200
B15: 2027 | C15: -200
B16: 2028 | C16: -200
B17: 2029 | C17: -200
B18: 2030 | C18: -200
B20: 📝 CAPTURA MENSUAL DE VARIABLES (Ene-2026 → Dic-2030)
B21: Ingrese los valores en las celdas azules. El resultado, % cumplimiento y semáforo se calculan automáticamente. Solo se habilitan los meses según la frecuencia del indicador.
B22: # | C22: Año | D22: Mes | E22: Tasa promedio ponderada Fondo de Liquidez (%) | F22: IBR (%) | G22: Resultado | H22: Meta año | I22: % Cumpl. | J22: Estado
B23: 1 | C23: 2026 | D23: Enero | G23: =IFERROR(IF(OR(E23="",F23=""),"",(E23-F23)*10000),"") | H23: =IFERROR(VLOOKUP(C23,$B$14:$C$18,2,FALSE()),"") -> -200 | I23: =IFERROR(IF(OR(G23="",NOT(ISNUMBER(H23))),"",G23/H23),"") | J23: =IFERROR(IF(I23="","Pendiente",IF(I23>=0.95,"Cumple",IF(I23>=0.8,"En riesgo","Crítico"))),"Pendiente") -> Pendiente
B24: 2 | C24: 2026 | D24: Febrero | G24: =IFERROR(IF(OR(E24="",F24=""),"",(E24-F24)*10000),"") | H24: =IFERROR(VLOOKUP(C24,$B$14:$C$18,2,FALSE()),"") -> -200 | I24: =IFERROR(IF(OR(G24="",NOT(ISNUMBER(H24))),"",G24/H24),"") | J24: =IFERROR(IF(I24="","Pendiente",IF(I24>=0.95,"Cumple",IF(I24>=0.8,"En riesgo","Crítico"))),"Pendiente") -> Pendiente
B25: 3 | C25: 2026 | D25: Marzo | G25: =IFERROR(IF(OR(E25="",F25=""),"",(E25-F25)*10000),"") | H25: =IFERROR(VLOOKUP(C25,$B$14:$C$18,2,FALSE()),"") -> -200 | I25: =IFERROR(IF(OR(G25="",NOT(ISNUMBER(H25))),"",G25/H25),"") | J25: =IFERROR(IF(I25="","Pendiente",IF(I25>=0.95,"Cumple",IF(I25>=0.8,"En riesgo","Crítico"))),"Pendiente") -> Pendiente
B26: 4 | C26: 2026 | D26: Abril | G26: =IFERROR(IF(OR(E26="",F26=""),"",(E26-F26)*10000),"") | H26: =IFERROR(VLOOKUP(C26,$B$14:$C$18,2,FALSE()),"") -> -200 | I26: =IFERROR(IF(OR(G26="",NOT(ISNUMBER(H26))),"",G26/H26),"") | J26: =IFERROR(IF(I26="","Pendiente",IF(I26>=0.95,"Cumple",IF(I26>=0.8,"En riesgo","Crítico"))),"Pendiente") -> Pendiente
B27: 5 | C27: 2026 | D27: Mayo | G27: =IFERROR(IF(OR(E27="",F27=""),"",(E27-F27)*10000),"") | H27: =IFERROR(VLOOKUP(C27,$B$14:$C$18,2,FALSE()),"") -> -200 | I27: =IFERROR(IF(OR(G27="",NOT(ISNUMBER(H27))),"",G27/H27),"") | J27: =IFERROR(IF(I27="","Pendiente",IF(I27>=0.95,"Cumple",IF(I27>=0.8,"En riesgo","Crítico"))),"Pendiente") -> Pendiente
B28: 6 | C28: 2026 | D28: Junio | G28: =IFERROR(IF(OR(E28="",F28=""),"",(E28-F28)*10000),"") | H28: =IFERROR(VLOOKUP(C28,$B$14:$C$18,2,FALSE()),"") -> -200 | I28: =IFERROR(IF(OR(G28="",NOT(ISNUMBER(H28))),"",G28/H28),"") | J28: =IFERROR(IF(I28="","Pendiente",IF(I28>=0.95,"Cumple",IF(I28>=0.8,"En riesgo","Crítico"))),"Pendiente") -> Pendiente
B29: 7 | C29: 2026 | D29: Julio | G29: =IFERROR(IF(OR(E29="",F29=""),"",(E29-F29)*10000),"") | H29: =IFERROR(VLOOKUP(C29,$B$14:$C$18,2,FALSE()),"") -> -200 | I29: =IFERROR(IF(OR(G29="",NOT(ISNUMBER(H29))),"",G29/H29),"") | J29: =IFERROR(IF(I29="","Pendiente",IF(I29>=0.95,"Cumple",IF(I29>=0.8,"En riesgo","Crítico"))),"Pendiente") -> Pendiente
B30: 8 | C30: 2026 | D30: Agosto | G30: =IFERROR(IF(OR(E30="",F30=""),"",(E30-F30)*10000),"") | H30: =IFERROR(VLOOKUP(C30,$B$14:$C$18,2,FALSE()),"") -> -200 | I30: =IFERROR(IF(OR(G30="",NOT(ISNUMBER(H30))),"",G30/H30),"") | J30: =IFERROR(IF(I30="","Pendiente",IF(I30>=0.95,"Cumple",IF(I30>=0.8,"En riesgo","Crítico"))),"Pendiente") -> Pendiente
B31: 9 | C31: 2026 | D31: Septiembre | G31: =IFERROR(IF(OR(E31="",F31=""),"",(E31-F31)*10000),"") | H31: =IFERROR(VLOOKUP(C31,$B$14:$C$18,2,FALSE()),"") -> -200 | I31: =IFERROR(IF(OR(G31="",NOT(ISNUMBER(H31))),"",G31/H31),"") | J31: =IFERROR(IF(I31="","Pendiente",IF(I31>=0.95,"Cumple",IF(I31>=0.8,"En riesgo","Crítico"))),"Pendiente") -> Pendiente
B32: 10 | C32: 2026 | D32: Octubre | G32: =IFERROR(IF(OR(E32="",F32=""),"",(E32-F32)*10000),"") | H32: =IFERROR(VLOOKUP(C32,$B$14:$C$18,2,FALSE()),"") -> -200 | I32: =IFERROR(IF(OR(G32="",NOT(ISNUMBER(H32))),"",G32/H32),"") | J32: =IFERROR(IF(I32="","Pendiente",IF(I32>=0.95,"Cumple",IF(I32>=0.8,"En riesgo","Crítico"))),"Pendiente") -> Pendiente
B33: 11 | C33: 2026 | D33: Noviembre | G33: =IFERROR(IF(OR(E33="",F33=""),"",(E33-F33)*10000),"") | H33: =IFERROR(VLOOKUP(C33,$B$14:$C$18,2,FALSE()),"") -> -200 | I33: =IFERROR(IF(OR(G33="",NOT(ISNUMBER(H33))),"",G33/H33),"") | J33: =IFERROR(IF(I33="","Pendiente",IF(I33>=0.95,"Cumple",IF(I33>=0.8,"En riesgo","Crítico"))),"Pendiente") -> Pendiente
B34: 12 | C34: 2026 | D34: Diciembre | G34: =IFERROR(IF(OR(E34="",F34=""),"",(E34-F34)*10000),"") | H34: =IFERROR(VLOOKUP(C34,$B$14:$C$18,2,FALSE()),"") -> -200 | I34: =IFERROR(IF(OR(G34="",NOT(ISNUMBER(H34))),"",G34/H34),"") | J34: =IFERROR(IF(I34="","Pendiente",IF(I34>=0.95,"Cumple",IF(I34>=0.8,"En riesgo","Crítico"))),"Pendiente") -> Pendiente
... B82: 60 | C82: 2030 | D82: Diciembre | G82: =IFERROR(IF(OR(E82="",F82=""),"",(E82-F82)*10000),"") | H82: =IFERROR(VLOOKUP(C82,$B$14:$C$18,2,FALSE()),"") -> -200 | I82: =IFERROR(IF(OR(G82="",NOT(ISNUMBER(H82))),"",G82/H82),"") | J82: =IFERROR(IF(I82="","Pendiente",IF(I82>=0.95,"Cumple",IF(I82>=0.8,"En riesgo","Crítico"))),"Pendiente") -> Pendiente

Sheet IND-05
B2: 💰 IND-05 · ÍNDICE DE MORA
B3: Perspectiva: Financiera · Objetivo específico: 🛡️ Reducción de mora
B5: Fórmula | D5: Saldo de cartera ≥ B ÷ Saldo total de cartera
B6: Descripción | D6: Mide el nivel de morosidad de la cartera por crédito, sin aplicación de arrastres o riesgo.
B7: Unidad | D7: %
B8: Tendencia objetivo | D8: Reducir
B9: Frecuencia | D9: Mensual
B10: Responsable | D10: =VLOOKUP("IND-05",Parámetros!$B$6:$F$30,5,FALSE()) -> Cartera
B12: 🎯 METAS ANUALES (editable)
B13: Año | C13: Meta | E13: Notas
B14: 2026 | C14: 0.05
B15: 2027 | C15: 0.05
B16: 2028 | C16: 0.05
B17: 2029 | C17: 0.05
B18: 2030 | C18: 0.05
B20: 📝 CAPTURA MENSUAL DE VARIABLES (Ene-2026 → Dic-2030)
B21: Ingrese los valores en las celdas azules. El resultado, % cumplimiento y semáforo se calculan automáticamente. Solo se habilitan los meses según la frecuencia del indicador.
B22: # | C22: Año | D22: Mes | E22: Saldo de cartera en mora ≥ B ($) | F22: Saldo total de cartera ($) | G22: Resultado | H22: Meta año | I22: % Cumpl. | J22: Estado
B23: 1 | C23: 2026 | D23: Enero | E23: 45 | F23: 1000 | G23: =IFERROR(IF(F23=0,"",E23/F23),"") -> 0.045 | H23: =IFERROR(VLOOKUP(C23,$B$14:$C$18,2,FALSE()),"") -> 0.05 | I23: =IFERROR(IF(OR(G23="",NOT(ISNUMBER(H23))),"",H23/G23),"") -> 1.1111111 | J23: =IFERROR(IF(I23="","Pendiente",IF(I23>=0.95,"Cumple",IF(I23>=0.8,"En riesgo","Crítico"))),"Pendiente") -> Cumple
B24: 2 | C24: 2026 | D24: Febrero | E24: 46 | F24: 1000 | G24: =IFERROR(IF(F24=0,"",E24/F24),"") -> 0.046 | H24: =IFERROR(VLOOKUP(C24,$B$14:$C$18,2,FALSE()),"") -> 0.05 | I24: =IFERROR(IF(OR(G24="",NOT(ISNUMBER(H24))),"",H24/G24),"") -> 1.0869565 | J24: =IFERROR(IF(I24="","Pendiente",IF(I24>=0.95,"Cumple",IF(I24>=0.8,"En riesgo","Crítico"))),"Pendiente") -> Cumple
B25: 3 | C25: 2026 | D25: Marzo | E25: 47 | F25: 1000 | G25: =IFERROR(IF(F25=0,"",E25/F25),"") -> 0.047 | H25: =IFERROR(VLOOKUP(C25,$B$14:$C$18,2,FALSE()),"") -> 0.05 | I25: =IFERROR(IF(OR(G25="",NOT(ISNUMBER(H25))),"",H25/G25),"") -> 1.0638298 | J25: =IFERROR(IF(I25="","Pendiente",IF(I25>=0.95,"Cumple",IF(I25>=0.8,"En riesgo","Crítico"))),"Pendiente") -> Cumple
B26: 4 | C26: 2026 | D26: Abril | E26: 48 | F26: 1000 | G26: =IFERROR(IF(F26=0,"",E26/F26),"") -> 0.048 | H26: =IFERROR(VLOOKUP(C26,$B$14:$C$18,2,FALSE()),"") -> 0.05 | I26: =IFERROR(IF(OR(G26="",NOT(ISNUMBER(H26))),"",H26/G26),"") -> 1.0416667 | J26: =IFERROR(IF(I26="","Pendiente",IF(I26>=0.95,"Cumple",IF(I26>=0.8,"En riesgo","Crítico"))),"Pendiente") -> Cumple
B27: 5 | C27: 2026 | D27: Mayo | E27: 49 | F27: 1000 | G27: =IFERROR(IF(F27=0,"",E27/F27),"") -> 0.049 | H27: =IFERROR(VLOOKUP(C27,$B$14:$C$18,2,FALSE()),"") -> 0.05 | I27: =IFERROR(IF(OR(G27="",NOT(ISNUMBER(H27))),"",H27/G27),"") -> 1.0204082 | J27: =IFERROR(IF(I27="","Pendiente",IF(I27>=0.95,"Cumple",IF(I27>=0.8,"En riesgo","Crítico"))),"Pendiente") -> Cumple
B28: 6 | C28: 2026 | D28: Junio | E28: 50 | F28: 1000 | G28: =IFERROR(IF(F28=0,"",E28/F28),"") -> 0.05 | H28: =IFERROR(VLOOKUP(C28,$B$14:$C$18,2,FALSE()),"") -> 0.05 | I28: =IFERROR(IF(OR(G28="",NOT(ISNUMBER(H28))),"",H28/G28),"") -> 1 | J28: =IFERROR(IF(I28="","Pendiente",IF(I28>=0.95,"Cumple",IF(I28>=0.8,"En riesgo","Crítico"))),"Pendiente") -> Cumple
B29: 7 | C29: 2026 | D29: Julio | E29: 51 | F29: 1000 | G29: =IFERROR(IF(F29=0,"",E29/F29),"") -> 0.051 | H29: =IFERROR(VLOOKUP(C29,$B$14:$C$18,2,FALSE()),"") -> 0.05 | I29: =IFERROR(IF(OR(G29="",NOT(ISNUMBER(H29))),"",H29/G29),"") -> 0.98039216 | J29: =IFERROR(IF(I29="","Pendiente",IF(I29>=0.95,"Cumple",IF(I29>=0.8,"En riesgo","Crítico"))),"Pendiente") -> Cumple
B30: 8 | C30: 2026 | D30: Agosto | E30: 52 | F30: 1000 | G30: =IFERROR(IF(F30=0,"",E30/F30),"") -> 0.052 | H30: =IFERROR(VLOOKUP(C30,$B$14:$C$18,2,FALSE()),"") -> 0.05 | I30: =IFERROR(IF(OR(G30="",NOT(ISNUMBER(H30))),"",H30/G30),"") -> 0.96153846 | J30: =IFERROR(IF(I30="","Pendiente",IF(I30>=0.95,"Cumple",IF(I30>=0.8,"En riesgo","Crítico"))),"Pendiente") -> Cumple
B31: 9 | C31: 2026 | D31: Septiembre | E31: 53 | F31: 1000 | G31: =IFERROR(IF(F31=0,"",E31/F31),"") -> 0.053 | H31: =IFERROR(VLOOKUP(C31,$B$14:$C$18,2,FALSE()),"") -> 0.05 | I31: =IFERROR(IF(OR(G31="",NOT(ISNUMBER(H31))),"",H31/G31),"") -> 0.94339623 | J31: =IFERROR(IF(I31="","Pendiente",IF(I31>=0.95,"Cumple",IF(I31>=0.8,"En riesgo","Crítico"))),"Pendiente") -> En riesgo
B32: 10 | C32: 2026 | D32: Octubre | E32: 54 | F32: 1000 | G32: =IFERROR(IF(F32=0,"",E32/F32),"") -> 0.054 | H32: =IFERROR(VLOOKUP(C32,$B$14:$C$18,2,FALSE()),"") -> 0.05 | I32: =IFERROR(IF(OR(G32="",NOT(ISNUMBER(H32))),"",H32/G32),"") -> 0.92592593 | J32: =IFERROR(IF(I32="","Pendiente",IF(I32>=0.95,"Cumple",IF(I32>=0.8,"En riesgo","Crítico"))),"Pendiente") -> En riesgo
B33: 11 | C33: 2026 | D33: Noviembre | E33: 55 | F33: 1000 | G33: =IFERROR(IF(F33=0,"",E33/F33),"") -> 0.055 | H33: =IFERROR(VLOOKUP(C33,$B$14:$C$18,2,FALSE()),"") -> 0.05 | I33: =IFERROR(IF(OR(G33="",NOT(ISNUMBER(H33))),"",H33/G33),"") -> 0.90909091 | J33: =IFERROR(IF(I33="","Pendiente",IF(I33>=0.95,"Cumple",IF(I33>=0.8,"En riesgo","Crítico"))),"Pendiente") -> En riesgo
B34: 12 | C34: 2026 | D34: Diciembre | E34: 56 | F34: 1000 | G34: =IFERROR(IF(F34=0,"",E34/F34),"") -> 0.056 | H34: =IFERROR(VLOOKUP(C34,$B$14:$C$18,2,FALSE()),"") -> 0.05 | I34: =IFERROR(IF(OR(G34="",NOT(ISNUMBER(H34))),"",H34/G34),"") -> 0.89285714 | J34: =IFERROR(IF(I34="","Pendiente",IF(I34>=0.95,"Cumple",IF(I34>=0.8,"En riesgo","Crítico"))),"Pendiente") -> En riesgo
... B37: 15 | C37: 2027 | D37: Marzo | E37: 100 | F37: 1000 | G37: =IFERROR(IF(F37=0,"",E37/F37),"") -> 0.1 | H37: =IFERROR(VLOOKUP(C37,$B$14:$C$18,2,FALSE()),"") -> 0.05 | I37: =IFERROR(IF(OR(G37="",NOT(ISNUMBER(H37))),"",H37/G37),"") -> 0.5 | J37: =IFERROR(IF(I37="","Pendiente",IF(I37>=0.95,"Cumple",IF(I37>=0.8,"En riesgo","Crítico"))),"Pendiente") -> Crítico
B38: 16 | C38: 2027 | D38: Abril | G38: =IFERROR(IF(F38=0,"",E38/F38),"") | H38: =IFERROR(VLOOKUP(C38,$B$14:$C$18,2,FALSE()),"") -> 0.05 | I38: =IFERROR(IF(OR(G38="",NOT(ISNUMBER(H38))),"",H38/G38),"") | J38: =IFERROR(IF(I38="","Pendiente",IF(I38>=0.95,"Cumple",IF(I38>=0.8,"En riesgo","Crítico"))),"Pendiente") -> Pendiente
B39: 17 | C39: 2027 | D39: Mayo | G39: =IFERROR(IF(F39=0,"",E39/F39),"") | H39: =IFERROR(VLOOKUP(C39,$B$14:$C$18,2,FALSE()),"") -> 0.05 | I39: =IFERROR(IF(OR(G39="",NOT(ISNUMBER(H39))),"",H39/G39),"") | J39: =IFERROR(IF(I39="","Pendiente",IF(I39>=0.95,"Cumple",IF(I39>=0.8,"En riesgo","Crítico"))),"Pendiente") -> Pendiente
B40: 18 | C40: 2027 | D40: Junio | G40: =IFERROR(IF(F40=0,"",E40/F40),"") | H40: =IFERROR(VLOOKUP(C40,$B$14:$C$18,2,FALSE()),"") -> 0.05 | I40: =IFERROR(IF(OR(G40="",NOT(ISNUMBER(H40))),"",H40/G40),"") | J40: =IFERROR(IF(I40="","Pendiente",IF(I40>=0.95,"Cumple",IF(I40>=0.8,"En riesgo","Crítico"))),"Pendiente") -> Pendiente
B41: 19 | C41: 2027 | D41: Julio | G41: =IFERROR(IF(F41=0,"",E41/F41),"") | H41: =IFERROR(VLOOKUP(C41,$B$14:$C$18,2,FALSE()),"") -> 0.05 | I41: =IFERROR(IF(OR(G41="",NOT(ISNUMBER(H41))),"",H41/G41),"") | J41: =IFERROR(IF(I41="","Pendiente",IF(I41>=0.95,"Cumple",IF(I41>=0.8,"En riesgo","Crítico"))),"Pendiente") -> Pendiente
B42: 20 | C42: 2027 | D42: Agosto | G42: =IFERROR(IF(F42=0,"",E42/F42),"") | H42: =IFERROR(VLOOKUP(C42,$B$14:$C$18,2,FALSE()),"") -> 0.05 | I42: =IFERROR(IF(OR(G42="",NOT(ISNUMBER(H42))),"",H42/G42),"") | J42: =IFERROR(IF(I42="","Pendiente",IF(I42>=0.95,"Cumple",IF(I42>=0.8,"En riesgo","Crítico"))),"Pendiente") -> Pendiente
B43: 21 | C43: 2027 | D43: Septiembre | G43: =IFERROR(IF(F43=0,"",E43/F43),"") | H43: =IFERROR(VLOOKUP(C43,$B$14:$C$18,2,FALSE()),"") -> 0.05 | I43: =IFERROR(IF(OR(G43="",NOT(ISNUMBER(H43))),"",H43/G43),"") | J43: =IFERROR(IF(I43="","Pendiente",IF(I43>=0.95,"Cumple",IF(I43>=0.8,"En riesgo","Crítico"))),"Pendiente") -> Pendiente
B44: 22 | C44: 2027 | D44: Octubre | G44: =IFERROR(IF(F44=0,"",E44/F44),"") | H44: =IFERROR(VLOOKUP(C44,$B$14:$C$18,2,FALSE()),"") -> 0.05 | I44: =IFERROR(IF(OR(G44="",NOT(ISNUMBER(H44))),"",H44/G44),"") | J44: =IFERROR(IF(I44="","Pendiente",IF(I44>=0.95,"Cumple",IF(I44>=0.8,"En riesgo","Crítico"))),"Pendiente") -> Pendiente
B45: 23 | C45: 2027 | D45: Noviembre | G45: =IFERROR(IF(F45=0,"",E45/F45),"") | H45: =IFERROR(VLOOKUP(C45,$B$14:$C$18,2,FALSE()),"") -> 0.05 | I45: =IFERROR(IF(OR(G45="",NOT(ISNUMBER(H45))),"",H45/G45),"") | J45: =IFERROR(IF(I45="","Pendiente",IF(I45>=0.95,"Cumple",IF(I45>=0.8,"En riesgo","Crítico"))),"Pendiente") -> Pendiente
B46: 24 | C46: 2027 | D46: Diciembre | G46: =IFERROR(IF(F46=0,"",E46/F46),"") | H46: =IFERROR(VLOOKUP(C46,$B$14:$C$18,2,FALSE()),"") -> 0.05 | I46: =IFERROR(IF(OR(G46="",NOT(ISNUMBER(H46))),"",H46/G46),"") | J46: =IFERROR(IF(I46="","Pendiente",IF(I46>=0.95,"Cumple",IF(I46>=0.8,"En riesgo","Crítico"))),"Pendiente") -> Pendiente
B47: 25 | C47: 2028 | D47: Enero | G47: =IFERROR(IF(F47=0,"",E47/F47),"") | H47: =IFERROR(VLOOKUP(C47,$B$14:$C$18,2,FALSE()),"") -> 0.05 | I47: =IFERROR(IF(OR(G47="",NOT(ISNUMBER(H47))),"",H47/G47),"") | J47: =IFERROR(IF(I47="","Pendiente",IF(I47>=0.95,"Cumple",IF(I47>=0.8,"En riesgo","Crítico"))),"Pendiente") -> Pendiente
B48: 26 | C48: 2028 | D48: Febrero | G48: =IFERROR(IF(F48=0,"",E48/F48),"") | H48: =IFERROR(VLOOKUP(C48,$B$14:$C$18,2,FALSE()),"") -> 0.05 | I48: =IFERROR(IF(OR(G48="",NOT(ISNUMBER(H48))),"",H48/G48),"") | J48: =IFERROR(IF(I48="","Pendiente",IF(I48>=0.95,"Cumple",IF(I48>=0.8,"En riesgo","Crítico"))),"Pendiente") -> Pendiente
B49: 27 | C49: 2028 | D49: Marzo | G49: =IFERROR(IF(F49=0,"",E49/F49),"") | H49: =IFERROR(VLOOKUP(C49,$B$14:$C$18,2,FALSE()),"") -> 0.05 | I49: =IFERROR(IF(OR(G49="",NOT(ISNUMBER(H49))),"",H49/G49),"") | J49: =IFERROR(IF(I49="","Pendiente",IF(I49>=0.95,"Cumple",IF(I49>=0.8,"En riesgo","Crítico"))),"Pendiente") -> Pendiente
... B82: 60 | C82: 2030 | D82: Diciembre | G82: =IFERROR(IF(F82=0,"",E82/F82),"") | H82: =IFERROR(VLOOKUP(C82,$B$14:$C$18,2,FALSE()),"") -> 0.05 | I82: =IFERROR(IF(OR(G82="",NOT(ISNUMBER(H82))),"",H82/G82),"") | J82: =IFERROR(IF(I82="","Pendiente",IF(I82>=0.95,"Cumple",IF(I82>=0.8,"En riesgo","Crítico"))),"Pendiente") -> Pendiente

Sheet IND-06
B2: 💰 IND-06 · TASA DE RECUPERACIÓN
B3: Perspectiva: Financiera · Objetivo específico: 🛡️ Reducción de mora
B5: Fórmula | D5: Saldo de cartera recuperada ÷ Saldo de cartera deteriorada
B6: Descripción | D6: Mide la proporción de cartera recuperada frente a la deteriorada por rodamiento (matriz de transición).
B7: Unidad | D7: %
B8: Tendencia objetivo | D8: Crecer
B9: Frecuencia | D9: Mensual
B10: Responsable | D10: =VLOOKUP("IND-06",Parámetros!$B$6:$F$30,5,FALSE()) -> Por definir
B12: 🎯 METAS ANUALES (editable)
B13: Año | C13: Meta | E13: Notas
B14: 2026 | C14: 0.3
B15: 2027 | C15: 0.3
B16: 2028 | C16: 0.3
B17: 2029 | C17: 0.3
B18: 2030 | C18: 0.3
B20: 📝 CAPTURA MENSUAL DE VARIABLES (Ene-2026 → Dic-2030)
B21: Ingrese los valores en las celdas azules. El resultado, % cumplimiento y semáforo se calculan automáticamente. Solo se habilitan los meses según la frecuencia del indicador.
B22: # | C22: Año | D22: Mes | E22: Saldo cartera recuperada ($) | F22: Saldo cartera deteriorada ($) | G22: Resultado | H22: Meta año | I22: % Cumpl. | J22: Estado
B23: 1 | C23: 2026 | D23: Enero | G23: =IFERROR(IF(F23=0,"",E23/F23),"") | H23: =IFERROR(VLOOKUP(C23,$B$14:$C$18,2,FALSE()),"") -> 0.3 | I23: =IFERROR(IF(OR(G23="",NOT(ISNUMBER(H23))),"",G23/H23),"") | J23: =IFERROR(IF(I23="","Pendiente",IF(I23>=0.95,"Cumple",IF(I23>=0.8,"En riesgo","Crítico"))),"Pendiente") -> Pendiente
B24: 2 | C24: 2026 | D24: Febrero | G24: =IFERROR(IF(F24=0,"",E24/F24),"") | H24: =IFERROR(VLOOKUP(C24,$B$14:$C$18,2,FALSE()),"") -> 0.3 | I24: =IFERROR(IF(OR(G24="",NOT(ISNUMBER(H24))),"",G24/H24),"") | J24: =IFERROR(IF(I24="","Pendiente",IF(I24>=0.95,"Cumple",IF(I24>=0.8,"En riesgo","Crítico"))),"Pendiente") -> Pendiente
B25: 3 | C25: 2026 | D25: Marzo | G25: =IFERROR(IF(F25=0,"",E25/F25),"") | H25: =IFERROR(VLOOKUP(C25,$B$14:$C$18,2,FALSE()),"") -> 0.3 | I25: =IFERROR(IF(OR(G25="",NOT(ISNUMBER(H25))),"",G25/H25),"") | J25: =IFERROR(IF(I25="","Pendiente",IF(I25>=0.95,"Cumple",IF(I25>=0.8,"En riesgo","Crítico"))),"Pendiente") -> Pendiente
B26: 4 | C26: 2026 | D26: Abril | G26: =IFERROR(IF(F26=0,"",E26/F26),"") | H26: =IFERROR(VLOOKUP(C26,$B$14:$C$18,2,FALSE()),"") -> 0.3 | I26: =IFERROR(IF(OR(G26="",NOT(ISNUMBER(H26))),"",G26/H26),"") | J26: =IFERROR(IF(I26="","Pendiente",IF(I26>=0.95,"Cumple",IF(I26>=0.8,"En riesgo","Crítico"))),"Pendiente") -> Pendiente
B27: 5 | C27: 2026 | D27: Mayo | G27: =IFERROR(IF(F27=0,"",E27/F27),"") | H27: =IFERROR(VLOOKUP(C27,$B$14:$C$18,2,FALSE()),"") -> 0.3 | I27: =IFERROR(IF(OR(G27="",NOT(ISNUMBER(H27))),"",G27/H27),"") | J27: =IFERROR(IF(I27="","Pendiente",IF(I27>=0.95,"Cumple",IF(I27>=0.8,"En riesgo","Crítico"))),"Pendiente") -> Pendiente
B28: 6 | C28: 2026 | D28: Junio | G28: =IFERROR(IF(F28=0,"",E28/F28),"") | H28: =IFERROR(VLOOKUP(C28,$B$14:$C$18,2,FALSE()),"") -> 0.3 | I28: =IFERROR(IF(OR(G28="",NOT(ISNUMBER(H28))),"",G28/H28),"") | J28: =IFERROR(IF(I28="","Pendiente",IF(I28>=0.95,"Cumple",IF(I28>=0.8,"En riesgo","Crítico"))),"Pendiente") -> Pendiente
B29: 7 | C29: 2026 | D29: Julio | G29: =IFERROR(IF(F29=0,"",E29/F29),"") | H29: =IFERROR(VLOOKUP(C29,$B$14:$C$18,2,FALSE()),"") -> 0.3 | I29: =IFERROR(IF(OR(G29="",NOT(ISNUMBER(H29))),"",G29/H29),"") | J29: =IFERROR(IF(I29="","Pendiente",IF(I29>=0.95,"Cumple",IF(I29>=0.8,"En riesgo","Crítico"))),"Pendiente") -> Pendiente
B30: 8 | C30: 2026 | D30: Agosto | G30: =IFERROR(IF(F30=0,"",E30/F30),"") | H30: =IFERROR(VLOOKUP(C30,$B$14:$C$18,2,FALSE()),"") -> 0.3 | I30: =IFERROR(IF(OR(G30="",NOT(ISNUMBER(H30))),"",G30/H30),"") | J30: =IFERROR(IF(I30="","Pendiente",IF(I30>=0.95,"Cumple",IF(I30>=0.8,"En riesgo","Crítico"))),"Pendiente") -> Pendiente
B31: 9 | C31: 2026 | D31: Septiembre | G31: =IFERROR(IF(F31=0,"",E31/F31),"") | H31: =IFERROR(VLOOKUP(C31,$B$14:$C$18,2,FALSE()),"") -> 0.3 | I31: =IFERROR(IF(OR(G31="",NOT(ISNUMBER(H31))),"",G31/H31),"") | J31: =IFERROR(IF(I31="","Pendiente",IF(I31>=0.95,"Cumple",IF(I31>=0.8,"En riesgo","Crítico"))),"Pendiente") -> Pendiente
B32: 10 | C32: 2026 | D32: Octubre | G32: =IFERROR(IF(F32=0,"",E32/F32),"") | H32: =IFERROR(VLOOKUP(C32,$B$14:$C$18,2,FALSE()),"") -> 0.3 | I32: =IFERROR(IF(OR(G32="",NOT(ISNUMBER(H32))),"",G32/H32),"") | J32: =IFERROR(IF(I32="","Pendiente",IF(I32>=0.95,"Cumple",IF(I32>=0.8,"En riesgo","Crítico"))),"Pendiente") -> Pendiente
B33: 11 | C33: 2026 | D33: Noviembre | G33: =IFERROR(IF(F33=0,"",E33/F33),"") | H33: =IFERROR(VLOOKUP(C33,$B$14:$C$18,2,FALSE()),"") -> 0.3 | I33: =IFERROR(IF(OR(G33="",NOT(ISNUMBER(H33))),"",G33/H33),"") | J33: =IFERROR(IF(I33="","Pendiente",IF(I33>=0.95,"Cumple",IF(I33>=0.8,"En riesgo","Crítico"))),"Pendiente") -> Pendiente
B34: 12 | C34: 2026 | D34: Diciembre | G34: =IFERROR(IF(F34=0,"",E34/F34),"") | H34: =IFERROR(VLOOKUP(C34,$B$14:$C$18,2,FALSE()),"") -> 0.3 | I34: =IFERROR(IF(OR(G34="",NOT(ISNUMBER(H34))),"",G34/H34),"") | J34: =IFERROR(IF(I34="","Pendiente",IF(I34>=0.95,"Cumple",IF(I34>=0.8,"En riesgo","Crítico"))),"Pendiente") -> Pendiente
... B82: 60 | C82: 2030 | D82: Diciembre | G82: =IFERROR(IF(F82=0,"",E82/F82),"") | H82: =IFERROR(VLOOKUP(C82,$B$14:$C$18,2,FALSE()),"") -> 0.3 | I82: =IFERROR(IF(OR(G82="",NOT(ISNUMBER(H82))),"",G82/H82),"") | J82: =IFERROR(IF(I82="","Pendiente",IF(I82>=0.95,"Cumple",IF(I82>=0.8,"En riesgo","Crítico"))),"Pendiente") -> Pendiente

Sheet IND-07
B2: 💰 IND-07 · TASA DE NORMALIZACIÓN DE CARTERA
B3: Perspectiva: Financiera · Objetivo específico: 🛡️ Reducción de mora
B5: Fórmula | D5: Saldo de normalizaciones al día ÷ Saldo total de normalizaciones
B6: Descripción | D6: Mide la efectividad de acuerdos de pago y reestructuraciones.
B7: Unidad | D7: %
B8: Tendencia objetivo | D8: Crecer
B9: Frecuencia | D9: Mensual
B10: Responsable | D10: =VLOOKUP("IND-07",Parámetros!$B$6:$F$30,5,FALSE()) -> Por definir
B12: 🎯 METAS ANUALES (editable)
B13: Año | C13: Meta | E13: Notas
B14: 2026 | C14: 0.8
B15: 2027 | C15: 0.8
B16: 2028 | C16: 0.8
B17: 2029 | C17: 0.8
B18: 2030 | C18: 0.8
B20: 📝 CAPTURA MENSUAL DE VARIABLES (Ene-2026 → Dic-2030)
B21: Ingrese los valores en las celdas azules. El resultado, % cumplimiento y semáforo se calculan automáticamente. Solo se habilitan los meses según la frecuencia del indicador.
B22: # | C22: Año | D22: Mes | E22: Saldo normalizaciones al día ($) | F22: Saldo total normalizaciones ($) | G22: Resultado | H22: Meta año | I22: % Cumpl. | J22: Estado
B23: 1 | C23: 2026 | D23: Enero | G23: =IFERROR(IF(F23=0,"",E23/F23),"") | H23: =IFERROR(VLOOKUP(C23,$B$14:$C$18,2,FALSE()),"") -> 0.8 | I23: =IFERROR(IF(OR(G23="",NOT(ISNUMBER(H23))),"",G23/H23),"") | J23: =IFERROR(IF(I23="","Pendiente",IF(I23>=0.95,"Cumple",IF(I23>=0.8,"En riesgo","Crítico"))),"Pendiente") -> Pendiente
B24: 2 | C24: 2026 | D24: Febrero | G24: =IFERROR(IF(F24=0,"",E24/F24),"") | H24: =IFERROR(VLOOKUP(C24,$B$14:$C$18,2,FALSE()),"") -> 0.8 | I24: =IFERROR(IF(OR(G24="",NOT(ISNUMBER(H24))),"",G24/H24),"") | J24: =IFERROR(IF(I24="","Pendiente",IF(I24>=0.95,"Cumple",IF(I24>=0.8,"En riesgo","Crítico"))),"Pendiente") -> Pendiente
B25: 3 | C25: 2026 | D25: Marzo | G25: =IFERROR(IF(F25=0,"",E25/F25),"") | H25: =IFERROR(VLOOKUP(C25,$B$14:$C$18,2,FALSE()),"") -> 0.8 | I25: =IFERROR(IF(OR(G25="",NOT(ISNUMBER(H25))),"",G25/H25),"") | J25: =IFERROR(IF(I25="","Pendiente",IF(I25>=0.95,"Cumple",IF(I25>=0.8,"En riesgo","Crítico"))),"Pendiente") -> Pendiente
B26: 4 | C26: 2026 | D26: Abril | G26: =IFERROR(IF(F26=0,"",E26/F26),"") | H26: =IFERROR(VLOOKUP(C26,$B$14:$C$18,2,FALSE()),"") -> 0.8 | I26: =IFERROR(IF(OR(G26="",NOT(ISNUMBER(H26))),"",G26/H26),"") | J26: =IFERROR(IF(I26="","Pendiente",IF(I26>=0.95,"Cumple",IF(I26>=0.8,"En riesgo","Crítico"))),"Pendiente") -> Pendiente
B27: 5 | C27: 2026 | D27: Mayo | G27: =IFERROR(IF(F27=0,"",E27/F27),"") | H27: =IFERROR(VLOOKUP(C27,$B$14:$C$18,2,FALSE()),"") -> 0.8 | I27: =IFERROR(IF(OR(G27="",NOT(ISNUMBER(H27))),"",G27/H27),"") | J27: =IFERROR(IF(I27="","Pendiente",IF(I27>=0.95,"Cumple",IF(I27>=0.8,"En riesgo","Crítico"))),"Pendiente") -> Pendiente
B28: 6 | C28: 2026 | D28: Junio | G28: =IFERROR(IF(F28=0,"",E28/F28),"") | H28: =IFERROR(VLOOKUP(C28,$B$14:$C$18,2,FALSE()),"") -> 0.8 | I28: =IFERROR(IF(OR(G28="",NOT(ISNUMBER(H28))),"",G28/H28),"") | J28: =IFERROR(IF(I28="","Pendiente",IF(I28>=0.95,"Cumple",IF(I28>=0.8,"En riesgo","Crítico"))),"Pendiente") -> Pendiente
B29: 7 | C29: 2026 | D29: Julio | G29: =IFERROR(IF(F29=0,"",E29/F29),"") | H29: =IFERROR(VLOOKUP(C29,$B$14:$C$18,2,FALSE()),"") -> 0.8 | I29: =IFERROR(IF(OR(G29="",NOT(ISNUMBER(H29))),"",G29/H29),"") | J29: =IFERROR(IF(I29="","Pendiente",IF(I29>=0.95,"Cumple",IF(I29>=0.8,"En riesgo","Crítico"))),"Pendiente") -> Pendiente
B30: 8 | C30: 2026 | D30: Agosto | G30: =IFERROR(IF(F30=0,"",E30/F30),"") | H30: =IFERROR(VLOOKUP(C30,$B$14:$C$18,2,FALSE()),"") -> 0.8 | I30: =IFERROR(IF(OR(G30="",NOT(ISNUMBER(H30))),"",G30/H30),"") | J30: =IFERROR(IF(I30="","Pendiente",IF(I30>=0.95,"Cumple",IF(I30>=0.8,"En riesgo","Crítico"))),"Pendiente") -> Pendiente
B31: 9 | C31: 2026 | D31: Septiembre | G31: =IFERROR(IF(F31=0,"",E31/F31),"") | H31: =IFERROR(VLOOKUP(C31,$B$14:$C$18,2,FALSE()),"") -> 0.8 | I31: =IFERROR(IF(OR(G31="",NOT(ISNUMBER(H31))),"",G31/H31),"") | J31: =IFERROR(IF(I31="","Pendiente",IF(I31>=0.95,"Cumple",IF(I31>=0.8,"En riesgo","Crítico"))),"Pendiente") -> Pendiente
B32: 10 | C32: 2026 | D32: Octubre | G32: =IFERROR(IF(F32=0,"",E32/F32),"") | H32: =IFERROR(VLOOKUP(C32,$B$14:$C$18,2,FALSE()),"") -> 0.8 | I32: =IFERROR(IF(OR(G32="",NOT(ISNUMBER(H32))),"",G32/H32),"") | J32: =IFERROR(IF(I32="","Pendiente",IF(I32>=0.95,"Cumple",IF(I32>=0.8,"En riesgo","Crítico"))),"Pendiente") -> Pendiente
B33: 11 | C33: 2026 | D33: Noviembre | G33: =IFERROR(IF(F33=0,"",E33/F33),"") | H33: =IFERROR(VLOOKUP(C33,$B$14:$C$18,2,FALSE()),"") -> 0.8 | I33: =IFERROR(IF(OR(G33="",NOT(ISNUMBER(H33))),"",G33/H33),"") | J33: =IFERROR(IF(I33="","Pendiente",IF(I33>=0.95,"Cumple",IF(I33>=0.8,"En riesgo","Crítico"))),"Pendiente") -> Pendiente
B34: 12 | C34: 2026 | D34: Diciembre | G34: =IFERROR(IF(F34=0,"",E34/F34),"") | H34: =IFERROR(VLOOKUP(C34,$B$14:$C$18,2,FALSE()),"") -> 0.8 | I34: =IFERROR(IF(OR(G34="",NOT(ISNUMBER(H34))),"",G34/H34),"") | J34: =IFERROR(IF(I34="","Pendiente",IF(I34>=0.95,"Cumple",IF(I34>=0.8,"En riesgo","Crítico"))),"Pendiente") -> Pendiente
... B82: 60 | C82: 2030 | D82: Diciembre | G82: =IFERROR(IF(F82=0,"",E82/F82),"") | H82: =IFERROR(VLOOKUP(C82,$B$14:$C$18,2,FALSE()),"") -> 0.8 | I82: =IFERROR(IF(OR(G82="",NOT(ISNUMBER(H82))),"",G82/H82),"") | J82: =IFERROR(IF(I82="","Pendiente",IF(I82>=0.95,"Cumple",IF(I82>=0.8,"En riesgo","Crítico"))),"Pendiente") -> Pendiente

Sheet IND-08
B2: 💰 IND-08 · TASA DE CRECIMIENTO DE AHORROS
B3: Perspectiva: Financiera · Objetivo específico: 🏦 Crecimiento y remuneración de depósitos
B5: Fórmula | D5: (Saldo final depósitos − Saldo inicial depósitos) ÷ Saldo inicial depósitos
B6: Descripción | D6: Mide el crecimiento de los depósitos entre periodos.
B7: Unidad | D7: %
B8: Tendencia objetivo | D8: Crecer
B9: Frecuencia | D9: Mensual
B10: Responsable | D10: =VLOOKUP("IND-08",Parámetros!$B$6:$F$30,5,FALSE()) -> Por definir
B12: 🎯 METAS ANUALES (editable)
B13: Año | C13: Meta | E13: Notas
B14: 2026 | C14: ≥ IPC
B15: 2027 | C15: ≥ IPC
B16: 2028 | C16: ≥ IPC
B17: 2029 | C17: ≥ IPC
B18: 2030 | C18: ≥ IPC
B20: 📝 CAPTURA MENSUAL DE VARIABLES (Ene-2026 → Dic-2030)
B21: Ingrese los valores en las celdas azules. El resultado, % cumplimiento y semáforo se calculan automáticamente. Solo se habilitan los meses según la frecuencia del indicador.
B22: # | C22: Año | D22: Mes | E22: Saldo total de depósitos del mes ($) | F22: Resultado | G22: Meta año | H22: % Cumpl. | I22: Estado
B23: 1 | C23: 2026 | D23: Enero | G23: =IFERROR(VLOOKUP(C23,$B$14:$C$18,2,FALSE()),"") -> ≥ IPC | H23: =IF(F23="","","N/A") | I23: =IF(F23="","Pendiente","Manual") -> Pendiente
B24: 2 | C24: 2026 | D24: Febrero | F24: =IFERROR(IF(OR(E24="",E23="",E23=0),"",(E24-E23)/E23),"") | G24: =IFERROR(VLOOKUP(C24,$B$14:$C$18,2,FALSE()),"") -> ≥ IPC | H24: =IF(F24="","","N/A") | I24: =IF(F24="","Pendiente","Manual") -> Pendiente
B25: 3 | C25: 2026 | D25: Marzo | F25: =IFERROR(IF(OR(E25="",E24="",E24=0),"",(E25-E24)/E24),"") | G25: =IFERROR(VLOOKUP(C25,$B$14:$C$18,2,FALSE()),"") -> ≥ IPC | H25: =IF(F25="","","N/A") | I25: =IF(F25="","Pendiente","Manual") -> Pendiente
B26: 4 | C26: 2026 | D26: Abril | F26: =IFERROR(IF(OR(E26="",E25="",E25=0),"",(E26-E25)/E25),"") | G26: =IFERROR(VLOOKUP(C26,$B$14:$C$18,2,FALSE()),"") -> ≥ IPC | H26: =IF(F26="","","N/A") | I26: =IF(F26="","Pendiente","Manual") -> Pendiente
B27: 5 | C27: 2026 | D27: Mayo | F27: =IFERROR(IF(OR(E27="",E26="",E26=0),"",(E27-E26)/E26),"") | G27: =IFERROR(VLOOKUP(C27,$B$14:$C$18,2,FALSE()),"") -> ≥ IPC | H27: =IF(F27="","","N/A") | I27: =IF(F27="","Pendiente","Manual") -> Pendiente
B28: 6 | C28: 2026 | D28: Junio | F28: =IFERROR(IF(OR(E28="",E27="",E27=0),"",(E28-E27)/E27),"") | G28: =IFERROR(VLOOKUP(C28,$B$14:$C$18,2,FALSE()),"") -> ≥ IPC | H28: =IF(F28="","","N/A") | I28: =IF(F28="","Pendiente","Manual") -> Pendiente
B29: 7 | C29: 2026 | D29: Julio | F29: =IFERROR(IF(OR(E29="",E28="",E28=0),"",(E29-E28)/E28),"") | G29: =IFERROR(VLOOKUP(C29,$B$14:$C$18,2,FALSE()),"") -> ≥ IPC | H29: =IF(F29="","","N/A") | I29: =IF(F29="","Pendiente","Manual") -> Pendiente
B30: 8 | C30: 2026 | D30: Agosto | F30: =IFERROR(IF(OR(E30="",E29="",E29=0),"",(E30-E29)/E29),"") | G30: =IFERROR(VLOOKUP(C30,$B$14:$C$18,2,FALSE()),"") -> ≥ IPC | H30: =IF(F30="","","N/A") | I30: =IF(F30="","Pendiente","Manual") -> Pendiente
B31: 9 | C31: 2026 | D31: Septiembre | F31: =IFERROR(IF(OR(E31="",E30="",E30=0),"",(E31-E30)/E30),"") | G31: =IFERROR(VLOOKUP(C31,$B$14:$C$18,2,FALSE()),"") -> ≥ IPC | H31: =IF(F31="","","N/A") | I31: =IF(F31="","Pendiente","Manual") -> Pendiente
B32: 10 | C32: 2026 | D32: Octubre | F32: =IFERROR(IF(OR(E32="",E31="",E31=0),"",(E32-E31)/E31),"") | G32: =IFERROR(VLOOKUP(C32,$B$14:$C$18,2,FALSE()),"") -> ≥ IPC | H32: =IF(F32="","","N/A") | I32: =IF(F32="","Pendiente","Manual") -> Pendiente
B33: 11 | C33: 2026 | D33: Noviembre | F33: =IFERROR(IF(OR(E33="",E32="",E32=0),"",(E33-E32)/E32),"") | G33: =IFERROR(VLOOKUP(C33,$B$14:$C$18,2,FALSE()),"") -> ≥ IPC | H33: =IF(F33="","","N/A") | I33: =IF(F33="","Pendiente","Manual") -> Pendiente
B34: 12 | C34: 2026 | D34: Diciembre | F34: =IFERROR(IF(OR(E34="",E33="",E33=0),"",(E34-E33)/E33),"") | G34: =IFERROR(VLOOKUP(C34,$B$14:$C$18,2,FALSE()),"") -> ≥ IPC | H34: =IF(F34="","","N/A") | I34: =IF(F34="","Pendiente","Manual") -> Pendiente
B35: 13 | C35: 2027 | D35: Enero | F35: =IFERROR(IF(OR(E35="",E34="",E34=0),"",(E35-E34)/E34),"") | G35: =IFERROR(VLOOKUP(C35,$B$14:$C$18,2,FALSE()),"") -> ≥ IPC | H35: =IF(F35="","","N/A") | I35: =IF(F35="","Pendiente","Manual") -> Pendiente
... B82: 60 | C82: 2030 | D82: Diciembre | F82: =IFERROR(IF(OR(E82="",E81="",E81=0),"",(E82-E81)/E81),"") | G82: =IFERROR(VLOOKUP(C82,$B$14:$C$18,2,FALSE()),"") -> ≥ IPC | H82: =IF(F82="","","N/A") | I82: =IF(F82="","Pendiente","Manual") -> Pendiente

Sheet IND-09
B2: 💰 IND-09 · RENTABILIDAD REAL DE LOS DEPÓSITOS
B3: Perspectiva: Financiera · Objetivo específico: 🏦 Crecimiento y remuneración de depósitos
B5: Fórmula | D5: Tasa promedio ponderada ahorros − IPC
B6: Descripción | D6: Asegura que la tasa de rendimiento de los depósitos supere la inflación (poder adquisitivo del ahorro).
B7: Unidad | D7: % vs IPC
B8: Tendencia objetivo | D8: Mantener
B9: Frecuencia | D9: Mensual
B10: Responsable | D10: =VLOOKUP("IND-09",Parámetros!$B$6:$F$30,5,FALSE()) -> Por definir
B12: 🎯 METAS ANUALES (editable)
B13: Año | C13: Meta | E13: Notas
B14: 2026 | C14: 0
B15: 2027 | C15: 0
B16: 2028 | C16: 0
B17: 2029 | C17: 0
B18: 2030 | C18: 0
B20: 📝 CAPTURA MENSUAL DE VARIABLES (Ene-2026 → Dic-2030)
B21: Ingrese los valores en las celdas azules. El resultado, % cumplimiento y semáforo se calculan automáticamente. Solo se habilitan los meses según la frecuencia del indicador.
B22: # | C22: Año | D22: Mes | E22: Tasa promedio ponderada ahorros (%) | F22: IPC (%) | G22: Resultado | H22: Meta año | I22: % Cumpl. | J22: Estado
B23: 1 | C23: 2026 | D23: Enero | G23: =IFERROR(IF(OR(E23="",F23=""),"",E23-F23),"") | H23: =IFERROR(VLOOKUP(C23,$B$14:$C$18,2,FALSE()),"") -> 0 | I23: =IFERROR(IF(OR(G23="",NOT(ISNUMBER(H23))),"",1-ABS(G23-H23)/MAX(ABS(H23),1)),"") | J23: =IFERROR(IF(I23="","Pendiente",IF(I23>=0.95,"Cumple",IF(I23>=0.8,"En riesgo","Crítico"))),"Pendiente") -> Pendiente
B24: 2 | C24: 2026 | D24: Febrero | G24: =IFERROR(IF(OR(E24="",F24=""),"",E24-F24),"") | H24: =IFERROR(VLOOKUP(C24,$B$14:$C$18,2,FALSE()),"") -> 0 | I24: =IFERROR(IF(OR(G24="",NOT(ISNUMBER(H24))),"",1-ABS(G24-H24)/MAX(ABS(H24),1)),"") | J24: =IFERROR(IF(I24="","Pendiente",IF(I24>=0.95,"Cumple",IF(I24>=0.8,"En riesgo","Crítico"))),"Pendiente") -> Pendiente
B25: 3 | C25: 2026 | D25: Marzo | G25: =IFERROR(IF(OR(E25="",F25=""),"",E25-F25),"") | H25: =IFERROR(VLOOKUP(C25,$B$14:$C$18,2,FALSE()),"") -> 0 | I25: =IFERROR(IF(OR(G25="",NOT(ISNUMBER(H25))),"",1-ABS(G25-H25)/MAX(ABS(H25),1)),"") | J25: =IFERROR(IF(I25="","Pendiente",IF(I25>=0.95,"Cumple",IF(I25>=0.8,"En riesgo","Crítico"))),"Pendiente") -> Pendiente
B26: 4 | C26: 2026 | D26: Abril | G26: =IFERROR(IF(OR(E26="",F26=""),"",E26-F26),"") | H26: =IFERROR(VLOOKUP(C26,$B$14:$C$18,2,FALSE()),"") -> 0 | I26: =IFERROR(IF(OR(G26="",NOT(ISNUMBER(H26))),"",1-ABS(G26-H26)/MAX(ABS(H26),1)),"") | J26: =IFERROR(IF(I26="","Pendiente",IF(I26>=0.95,"Cumple",IF(I26>=0.8,"En riesgo","Crítico"))),"Pendiente") -> Pendiente
B27: 5 | C27: 2026 | D27: Mayo | G27: =IFERROR(IF(OR(E27="",F27=""),"",E27-F27),"") | H27: =IFERROR(VLOOKUP(C27,$B$14:$C$18,2,FALSE()),"") -> 0 | I27: =IFERROR(IF(OR(G27="",NOT(ISNUMBER(H27))),"",1-ABS(G27-H27)/MAX(ABS(H27),1)),"") | J27: =IFERROR(IF(I27="","Pendiente",IF(I27>=0.95,"Cumple",IF(I27>=0.8,"En riesgo","Crítico"))),"Pendiente") -> Pendiente
B28: 6 | C28: 2026 | D28: Junio | G28: =IFERROR(IF(OR(E28="",F28=""),"",E28-F28),"") | H28: =IFERROR(VLOOKUP(C28,$B$14:$C$18,2,FALSE()),"") -> 0 | I28: =IFERROR(IF(OR(G28="",NOT(ISNUMBER(H28))),"",1-ABS(G28-H28)/MAX(ABS(H28),1)),"") | J28: =IFERROR(IF(I28="","Pendiente",IF(I28>=0.95,"Cumple",IF(I28>=0.8,"En riesgo","Crítico"))),"Pendiente") -> Pendiente
B29: 7 | C29: 2026 | D29: Julio | G29: =IFERROR(IF(OR(E29="",F29=""),"",E29-F29),"") | H29: =IFERROR(VLOOKUP(C29,$B$14:$C$18,2,FALSE()),"") -> 0 | I29: =IFERROR(IF(OR(G29="",NOT(ISNUMBER(H29))),"",1-ABS(G29-H29)/MAX(ABS(H29),1)),"") | J29: =IFERROR(IF(I29="","Pendiente",IF(I29>=0.95,"Cumple",IF(I29>=0.8,"En riesgo","Crítico"))),"Pendiente") -> Pendiente
B30: 8 | C30: 2026 | D30: Agosto | G30: =IFERROR(IF(OR(E30="",F30=""),"",E30-F30),"") | H30: =IFERROR(VLOOKUP(C30,$B$14:$C$18,2,FALSE()),"") -> 0 | I30: =IFERROR(IF(OR(G30="",NOT(ISNUMBER(H30))),"",1-ABS(G30-H30)/MAX(ABS(H30),1)),"") | J30: =IFERROR(IF(I30="","Pendiente",IF(I30>=0.95,"Cumple",IF(I30>=0.8,"En riesgo","Crítico"))),"Pendiente") -> Pendiente
B31: 9 | C31: 2026 | D31: Septiembre | G31: =IFERROR(IF(OR(E31="",F31=""),"",E31-F31),"") | H31: =IFERROR(VLOOKUP(C31,$B$14:$C$18,2,FALSE()),"") -> 0 | I31: =IFERROR(IF(OR(G31="",NOT(ISNUMBER(H31))),"",1-ABS(G31-H31)/MAX(ABS(H31),1)),"") | J31: =IFERROR(IF(I31="","Pendiente",IF(I31>=0.95,"Cumple",IF(I31>=0.8,"En riesgo","Crítico"))),"Pendiente") -> Pendiente
B32: 10 | C32: 2026 | D32: Octubre | G32: =IFERROR(IF(OR(E32="",F32=""),"",E32-F32),"") | H32: =IFERROR(VLOOKUP(C32,$B$14:$C$18,2,FALSE()),"") -> 0 | I32: =IFERROR(IF(OR(G32="",NOT(ISNUMBER(H32))),"",1-ABS(G32-H32)/MAX(ABS(H32),1)),"") | J32: =IFERROR(IF(I32="","Pendiente",IF(I32>=0.95,"Cumple",IF(I32>=0.8,"En riesgo","Crítico"))),"Pendiente") -> Pendiente
B33: 11 | C33: 2026 | D33: Noviembre | G33: =IFERROR(IF(OR(E33="",F33=""),"",E33-F33),"") | H33: =IFERROR(VLOOKUP(C33,$B$14:$C$18,2,FALSE()),"") -> 0 | I33: =IFERROR(IF(OR(G33="",NOT(ISNUMBER(H33))),"",1-ABS(G33-H33)/MAX(ABS(H33),1)),"") | J33: =IFERROR(IF(I33="","Pendiente",IF(I33>=0.95,"Cumple",IF(I33>=0.8,"En riesgo","Crítico"))),"Pendiente") -> Pendiente
B34: 12 | C34: 2026 | D34: Diciembre | G34: =IFERROR(IF(OR(E34="",F34=""),"",E34-F34),"") | H34: =IFERROR(VLOOKUP(C34,$B$14:$C$18,2,FALSE()),"") -> 0 | I34: =IFERROR(IF(OR(G34="",NOT(ISNUMBER(H34))),"",1-ABS(G34-H34)/MAX(ABS(H34),1)),"") | J34: =IFERROR(IF(I34="","Pendiente",IF(I34>=0.95,"Cumple",IF(I34>=0.8,"En riesgo","Crítico"))),"Pendiente") -> Pendiente
... B82: 60 | C82: 2030 | D82: Diciembre | G82: =IFERROR(IF(OR(E82="",F82=""),"",E82-F82),"") | H82: =IFERROR(VLOOKUP(C82,$B$14:$C$18,2,FALSE()),"") -> 0 | I82: =IFERROR(IF(OR(G82="",NOT(ISNUMBER(H82))),"",1-ABS(G82-H82)/MAX(ABS(H82),1)),"") | J82: =IFERROR(IF(I82="","Pendiente",IF(I82>=0.95,"Cumple",IF(I82>=0.8,"En riesgo","Crítico"))),"Pendiente") -> Pendiente

Sheet IND-10
B2: 💰 IND-10 · SUFICIENCIA DEL MARGEN
B3: Perspectiva: Financiera · Objetivo específico: 💎 Rentabilidad y fortalecimiento patrimonial
B5: Fórmula | D5: Margen financiero bruto ÷ Gastos operativos
B6: Descripción | D6: Evalúa la capacidad del margen financiero bruto para cubrir los gastos operativos.
B7: Unidad | D7: Veces (x)
B8: Tendencia objetivo | D8: Mantener
B9: Frecuencia | D9: Mensual
B10: Responsable | D10: =VLOOKUP("IND-10",Parámetros!$B$6:$F$30,5,FALSE()) -> Por definir
B12: 🎯 METAS ANUALES (editable)
B13: Año | C13: Meta | E13: Notas
B14: 2026 | C14: 1.2
B15: 2027 | C15: 1.2
B16: 2028 | C16: 1.2
B17: 2029 | C17: 1.2
B18: 2030 | C18: 1.2
B20: 📝 CAPTURA MENSUAL DE VARIABLES (Ene-2026 → Dic-2030)
B21: Ingrese los valores en las celdas azules. El resultado, % cumplimiento y semáforo se calculan automáticamente. Solo se habilitan los meses según la frecuencia del indicador.
B22: # | C22: Año | D22: Mes | E22: Margen financiero bruto ($) | F22: Gastos operativos ($) | G22: Resultado | H22: Meta año | I22: % Cumpl. | J22: Estado
B23: 1 | C23: 2026 | D23: Enero | G23: =IFERROR(IF(F23=0,"",E23/F23),"") | H23: =IFERROR(VLOOKUP(C23,$B$14:$C$18,2,FALSE()),"") -> 1.2 | I23: =IFERROR(IF(OR(G23="",NOT(ISNUMBER(H23))),"",1-ABS(G23-H23)/MAX(ABS(H23),1)),"") | J23: =IFERROR(IF(I23="","Pendiente",IF(I23>=0.95,"Cumple",IF(I23>=0.8,"En riesgo","Crítico"))),"Pendiente") -> Pendiente
B24: 2 | C24: 2026 | D24: Febrero | G24: =IFERROR(IF(F24=0,"",E24/F24),"") | H24: =IFERROR(VLOOKUP(C24,$B$14:$C$18,2,FALSE()),"") -> 1.2 | I24: =IFERROR(IF(OR(G24="",NOT(ISNUMBER(H24))),"",1-ABS(G24-H24)/MAX(ABS(H24),1)),"") | J24: =IFERROR(IF(I24="","Pendiente",IF(I24>=0.95,"Cumple",IF(I24>=0.8,"En riesgo","Crítico"))),"Pendiente") -> Pendiente
B25: 3 | C25: 2026 | D25: Marzo | G25: =IFERROR(IF(F25=0,"",E25/F25),"") | H25: =IFERROR(VLOOKUP(C25,$B$14:$C$18,2,FALSE()),"") -> 1.2 | I25: =IFERROR(IF(OR(G25="",NOT(ISNUMBER(H25))),"",1-ABS(G25-H25)/MAX(ABS(H25),1)),"") | J25: =IFERROR(IF(I25="","Pendiente",IF(I25>=0.95,"Cumple",IF(I25>=0.8,"En riesgo","Crítico"))),"Pendiente") -> Pendiente
B26: 4 | C26: 2026 | D26: Abril | G26: =IFERROR(IF(F26=0,"",E26/F26),"") | H26: =IFERROR(VLOOKUP(C26,$B$14:$C$18,2,FALSE()),"") -> 1.2 | I26: =IFERROR(IF(OR(G26="",NOT(ISNUMBER(H26))),"",1-ABS(G26-H26)/MAX(ABS(H26),1)),"") | J26: =IFERROR(IF(I26="","Pendiente",IF(I26>=0.95,"Cumple",IF(I26>=0.8,"En riesgo","Crítico"))),"Pendiente") -> Pendiente
B27: 5 | C27: 2026 | D27: Mayo | G27: =IFERROR(IF(F27=0,"",E27/F27),"") | H27: =IFERROR(VLOOKUP(C27,$B$14:$C$18,2,FALSE()),"") -> 1.2 | I27: =IFERROR(IF(OR(G27="",NOT(ISNUMBER(H27))),"",1-ABS(G27-H27)/MAX(ABS(H27),1)),"") | J27: =IFERROR(IF(I27="","Pendiente",IF(I27>=0.95,"Cumple",IF(I27>=0.8,"En riesgo","Crítico"))),"Pendiente") -> Pendiente
B28: 6 | C28: 2026 | D28: Junio | G28: =IFERROR(IF(F28=0,"",E28/F28),"") | H28: =IFERROR(VLOOKUP(C28,$B$14:$C$18,2,FALSE()),"") -> 1.2 | I28: =IFERROR(IF(OR(G28="",NOT(ISNUMBER(H28))),"",1-ABS(G28-H28)/MAX(ABS(H28),1)),"") | J28: =IFERROR(IF(I28="","Pendiente",IF(I28>=0.95,"Cumple",IF(I28>=0.8,"En riesgo","Crítico"))),"Pendiente") -> Pendiente
B29: 7 | C29: 2026 | D29: Julio | G29: =IFERROR(IF(F29=0,"",E29/F29),"") | H29: =IFERROR(VLOOKUP(C29,$B$14:$C$18,2,FALSE()),"") -> 1.2 | I29: =IFERROR(IF(OR(G29="",NOT(ISNUMBER(H29))),"",1-ABS(G29-H29)/MAX(ABS(H29),1)),"") | J29: =IFERROR(IF(I29="","Pendiente",IF(I29>=0.95,"Cumple",IF(I29>=0.8,"En riesgo","Crítico"))),"Pendiente") -> Pendiente
B30: 8 | C30: 2026 | D30: Agosto | G30: =IFERROR(IF(F30=0,"",E30/F30),"") | H30: =IFERROR(VLOOKUP(C30,$B$14:$C$18,2,FALSE()),"") -> 1.2 | I30: =IFERROR(IF(OR(G30="",NOT(ISNUMBER(H30))),"",1-ABS(G30-H30)/MAX(ABS(H30),1)),"") | J30: =IFERROR(IF(I30="","Pendiente",IF(I30>=0.95,"Cumple",IF(I30>=0.8,"En riesgo","Crítico"))),"Pendiente") -> Pendiente
B31: 9 | C31: 2026 | D31: Septiembre | G31: =IFERROR(IF(F31=0,"",E31/F31),"") | H31: =IFERROR(VLOOKUP(C31,$B$14:$C$18,2,FALSE()),"") -> 1.2 | I31: =IFERROR(IF(OR(G31="",NOT(ISNUMBER(H31))),"",1-ABS(G31-H31)/MAX(ABS(H31),1)),"") | J31: =IFERROR(IF(I31="","Pendiente",IF(I31>=0.95,"Cumple",IF(I31>=0.8,"En riesgo","Crítico"))),"Pendiente") -> Pendiente
B32: 10 | C32: 2026 | D32: Octubre | G32: =IFERROR(IF(F32=0,"",E32/F32),"") | H32: =IFERROR(VLOOKUP(C32,$B$14:$C$18,2,FALSE()),"") -> 1.2 | I32: =IFERROR(IF(OR(G32="",NOT(ISNUMBER(H32))),"",1-ABS(G32-H32)/MAX(ABS(H32),1)),"") | J32: =IFERROR(IF(I32="","Pendiente",IF(I32>=0.95,"Cumple",IF(I32>=0.8,"En riesgo","Crítico"))),"Pendiente") -> Pendiente
B33: 11 | C33: 2026 | D33: Noviembre | G33: =IFERROR(IF(F33=0,"",E33/F33),"") | H33: =IFERROR(VLOOKUP(C33,$B$14:$C$18,2,FALSE()),"") -> 1.2 | I33: =IFERROR(IF(OR(G33="",NOT(ISNUMBER(H33))),"",1-ABS(G33-H33)/MAX(ABS(H33),1)),"") | J33: =IFERROR(IF(I33="","Pendiente",IF(I33>=0.95,"Cumple",IF(I33>=0.8,"En riesgo","Crítico"))),"Pendiente") -> Pendiente
B34: 12 | C34: 2026 | D34: Diciembre | G34: =IFERROR(IF(F34=0,"",E34/F34),"") | H34: =IFERROR(VLOOKUP(C34,$B$14:$C$18,2,FALSE()),"") -> 1.2 | I34: =IFERROR(IF(OR(G34="",NOT(ISNUMBER(H34))),"",1-ABS(G34-H34)/MAX(ABS(H34),1)),"") | J34: =IFERROR(IF(I34="","Pendiente",IF(I34>=0.95,"Cumple",IF(I34>=0.8,"En riesgo","Crítico"))),"Pendiente") -> Pendiente
... B82: 60 | C82: 2030 | D82: Diciembre | G82: =IFERROR(IF(F82=0,"",E82/F82),"") | H82: =IFERROR(VLOOKUP(C82,$B$14:$C$18,2,FALSE()),"") -> 1.2 | I82: =IFERROR(IF(OR(G82="",NOT(ISNUMBER(H82))),"",1-ABS(G82-H82)/MAX(ABS(H82),1)),"") | J82: =IFERROR(IF(I82="","Pendiente",IF(I82>=0.95,"Cumple",IF(I82>=0.8,"En riesgo","Crítico"))),"Pendiente") -> Pendiente

Sheet IND-11
B2: 💰 IND-11 · CUMPLIMIENTO DE PAGO DE APORTES SOCIALES
B3: Perspectiva: Financiera · Objetivo específico: 💎 Rentabilidad y fortalecimiento patrimonial
B5: Fórmula | D5: Recaudo real de aportes ÷ Recaudo esperado de aportes
B6: Descripción | D6: Mide el grado de cumplimiento del recaudo mensual de aportes frente al esperado.
B7: Unidad | D7: %
B8: Tendencia objetivo | D8: Mantener
B9: Frecuencia | D9: Mensual
B10: Responsable | D10: =VLOOKUP("IND-11",Parámetros!$B$6:$F$30,5,FALSE()) -> Por definir
B12: 🎯 METAS ANUALES (editable)
B13: Año | C13: Meta | E13: Notas
B14: 2026 | C14: 0.95
B15: 2027 | C15: 0.95
B16: 2028 | C16: 0.95
B17: 2029 | C17: 0.95
B18: 2030 | C18: 0.95
B20: 📝 CAPTURA MENSUAL DE VARIABLES (Ene-2026 → Dic-2030)
B21: Ingrese los valores en las celdas azules. El resultado, % cumplimiento y semáforo se calculan automáticamente. Solo se habilitan los meses según la frecuencia del indicador.
B22: # | C22: Año | D22: Mes | E22: Recaudo real de aportes ($) | F22: Recaudo esperado de aportes ($) | G22: Resultado | H22: Meta año | I22: % Cumpl. | J22: Estado
B23: 1 | C23: 2026 | D23: Enero | G23: =IFERROR(IF(F23=0,"",E23/F23),"") | H23: =IFERROR(VLOOKUP(C23,$B$14:$C$18,2,FALSE()),"") -> 0.95 | I23: =IFERROR(IF(OR(G23="",NOT(ISNUMBER(H23))),"",1-ABS(G23-H23)/MAX(ABS(H23),1)),"") | J23: =IFERROR(IF(I23="","Pendiente",IF(I23>=0.95,"Cumple",IF(I23>=0.8,"En riesgo","Crítico"))),"Pendiente") -> Pendiente
B24: 2 | C24: 2026 | D24: Febrero | G24: =IFERROR(IF(F24=0,"",E24/F24),"") | H24: =IFERROR(VLOOKUP(C24,$B$14:$C$18,2,FALSE()),"") -> 0.95 | I24: =IFERROR(IF(OR(G24="",NOT(ISNUMBER(H24))),"",1-ABS(G24-H24)/MAX(ABS(H24),1)),"") | J24: =IFERROR(IF(I24="","Pendiente",IF(I24>=0.95,"Cumple",IF(I24>=0.8,"En riesgo","Crítico"))),"Pendiente") -> Pendiente
B25: 3 | C25: 2026 | D25: Marzo | G25: =IFERROR(IF(F25=0,"",E25/F25),"") | H25: =IFERROR(VLOOKUP(C25,$B$14:$C$18,2,FALSE()),"") -> 0.95 | I25: =IFERROR(IF(OR(G25="",NOT(ISNUMBER(H25))),"",1-ABS(G25-H25)/MAX(ABS(H25),1)),"") | J25: =IFERROR(IF(I25="","Pendiente",IF(I25>=0.95,"Cumple",IF(I25>=0.8,"En riesgo","Crítico"))),"Pendiente") -> Pendiente
B26: 4 | C26: 2026 | D26: Abril | G26: =IFERROR(IF(F26=0,"",E26/F26),"") | H26: =IFERROR(VLOOKUP(C26,$B$14:$C$18,2,FALSE()),"") -> 0.95 | I26: =IFERROR(IF(OR(G26="",NOT(ISNUMBER(H26))),"",1-ABS(G26-H26)/MAX(ABS(H26),1)),"") | J26: =IFERROR(IF(I26="","Pendiente",IF(I26>=0.95,"Cumple",IF(I26>=0.8,"En riesgo","Crítico"))),"Pendiente") -> Pendiente
B27: 5 | C27: 2026 | D27: Mayo | G27: =IFERROR(IF(F27=0,"",E27/F27),"") | H27: =IFERROR(VLOOKUP(C27,$B$14:$C$18,2,FALSE()),"") -> 0.95 | I27: =IFERROR(IF(OR(G27="",NOT(ISNUMBER(H27))),"",1-ABS(G27-H27)/MAX(ABS(H27),1)),"") | J27: =IFERROR(IF(I27="","Pendiente",IF(I27>=0.95,"Cumple",IF(I27>=0.8,"En riesgo","Crítico"))),"Pendiente") -> Pendiente
B28: 6 | C28: 2026 | D28: Junio | G28: =IFERROR(IF(F28=0,"",E28/F28),"") | H28: =IFERROR(VLOOKUP(C28,$B$14:$C$18,2,FALSE()),"") -> 0.95 | I28: =IFERROR(IF(OR(G28="",NOT(ISNUMBER(H28))),"",1-ABS(G28-H28)/MAX(ABS(H28),1)),"") | J28: =IFERROR(IF(I28="","Pendiente",IF(I28>=0.95,"Cumple",IF(I28>=0.8,"En riesgo","Crítico"))),"Pendiente") -> Pendiente
B29: 7 | C29: 2026 | D29: Julio | G29: =IFERROR(IF(F29=0,"",E29/F29),"") | H29: =IFERROR(VLOOKUP(C29,$B$14:$C$18,2,FALSE()),"") -> 0.95 | I29: =IFERROR(IF(OR(G29="",NOT(ISNUMBER(H29))),"",1-ABS(G29-H29)/MAX(ABS(H29),1)),"") | J29: =IFERROR(IF(I29="","Pendiente",IF(I29>=0.95,"Cumple",IF(I29>=0.8,"En riesgo","Crítico"))),"Pendiente") -> Pendiente
B30: 8 | C30: 2026 | D30: Agosto | G30: =IFERROR(IF(F30=0,"",E30/F30),"") | H30: =IFERROR(VLOOKUP(C30,$B$14:$C$18,2,FALSE()),"") -> 0.95 | I30: =IFERROR(IF(OR(G30="",NOT(ISNUMBER(H30))),"",1-ABS(G30-H30)/MAX(ABS(H30),1)),"") | J30: =IFERROR(IF(I30="","Pendiente",IF(I30>=0.95,"Cumple",IF(I30>=0.8,"En riesgo","Crítico"))),"Pendiente") -> Pendiente
B31: 9 | C31: 2026 | D31: Septiembre | G31: =IFERROR(IF(F31=0,"",E31/F31),"") | H31: =IFERROR(VLOOKUP(C31,$B$14:$C$18,2,FALSE()),"") -> 0.95 | I31: =IFERROR(IF(OR(G31="",NOT(ISNUMBER(H31))),"",1-ABS(G31-H31)/MAX(ABS(H31),1)),"") | J31: =IFERROR(IF(I31="","Pendiente",IF(I31>=0.95,"Cumple",IF(I31>=0.8,"En riesgo","Crítico"))),"Pendiente") -> Pendiente
B32: 10 | C32: 2026 | D32: Octubre | G32: =IFERROR(IF(F32=0,"",E32/F32),"") | H32: =IFERROR(VLOOKUP(C32,$B$14:$C$18,2,FALSE()),"") -> 0.95 | I32: =IFERROR(IF(OR(G32="",NOT(ISNUMBER(H32))),"",1-ABS(G32-H32)/MAX(ABS(H32),1)),"") | J32: =IFERROR(IF(I32="","Pendiente",IF(I32>=0.95,"Cumple",IF(I32>=0.8,"En riesgo","Crítico"))),"Pendiente") -> Pendiente
B33: 11 | C33: 2026 | D33: Noviembre | G33: =IFERROR(IF(F33=0,"",E33/F33),"") | H33: =IFERROR(VLOOKUP(C33,$B$14:$C$18,2,FALSE()),"") -> 0.95 | I33: =IFERROR(IF(OR(G33="",NOT(ISNUMBER(H33))),"",1-ABS(G33-H33)/MAX(ABS(H33),1)),"") | J33: =IFERROR(IF(I33="","Pendiente",IF(I33>=0.95,"Cumple",IF(I33>=0.8,"En riesgo","Crítico"))),"Pendiente") -> Pendiente
B34: 12 | C34: 2026 | D34: Diciembre | G34: =IFERROR(IF(F34=0,"",E34/F34),"") | H34: =IFERROR(VLOOKUP(C34,$B$14:$C$18,2,FALSE()),"") -> 0.95 | I34: =IFERROR(IF(OR(G34="",NOT(ISNUMBER(H34))),"",1-ABS(G34-H34)/MAX(ABS(H34),1)),"") | J34: =IFERROR(IF(I34="","Pendiente",IF(I34>=0.95,"Cumple",IF(I34>=0.8,"En riesgo","Crítico"))),"Pendiente") -> Pendiente
... B82: 60 | C82: 2030 | D82: Diciembre | G82: =IFERROR(IF(F82=0,"",E82/F82),"") | H82: =IFERROR(VLOOKUP(C82,$B$14:$C$18,2,FALSE()),"") -> 0.95 | I82: =IFERROR(IF(OR(G82="",NOT(ISNUMBER(H82))),"",1-ABS(G82-H82)/MAX(ABS(H82),1)),"") | J82: =IFERROR(IF(I82="","Pendiente",IF(I82>=0.95,"Cumple",IF(I82>=0.8,"En riesgo","Crítico"))),"Pendiente") -> Pendiente

Sheet IND-12
B2: 💰 IND-12 · CAPITAL INSTITUCIONAL
B3: Perspectiva: Financiera · Objetivo específico: 💎 Rentabilidad y fortalecimiento patrimonial
B5: Fórmula | D5: (Aportes amortizados + Reserva protección aportes + Excedente mes) ÷ Activo
B6: Descripción | D6: Mide la proporción del patrimonio permanente frente al total de activos.
B7: Unidad | D7: %
B8: Tendencia objetivo | D8: Mantener
B9: Frecuencia | D9: Mensual
B10: Responsable | D10: =VLOOKUP("IND-12",Parámetros!$B$6:$F$30,5,FALSE()) -> Por definir
B12: 🎯 METAS ANUALES (editable)
B13: Año | C13: Meta | E13: Notas
B14: 2026 | C14: 0.15
B15: 2027 | C15: 0.15
B16: 2028 | C16: 0.15
B17: 2029 | C17: 0.15
B18: 2030 | C18: 0.15
B20: 📝 CAPTURA MENSUAL DE VARIABLES (Ene-2026 → Dic-2030)
B21: Ingrese los valores en las celdas azules. El resultado, % cumplimiento y semáforo se calculan automáticamente. Solo se habilitan los meses según la frecuencia del indicador.
B22: # | C22: Año | D22: Mes | E22: Aportes amortizados ($) | F22: Reserva protección aportes ($) | G22: Excedente del mes ($) | H22: Activo total ($) | I22: Resultado | J22: Meta año | K22: % Cumpl. | L22: Estado
B23: 1 | C23: 2026 | D23: Enero | I23: =IFERROR(IF(H23=0,"",(E23+F23+G23)/H23),"") | J23: =IFERROR(VLOOKUP(C23,$B$14:$C$18,2,FALSE()),"") -> 0.15 | K23: =IFERROR(IF(OR(I23="",NOT(ISNUMBER(J23))),"",1-ABS(I23-J23)/MAX(ABS(J23),1)),"") | L23: =IFERROR(IF(K23="","Pendiente",IF(K23>=0.95,"Cumple",IF(K23>=0.8,"En riesgo","Crítico"))),"Pendiente") -> Pendiente
B24: 2 | C24: 2026 | D24: Febrero | I24: =IFERROR(IF(H24=0,"",(E24+F24+G24)/H24),"") | J24: =IFERROR(VLOOKUP(C24,$B$14:$C$18,2,FALSE()),"") -> 0.15 | K24: =IFERROR(IF(OR(I24="",NOT(ISNUMBER(J24))),"",1-ABS(I24-J24)/MAX(ABS(J24),1)),"") | L24: =IFERROR(IF(K24="","Pendiente",IF(K24>=0.95,"Cumple",IF(K24>=0.8,"En riesgo","Crítico"))),"Pendiente") -> Pendiente
B25: 3 | C25: 2026 | D25: Marzo | I25: =IFERROR(IF(H25=0,"",(E25+F25+G25)/H25),"") | J25: =IFERROR(VLOOKUP(C25,$B$14:$C$18,2,FALSE()),"") -> 0.15 | K25: =IFERROR(IF(OR(I25="",NOT(ISNUMBER(J25))),"",1-ABS(I25-J25)/MAX(ABS(J25),1)),"") | L25: =IFERROR(IF(K25="","Pendiente",IF(K25>=0.95,"Cumple",IF(K25>=0.8,"En riesgo","Crítico"))),"Pendiente") -> Pendiente
B26: 4 | C26: 2026 | D26: Abril | I26: =IFERROR(IF(H26=0,"",(E26+F26+G26)/H26),"") | J26: =IFERROR(VLOOKUP(C26,$B$14:$C$18,2,FALSE()),"") -> 0.15 | K26: =IFERROR(IF(OR(I26="",NOT(ISNUMBER(J26))),"",1-ABS(I26-J26)/MAX(ABS(J26),1)),"") | L26: =IFERROR(IF(K26="","Pendiente",IF(K26>=0.95,"Cumple",IF(K26>=0.8,"En riesgo","Crítico"))),"Pendiente") -> Pendiente
B27: 5 | C27: 2026 | D27: Mayo | I27: =IFERROR(IF(H27=0,"",(E27+F27+G27)/H27),"") | J27: =IFERROR(VLOOKUP(C27,$B$14:$C$18,2,FALSE()),"") -> 0.15 | K27: =IFERROR(IF(OR(I27="",NOT(ISNUMBER(J27))),"",1-ABS(I27-J27)/MAX(ABS(J27),1)),"") | L27: =IFERROR(IF(K27="","Pendiente",IF(K27>=0.95,"Cumple",IF(K27>=0.8,"En riesgo","Crítico"))),"Pendiente") -> Pendiente
B28: 6 | C28: 2026 | D28: Junio | I28: =IFERROR(IF(H28=0,"",(E28+F28+G28)/H28),"") | J28: =IFERROR(VLOOKUP(C28,$B$14:$C$18,2,FALSE()),"") -> 0.15 | K28: =IFERROR(IF(OR(I28="",NOT(ISNUMBER(J28))),"",1-ABS(I28-J28)/MAX(ABS(J28),1)),"") | L28: =IFERROR(IF(K28="","Pendiente",IF(K28>=0.95,"Cumple",IF(K28>=0.8,"En riesgo","Crítico"))),"Pendiente") -> Pendiente
B29: 7 | C29: 2026 | D29: Julio | I29: =IFERROR(IF(H29=0,"",(E29+F29+G29)/H29),"") | J29: =IFERROR(VLOOKUP(C29,$B$14:$C$18,2,FALSE()),"") -> 0.15 | K29: =IFERROR(IF(OR(I29="",NOT(ISNUMBER(J29))),"",1-ABS(I29-J29)/MAX(ABS(J29),1)),"") | L29: =IFERROR(IF(K29="","Pendiente",IF(K29>=0.95,"Cumple",IF(K29>=0.8,"En riesgo","Crítico"))),"Pendiente") -> Pendiente
B30: 8 | C30: 2026 | D30: Agosto | I30: =IFERROR(IF(H30=0,"",(E30+F30+G30)/H30),"") | J30: =IFERROR(VLOOKUP(C30,$B$14:$C$18,2,FALSE()),"") -> 0.15 | K30: =IFERROR(IF(OR(I30="",NOT(ISNUMBER(J30))),"",1-ABS(I30-J30)/MAX(ABS(J30),1)),"") | L30: =IFERROR(IF(K30="","Pendiente",IF(K30>=0.95,"Cumple",IF(K30>=0.8,"En riesgo","Crítico"))),"Pendiente") -> Pendiente
B31: 9 | C31: 2026 | D31: Septiembre | I31: =IFERROR(IF(H31=0,"",(E31+F31+G31)/H31),"") | J31: =IFERROR(VLOOKUP(C31,$B$14:$C$18,2,FALSE()),"") -> 0.15 | K31: =IFERROR(IF(OR(I31="",NOT(ISNUMBER(J31))),"",1-ABS(I31-J31)/MAX(ABS(J31),1)),"") | L31: =IFERROR(IF(K31="","Pendiente",IF(K31>=0.95,"Cumple",IF(K31>=0.8,"En riesgo","Crítico"))),"Pendiente") -> Pendiente
B32: 10 | C32: 2026 | D32: Octubre | I32: =IFERROR(IF(H32=0,"",(E32+F32+G32)/H32),"") | J32: =IFERROR(VLOOKUP(C32,$B$14:$C$18,2,FALSE()),"") -> 0.15 | K32: =IFERROR(IF(OR(I32="",NOT(ISNUMBER(J32))),"",1-ABS(I32-J32)/MAX(ABS(J32),1)),"") | L32: =IFERROR(IF(K32="","Pendiente",IF(K32>=0.95,"Cumple",IF(K32>=0.8,"En riesgo","Crítico"))),"Pendiente") -> Pendiente
B33: 11 | C33: 2026 | D33: Noviembre | I33: =IFERROR(IF(H33=0,"",(E33+F33+G33)/H33),"") | J33: =IFERROR(VLOOKUP(C33,$B$14:$C$18,2,FALSE()),"") -> 0.15 | K33: =IFERROR(IF(OR(I33="",NOT(ISNUMBER(J33))),"",1-ABS(I33-J33)/MAX(ABS(J33),1)),"") | L33: =IFERROR(IF(K33="","Pendiente",IF(K33>=0.95,"Cumple",IF(K33>=0.8,"En riesgo","Crítico"))),"Pendiente") -> Pendiente
B34: 12 | C34: 2026 | D34: Diciembre | I34: =IFERROR(IF(H34=0,"",(E34+F34+G34)/H34),"") | J34: =IFERROR(VLOOKUP(C34,$B$14:$C$18,2,FALSE()),"") -> 0.15 | K34: =IFERROR(IF(OR(I34="",NOT(ISNUMBER(J34))),"",1-ABS(I34-J34)/MAX(ABS(J34),1)),"") | L34: =IFERROR(IF(K34="","Pendiente",IF(K34>=0.95,"Cumple",IF(K34>=0.8,"En riesgo","Crítico"))),"Pendiente") -> Pendiente
... B82: 60 | C82: 2030 | D82: Diciembre | I82: =IFERROR(IF(H82=0,"",(E82+F82+G82)/H82),"") | J82: =IFERROR(VLOOKUP(C82,$B$14:$C$18,2,FALSE()),"") -> 0.15 | K82: =IFERROR(IF(OR(I82="",NOT(ISNUMBER(J82))),"",1-ABS(I82-J82)/MAX(ABS(J82),1)),"") | L82: =IFERROR(IF(K82="","Pendiente",IF(K82>=0.95,"Cumple",IF(K82>=0.8,"En riesgo","Crítico"))),"Pendiente") -> Pendiente

Sheet IND-13
B2: 💰 IND-13 · ROE
B3: Perspectiva: Financiera · Objetivo específico: 💎 Rentabilidad y fortalecimiento patrimonial
B5: Fórmula | D5: Excedente ÷ Patrimonio
B6: Descripción | D6: Rentabilidad sobre el patrimonio.
B7: Unidad | D7: %
B8: Tendencia objetivo | D8: Mantener
B9: Frecuencia | D9: Mensual
B10: Responsable | D10: =VLOOKUP("IND-13",Parámetros!$B$6:$F$30,5,FALSE()) -> Por definir
B12: 🎯 METAS ANUALES (editable)
B13: Año | C13: Meta | E13: Notas
B14: 2026 | C14: > IPC
B15: 2027 | C15: > IPC
B16: 2028 | C16: > IPC
B17: 2029 | C17: > IPC
B18: 2030 | C18: > IPC
B20: 📝 CAPTURA MENSUAL DE VARIABLES (Ene-2026 → Dic-2030)
B21: Ingrese los valores en las celdas azules. El resultado, % cumplimiento y semáforo se calculan automáticamente. Solo se habilitan los meses según la frecuencia del indicador.
B22: # | C22: Año | D22: Mes | E22: Excedente ($) | F22: Patrimonio ($) | G22: Resultado | H22: Meta año | I22: % Cumpl. | J22: Estado
B23: 1 | C23: 2026 | D23: Enero | G23: =IFERROR(IF(F23=0,"",E23/F23),"") | H23: =IFERROR(VLOOKUP(C23,$B$14:$C$18,2,FALSE()),"") -> > IPC | I23: =IF(G23="","","N/A") | J23: =IF(G23="","Pendiente","Manual") -> Pendiente
B24: 2 | C24: 2026 | D24: Febrero | G24: =IFERROR(IF(F24=0,"",E24/F24),"") | H24: =IFERROR(VLOOKUP(C24,$B$14:$C$18,2,FALSE()),"") -> > IPC | I24: =IF(G24="","","N/A") | J24: =IF(G24="","Pendiente","Manual") -> Pendiente
B25: 3 | C25: 2026 | D25: Marzo | G25: =IFERROR(IF(F25=0,"",E25/F25),"") | H25: =IFERROR(VLOOKUP(C25,$B$14:$C$18,2,FALSE()),"") -> > IPC | I25: =IF(G25="","","N/A") | J25: =IF(G25="","Pendiente","Manual") -> Pendiente
B26: 4 | C26: 2026 | D26: Abril | G26: =IFERROR(IF(F26=0,"",E26/F26),"") | H26: =IFERROR(VLOOKUP(C26,$B$14:$C$18,2,FALSE()),"") -> > IPC | I26: =IF(G26="","","N/A") | J26: =IF(G26="","Pendiente","Manual") -> Pendiente
B27: 5 | C27: 2026 | D27: Mayo | G27: =IFERROR(IF(F27=0,"",E27/F27),"") | H27: =IFERROR(VLOOKUP(C27,$B$14:$C$18,2,FALSE()),"") -> > IPC | I27: =IF(G27="","","N/A") | J27: =IF(G27="","Pendiente","Manual") -> Pendiente
B28: 6 | C28: 2026 | D28: Junio | G28: =IFERROR(IF(F28=0,"",E28/F28),"") | H28: =IFERROR(VLOOKUP(C28,$B$14:$C$18,2,FALSE()),"") -> > IPC | I28: =IF(G28="","","N/A") | J28: =IF(G28="","Pendiente","Manual") -> Pendiente
B29: 7 | C29: 2026 | D29: Julio | G29: =IFERROR(IF(F29=0,"",E29/F29),"") | H29: =IFERROR(VLOOKUP(C29,$B$14:$C$18,2,FALSE()),"") -> > IPC | I29: =IF(G29="","","N/A") | J29: =IF(G29="","Pendiente","Manual") -> Pendiente
B30: 8 | C30: 2026 | D30: Agosto | G30: =IFERROR(IF(F30=0,"",E30/F30),"") | H30: =IFERROR(VLOOKUP(C30,$B$14:$C$18,2,FALSE()),"") -> > IPC | I30: =IF(G30="","","N/A") | J30: =IF(G30="","Pendiente","Manual") -> Pendiente
B31: 9 | C31: 2026 | D31: Septiembre | G31: =IFERROR(IF(F31=0,"",E31/F31),"") | H31: =IFERROR(VLOOKUP(C31,$B$14:$C$18,2,FALSE()),"") -> > IPC | I31: =IF(G31="","","N/A") | J31: =IF(G31="","Pendiente","Manual") -> Pendiente
B32: 10 | C32: 2026 | D32: Octubre | G32: =IFERROR(IF(F32=0,"",E32/F32),"") | H32: =IFERROR(VLOOKUP(C32,$B$14:$C$18,2,FALSE()),"") -> > IPC | I32: =IF(G32="","","N/A") | J32: =IF(G32="","Pendiente","Manual") -> Pendiente
B33: 11 | C33: 2026 | D33: Noviembre | G33: =IFERROR(IF(F33=0,"",E33/F33),"") | H33: =IFERROR(VLOOKUP(C33,$B$14:$C$18,2,FALSE()),"") -> > IPC | I33: =IF(G33="","","N/A") | J33: =IF(G33="","Pendiente","Manual") -> Pendiente
